Workbook
Name Format: #REF!
Name Header: #REF!
Name RawData: 'ALTA 20242025'!$A$2:$DI$195

Sheet AE GF  (2)
D2: J (Ficha técnica) | E2: P3 (Permiso circulación) | AT2: CALCULOS GLOBAL OMNIUM | BD2: CALCULOS GLOBAL FACTOR
B3: ID CAE | C3: Matricula | D3: TIPO VEHÍCULO | E3: COMBUSTIBLE | F3: Columna4 | G3: Columna5 | H3: Contrato | I3: Acta de Entrega | J3: Acta Devolución | K3: BAJA | L3: Ficha Técnica | M3: Permiso de Circulación | N3: IVTM | O3: Compañía/Proveedor | P3: Cod.Tipo Contrato | Q3: Tipo Contrato | R3: Situación Contrato | S3: f Vig Inicio | T3: F.Vig.Final | U3: Tiempo Prop | V3: Año | W3: Cod.Sit.Contrato | X3: Combustible2 | Y3: Marca | Z3: Modelo/Versión | AA3: Cod.Sociedad | AB3: Sociedad | AC3: Ceco.Imput | AD3: Columna1 | AE3: Matricula nueva | AF3: Marca2 | AG3: Modelo/Versión3 | AH3: Combustible4 | AI3: Ceco | AJ3: Renov. Flota | AK3: Fecha Alta | AL3: Columna3 | AM3: Cod.Sociedad5 | AN3: Pedido | AO3: Sociedad6 | AP3: Ceco imputado | AQ3: Factura | AR3: Comunidad Autonoma | AS3: CHASIS/Bastidor | AT3: CVA | AU3: F | AV3: CVN | AW3: L | AX3: AE | AY3: Columna2 | AZ3: Vacias | BA3: Tipo vehículo2 | BB3: Tipo combustible | BC3: ID CAE2 | BD3: CVA2 | BE3: f2 | BF3: CVN2 | BG3: L2 | BH3: AE [kWh] | BI3: Comprobación | BJ3: Comprobación 2 | BK3: f23 | BL3: CVN22 | BM3: L23
A4: 1 | B4: CAE500001 | C4: 9853KXP | D4: M1 | E4: GASOLINA | F4: GASOLINA | G4: M1 | H4: X | I4: X | J4: X | L4: X | M4: X | O4: AYVENS | P4: 3 | Q4: ALQUILER | R4: DEVUELTO | S4: 45286 | T4: 45322 | U4: 36 | V4: 2024 | W4: 7 | X4: DIESEL | Y4: PEUGEOT | Z4: 208 | AA4: 1021 | AB4: MEDICION AVANZADA CONTAD. | AC4: 357712 | AD4: 1 | AE4: 0696MWT | AF4: RENAULT | AG4: KANGOO VAN E-TECH ELECTRIC | AH4: ELECTRICO | AI4: 357107 | AJ4: 2024 | AK4: 45625 | AL4: 0 | AM4: 1021 | AN4: 4500426762 | AO4: MEDICION AVANZADA CONTAD. | AQ4: X | AR4: COMUNIDAD VALENCIANA | AS4: VF1RFK00273824834 | AT4: 5.1 | AU4: 10 | AV4: 17.3 | AW4: 13073 | AX4: 4405.601 | AY4: M1 | AZ4: CORRECTO ALQUILER | BA4: =+IF(Tabla467824[[#This Row],[TIPO VEHÍCULO]]=Tabla467824[[#This Row],[Columna2]], "IGUAL", "DISTINTO") -> IGUAL | BB4: =+IF(Tabla467824[[#This Row],[Columna4]]=Tabla467824[[#This Row],[Combustible2]], "IGUAL", "DISTINTO") -> DISTINTO | BC4: CAE500001 | BD4: {=IFERROR(INDEX('[1]Anexos FICHA TRA050'!$D$27:$D$44, MATCH(Tabla467824[[#This Row],[Columna5]]&Tabla467824[[#This Row],[Columna4]], '[1]Anexos FICHA TRA050'!$E$27:$E$44&'[1]Anexos FICHA TRA050'!$F$27:$F$44, 0)), "")} -> 7.89 | BE4: =IFERROR(INDEX('[1]Anexos FICHA TRA050'!$B$4:$B$7, MATCH(Tabla467824[[#This Row],[Columna4]], '[1]Anexos FICHA TRA050'!$C$4:$C$7, 0)), "") -> 9.19 | BF4: =IFERROR(INDEX('[1]Anexos FICHA TRA050'!$C$14:$C$22, MATCH(Tabla467824[[#This Row],[Columna5]], '[1]Anexos FICHA TRA050'!$D$14:$D$22, 0)), "") -> 17.92 | BG4: =IFERROR(INDEX('[1]Anexos FICHA TRA050'!$C$49:$C$54, MATCH(Tabla467824[[#This Row],[Columna5]], '[1]Anexos FICHA TRA050'!$D$49:$D$54, 0)), "") -> 13073 | BH4: =+(((Tabla467824[[#This Row],[CVA2]]*Tabla467824[[#This Row],[f2]])-Tabla467824[[#This Row],[CVN2]])/100)*Tabla467824[[#This Row],[L2]] -> 7136.433 | BK4: =+IF(Tabla467824[[#This Row],[F]]=Tabla467824[[#This Row],[f2]], "IGUAL", "DISTINTO") -> DISTINTO | BL4: =+IF(Tabla467824[[#This Row],[CVN]]=Tabla467824[[#This Row],[CVN2]], "IGUAL", "DISTINTO") -> DISTINTO | BM4: =+IF(Tabla467824[[#This Row],[L]]=Tabla467824[[#This Row],[L2]], "IGUAL", "DISTINTO") -> IGUAL
A5: 2 | B5: CAE500002 | C5: 3483KWB | D5: M1 | E5: DIESEL | F5: DIESEL | G5: M1 | H5: X | I5: X | J5: X | L5: X | M5: X | O5: AYVENS | P5: 3 | Q5: ALQUILER | R5: DEVUELTO | S5: 45282 | T5: 45393 | U5: 111 | V5: 2024 | W5: 7 | X5: DIESEL | Y5: PEUGEOT | Z5: 208 | AA5: 1021 | AB5: MEDICION AVANZADA CONTAD. | AC5: 357712 | AD5: 2 | AE5: 0699MWT | AF5: RENAULT | AG5: KANGOO VAN E-TECH ELECTRIC | AH5: ELECTRICO | AI5: 357107 | AJ5: 2024 | AK5: 45625 | AL5: 0 | AM5: 1021 | AN5: 4500426781 | AO5: MEDICION AVANZADA CONTAD. | AQ5: X | AR5: COMUNIDAD VALENCIANA | AS5: VF1RFK00473824835 | AT5: 5.1 | AU5: 10 | AV5: 17.3 | AW5: 13073 | AX5: 4405.601 | AY5: M1 | AZ5: CORRECTO ALQUILER | BA5: =+IF(Tabla467824[[#This Row],[TIPO VEHÍCULO]]=Tabla467824[[#This Row],[Columna2]], "IGUAL", "DISTINTO") -> IGUAL | BB5: =+IF(Tabla467824[[#This Row],[Columna4]]=Tabla467824[[#This Row],[Combustible2]], "IGUAL", "DISTINTO") -> IGUAL | BC5: CAE500002 | BD5: {=IFERROR(INDEX('[1]Anexos FICHA TRA050'!$D$27:$D$44, MATCH(Tabla467824[[#This Row],[Columna5]]&Tabla467824[[#This Row],[Columna4]], '[1]Anexos FICHA TRA050'!$E$27:$E$44&'[1]Anexos FICHA TRA050'!$F$27:$F$44, 0)), "")} -> 6.99 | BE5: =IFERROR(INDEX('[1]Anexos FICHA TRA050'!$B$4:$B$7, MATCH(Tabla467824[[#This Row],[Columna4]], '[1]Anexos FICHA TRA050'!$C$4:$C$7, 0)), "") -> 10 | BF5: =IFERROR(INDEX('[1]Anexos FICHA TRA050'!$C$14:$C$22, MATCH(Tabla467824[[#This Row],[Columna5]], '[1]Anexos FICHA TRA050'!$D$14:$D$22, 0)), "") -> 17.92 | BG5: =IFERROR(INDEX('[1]Anexos FICHA TRA050'!$C$49:$C$54, MATCH(Tabla467824[[#This Row],[Columna5]], '[1]Anexos FICHA TRA050'!$D$49:$D$54, 0)), "") -> 13073 | BH5: =+(((Tabla467824[[#This Row],[CVA2]]*Tabla467824[[#This Row],[f2]])-Tabla467824[[#This Row],[CVN2]])/100)*Tabla467824[[#This Row],[L2]] -> 6795.3454 | BK5: =+IF(Tabla467824[[#This Row],[F]]=Tabla467824[[#This Row],[f2]], "IGUAL", "DISTINTO") -> IGUAL | BL5: =+IF(Tabla467824[[#This Row],[CVN]]=Tabla467824[[#This Row],[CVN2]], "IGUAL", "DISTINTO") -> DISTINTO | BM5: =+IF(Tabla467824[[#This Row],[L]]=Tabla467824[[#This Row],[L2]], "IGUAL", "DISTINTO") -> IGUAL
A6: 3 | B6: CAE500003 | C6: 0041LWY | D6: M1 | E6: DIESEL | F6: DIESEL | G6: M1 | H6: X | J6: X | L6: X | M6: X | O6: AYVENS | P6: 3 | Q6: ALQUILER | R6: DEVUELTO | S6: 45202 | T6: 45259 | U6: 57 | V6: 2023 | W6: 7 | X6: DIESEL | Y6: PEUGEOT | Z6: 208 100 CV | AA6: 1505 | AB6: CGAC | AC6: 355589 | AD6: 1 | AE6: 1255MJM | AF6: PEUGEOT | AG6: E-EXPERT PRO 100 KW | AH6: ELECTRICO | AI6: 725455 | AJ6: 2023 | AK6: 45133 | AL6: 0 | AM6: 1505 | AN6: 4500370218 | AO6: CGAC | AQ6: X | AR6: CATALUÑA | AS6: VF3V1ZKXZPZ005196 | AT6: 5.1 | AU6: 10 | AV6: 28.2 | AW6: 13073 | AX6: 2980.644 | AY6: M1 | AZ6: CORRECTO ALQUILER | BA6: =+IF(Tabla467824[[#This Row],[TIPO VEHÍCULO]]=Tabla467824[[#This Row],[Columna2]], "IGUAL", "DISTINTO") -> IGUAL | BB6: =+IF(Tabla467824[[#This Row],[Columna4]]=Tabla467824[[#This Row],[Combustible2]], "IGUAL", "DISTINTO") -> IGUAL | BC6: CAE500003 | BD6: {=IFERROR(INDEX('[1]Anexos FICHA TRA050'!$D$27:$D$44, MATCH(Tabla467824[[#This Row],[Columna5]]&Tabla467824[[#This Row],[Columna4]], '[1]Anexos FICHA TRA050'!$E$27:$E$44&'[1]Anexos FICHA TRA050'!$F$27:$F$44, 0)), "")} -> 6.99 | BE6: =IFERROR(INDEX('[1]Anexos FICHA TRA050'!$B$4:$B$7, MATCH(Tabla467824[[#This Row],[Columna4]], '[1]Anexos FICHA TRA050'!$C$4:$C$7, 0)), "") -> 10 | BF6: =IFERROR(INDEX('[1]Anexos FICHA TRA050'!$C$14:$C$22, MATCH(Tabla467824[[#This Row],[Columna5]], '[1]Anexos FICHA TRA050'!$D$14:$D$22, 0)), "") -> 17.92 | BG6: =IFERROR(INDEX('[1]Anexos FICHA TRA050'!$C$49:$C$54, MATCH(Tabla467824[[#This Row],[Columna5]], '[1]Anexos FICHA TRA050'!$D$49:$D$54, 0)), "") -> 13073 | BH6: =+(((Tabla467824[[#This Row],[CVA2]]*Tabla467824[[#This Row],[f2]])-Tabla467824[[#This Row],[CVN2]])/100)*Tabla467824[[#This Row],[L2]] -> 6795.3454 | BK6: =+IF(Tabla467824[[#This Row],[F]]=Tabla467824[[#This Row],[f2]], "IGUAL", "DISTINTO") -> IGUAL | BL6: =+IF(Tabla467824[[#This Row],[CVN]]=Tabla467824[[#This Row],[CVN2]], "IGUAL", "DISTINTO") -> DISTINTO | BM6: =+IF(Tabla467824[[#This Row],[L]]=Tabla467824[[#This Row],[L2]], "IGUAL", "DISTINTO") -> IGUAL
A7: 4 | B7: CAE500004 | C7: 5713LWX | D7: M1 | E7: DIESEL | F7: DIESEL | G7: M1 | H7: X | I7: X | J7: X | L7: X | M7: X | O7: AYVENS | P7: 3 | Q7: ALQUILER | R7: DEVUELTO | S7: 45202 | T7: 45261 | U7: 59 | V7: 2023 | W7: 7 | X7: DIESEL | Y7: PEUGEOT | Z7: 208 100 CV | AA7: 1505 | AB7: CGAC | AC7: 355589 | AD7: 2 | AE7: 2120MFK | AF7: RENAULT | AG7: KANGOO VAN E-TECH | AH7: ELECTRICO | AI7: 725465 | AJ7: 2023 | AK7: 44994 | AL7: 0 | AM7: 1505 | AN7: 4500351521 | AO7: CGAC | AQ7: X | AR7: CATALUÑA | AS7: VF1RFK00970687019 | AT7: 5.1 | AU7: 10 | AV7: 17.3 | AW7: 13073 | AX7: 4405.601 | AY7: M1 | AZ7: CORRECTO ALQUILER | BA7: =+IF(Tabla467824[[#This Row],[TIPO VEHÍCULO]]=Tabla467824[[#This Row],[Columna2]], "IGUAL", "DISTINTO") -> IGUAL | BB7: =+IF(Tabla467824[[#This Row],[Columna4]]=Tabla467824[[#This Row],[Combustible2]], "IGUAL", "DISTINTO") -> IGUAL | BC7: CAE500004 | BD7: {=IFERROR(INDEX('[1]Anexos FICHA TRA050'!$D$27:$D$44, MATCH(Tabla467824[[#This Row],[Columna5]]&Tabla467824[[#This Row],[Columna4]], '[1]Anexos FICHA TRA050'!$E$27:$E$44&'[1]Anexos FICHA TRA050'!$F$27:$F$44, 0)), "")} -> 6.99 | BE7: =IFERROR(INDEX('[1]Anexos FICHA TRA050'!$B$4:$B$7, MATCH(Tabla467824[[#This Row],[Columna4]], '[1]Anexos FICHA TRA050'!$C$4:$C$7, 0)), "") -> 10 | BF7: =IFERROR(INDEX('[1]Anexos FICHA TRA050'!$C$14:$C$22, MATCH(Tabla467824[[#This Row],[Columna5]], '[1]Anexos FICHA TRA050'!$D$14:$D$22, 0)), "") -> 17.92 | BG7: =IFERROR(INDEX('[1]Anexos FICHA TRA050'!$C$49:$C$54, MATCH(Tabla467824[[#This Row],[Columna5]], '[1]Anexos FICHA TRA050'!$D$49:$D$54, 0)), "") -> 13073 | BH7: =+(((Tabla467824[[#This Row],[CVA2]]*Tabla467824[[#This Row],[f2]])-Tabla467824[[#This Row],[CVN2]])/100)*Tabla467824[[#This Row],[L2]] -> 6795.3454 | BK7: =+IF(Tabla467824[[#This Row],[F]]=Tabla467824[[#This Row],[f2]], "IGUAL", "DISTINTO") -> IGUAL | BL7: =+IF(Tabla467824[[#This Row],[CVN]]=Tabla467824[[#This Row],[CVN2]], "IGUAL", "DISTINTO") -> DISTINTO | BM7: =+IF(Tabla467824[[#This Row],[L]]=Tabla467824[[#This Row],[L2]], "IGUAL", "DISTINTO") -> IGUAL
A8: 5 | B8: CAE500005 | C8: 5056LWD | D8: M1 | E8: DIESEL | F8: DIESEL | G8: M1 | H8: X | J8: X | L8: X | M8: X | O8: AYVENS | P8: 3 | Q8: ALQUILER | R8: DEVUELTO | S8: 45397 | T8: 45414 | U8: 17 | V8: 2024 | W8: 7 | X8: DIESEL | Y8: PEUGEOT | Z8: 208 100 CV | AA8: 1001 | AB8: AVSA | AC8: 201347 | AD8: 1 | AE8: 2788MXG | AF8: RENAULT | AG8: KANGOO VAN E-TECH ELECTRIC | AH8: ELECTRICO | AI8: 201420 | AJ8: 2024 | AK8: 45645 | AL8: 0 | AM8: 1001 | AN8: 4500426876 | AO8: AVSA | AQ8: X | AR8: COMUNIDAD VALENCIANA | AS8: VF1RFK00273934296 | AT8: 5.1 | AU8: 10 | AV8: 17.3 | AW8: 13073 | AX8: 4405.601 | AY8: M1 | AZ8: CORRECTO ALQUILER | BA8: =+IF(Tabla467824[[#This Row],[TIPO VEHÍCULO]]=Tabla467824[[#This Row],[Columna2]], "IGUAL", "DISTINTO") -> IGUAL | BB8: =+IF(Tabla467824[[#This Row],[Columna4]]=Tabla467824[[#This Row],[Combustible2]], "IGUAL", "DISTINTO") -> IGUAL | BC8: CAE500005 | BD8: {=IFERROR(INDEX('[1]Anexos FICHA TRA050'!$D$27:$D$44, MATCH(Tabla467824[[#This Row],[Columna5]]&Tabla467824[[#This Row],[Columna4]], '[1]Anexos FICHA TRA050'!$E$27:$E$44&'[1]Anexos FICHA TRA050'!$F$27:$F$44, 0)), "")} -> 6.99 | BE8: =IFERROR(INDEX('[1]Anexos FICHA TRA050'!$B$4:$B$7, MATCH(Tabla467824[[#This Row],[Columna4]], '[1]Anexos FICHA TRA050'!$C$4:$C$7, 0)), "") -> 10 | BF8: =IFERROR(INDEX('[1]Anexos FICHA TRA050'!$C$14:$C$22, MATCH(Tabla467824[[#This Row],[Columna5]], '[1]Anexos FICHA TRA050'!$D$14:$D$22, 0)), "") -> 17.92 | BG8: =IFERROR(INDEX('[1]Anexos FICHA TRA050'!$C$49:$C$54, MATCH(Tabla467824[[#This Row],[Columna5]], '[1]Anexos FICHA TRA050'!$D$49:$D$54, 0)), "") -> 13073 | BH8: =+(((Tabla467824[[#This Row],[CVA2]]*Tabla467824[[#This Row],[f2]])-Tabla467824[[#This Row],[CVN2]])/100)*Tabla467824[[#This Row],[L2]] -> 6795.3454 | BK8: =+IF(Tabla467824[[#This Row],[F]]=Tabla467824[[#This Row],[f2]], "IGUAL", "DISTINTO") -> IGUAL | BL8: =+IF(Tabla467824[[#This Row],[CVN]]=Tabla467824[[#This Row],[CVN2]], "IGUAL", "DISTINTO") -> DISTINTO | BM8: =+IF(Tabla467824[[#This Row],[L]]=Tabla467824[[#This Row],[L2]], "IGUAL", "DISTINTO") -> IGUAL
A9: 6 | B9: CAE500006 | C9: 0370LXS | D9: N1 | E9: DIESEL | F9: DIESEL | G9: N1 | H9: X | J9: X | L9: X | M9: X | O9: TLM | P9: 3 | Q9: ALQUILER | R9: DEVUELTO | S9: 45447 | T9: 45657 | U9: 210 | V9: 2024 | W9: 7 | X9: DIESEL | Y9: PEUGEOT | Z9: BOXER L2 H2 140 CV | AA9: 1066 | AB9: CANALIZ. CIVILES S.A. | AC9: 10669101 | AD9: 1 | AE9: 8651MWT | AF9: RENAULT | AG9: KANGOO VAN E-TECH ELECTRIC | AH9: ELECTRICO | AI9: 10669120 | AJ9: 2024 | AK9: 45625 | AL9: 0 | AM9: 1066 | AN9: 4500426872 | AO9: CANALIZ. CIVILES S.A. | AQ9: X | AR9: COMUNIDAD VALENCIANA | AS9: VF1RFK00073824833 | AT9: 5.6 | AU9: 10 | AV9: 17.3 | AW9: 15815 | AX9: 6120.405 | AY9: N1 | AZ9: CORRECTO ALQUILER | BA9: =+IF(Tabla467824[[#This Row],[TIPO VEHÍCULO]]=Tabla467824[[#This Row],[Columna2]], "IGUAL", "DISTINTO") -> IGUAL | BB9: =+IF(Tabla467824[[#This Row],[Columna4]]=Tabla467824[[#This Row],[Combustible2]], "IGUAL", "DISTINTO") -> IGUAL | BC9: CAE500006 | BD9: {=IFERROR(INDEX('[1]Anexos FICHA TRA050'!$D$27:$D$44, MATCH(Tabla467824[[#This Row],[Columna5]]&Tabla467824[[#This Row],[Columna4]], '[1]Anexos FICHA TRA050'!$E$27:$E$44&'[1]Anexos FICHA TRA050'!$F$27:$F$44, 0)), "")} -> 5.63 | BE9: =IFERROR(INDEX('[1]Anexos FICHA TRA050'!$B$4:$B$7, MATCH(Tabla467824[[#This Row],[Columna4]], '[1]Anexos FICHA TRA050'!$C$4:$C$7, 0)), "") -> 10 | BF9: =IFERROR(INDEX('[1]Anexos FICHA TRA050'!$C$14:$C$22, MATCH(Tabla467824[[#This Row],[Columna5]], '[1]Anexos FICHA TRA050'!$D$14:$D$22, 0)), "") -> 20.84 | BG9: =IFERROR(INDEX('[1]Anexos FICHA TRA050'!$C$49:$C$54, MATCH(Tabla467824[[#This Row],[Columna5]], '[1]Anexos FICHA TRA050'!$D$49:$D$54, 0)), "") -> 15815 | BH9: =+(((Tabla467824[[#This Row],[CVA2]]*Tabla467824[[#This Row],[f2]])-Tabla467824[[#This Row],[CVN2]])/100)*Tabla467824[[#This Row],[L2]] -> 5607.999 | BK9: =+IF(Tabla467824[[#This Row],[F]]=Tabla467824[[#This Row],[f2]], "IGUAL", "DISTINTO") -> IGUAL | BL9: =+IF(Tabla467824[[#This Row],[CVN]]=Tabla467824[[#This Row],[CVN2]], "IGUAL", "DISTINTO") -> DISTINTO | BM9: =+IF(Tabla467824[[#This Row],[L]]=Tabla467824[[#This Row],[L2]], "IGUAL", "DISTINTO") -> IGUAL
A10: 7 | B10: CAE500007 | C10: 1865LDL | D10: M1 | E10: DIESEL | F10: DIESEL | G10: M1 | H10: X | I10: X | J10: X | L10: X | M10: X | O10: AYVENS | P10: 3 | Q10: ALQUILER | R10: DEVUELTO | S10: 45282 | T10: 45321 | U10: 39 | V10: 2024 | W10: 7 | X10: DIESEL | Y10: CITROEN | Z10: C3 | AA10: 1021 | AB10: MEDICION AVANZADA CONTAD. | AC10: 357712 | AD10: 3 | AE10: 0695MWT | AF10: RENAULT | AG10: KANGOO VAN E-TECH ELECTRIC | AH10: ELECTRICO | AI10: 357706 | AJ10: 2024 | AK10: 45625 | AL10: 0 | AM10: 1021 | AN10: 4500426841 | AO10: MEDICION AVANZADA CONTAD. | AQ10: X | AR10: COMUNIDAD VALENCIANA | AS10: VF1RFK00773824845 | AT10: 5.1 | AU10: 10 | AV10: 17.3 | AW10: 13073 | AX10: 4405.601 | AY10: M1 | AZ10: CORRECTO ALQUILER | BA10: =+IF(Tabla467824[[#This Row],[TIPO VEHÍCULO]]=Tabla467824[[#This Row],[Columna2]], "IGUAL", "DISTINTO") -> IGUAL | BB10: =+IF(Tabla467824[[#This Row],[Columna4]]=Tabla467824[[#This Row],[Combustible2]], "IGUAL", "DISTINTO") -> IGUAL | BC10: CAE500007 | BD10: {=IFERROR(INDEX('[1]Anexos FICHA TRA050'!$D$27:$D$44, MATCH(Tabla467824[[#This Row],[Columna5]]&Tabla467824[[#This Row],[Columna4]], '[1]Anexos FICHA TRA050'!$E$27:$E$44&'[1]Anexos FICHA TRA050'!$F$27:$F$44, 0)), "")} -> 6.99 | BE10: =IFERROR(INDEX('[1]Anexos FICHA TRA050'!$B$4:$B$7, MATCH(Tabla467824[[#This Row],[Columna4]], '[1]Anexos FICHA TRA050'!$C$4:$C$7, 0)), "") -> 10 | BF10: =IFERROR(INDEX('[1]Anexos FICHA TRA050'!$C$14:$C$22, MATCH(Tabla467824[[#This Row],[Columna5]], '[1]Anexos FICHA TRA050'!$D$14:$D$22, 0)), "") -> 17.92 | BG10: =IFERROR(INDEX('[1]Anexos FICHA TRA050'!$C$49:$C$54, MATCH(Tabla467824[[#This Row],[Columna5]], '[1]Anexos FICHA TRA050'!$D$49:$D$54, 0)), "") -> 13073 | BH10: =+(((Tabla467824[[#This Row],[CVA2]]*Tabla467824[[#This Row],[f2]])-Tabla467824[[#This Row],[CVN2]])/100)*Tabla467824[[#This Row],[L2]] -> 6795.3454 | BK10: =+IF(Tabla467824[[#This Row],[F]]=Tabla467824[[#This Row],[f2]], "IGUAL", "DISTINTO") -> IGUAL | BL10: =+IF(Tabla467824[[#This Row],[CVN]]=Tabla467824[[#This Row],[CVN2]], "IGUAL", "DISTINTO") -> DISTINTO | BM10: =+IF(Tabla467824[[#This Row],[L]]=Tabla467824[[#This Row],[L2]], "IGUAL", "DISTINTO") -> IGUAL
A11: 8 | B11: CAE500008 | C11: 4295MRH | D11: M1 | E11: DIESEL | F11: DIESEL | G11: M1 | H11: X | J11: X | L11: X | M11: X | O11: AYVENS | P11: 3 | Q11: ALQUILER | R11: DEVUELTO | S11: 45451 | T11: 45565 | U11: 114 | V11: 2024 | W11: 7 | X11: DIESEL | Y11: CITROEN | Z11: C3 100 CV | AA11: 1001 | AB11: AVSA | AC11: 101353 | AD11: 2 | AE11: 6015MWV | AF11: CITROEN | AG11: Ë-C3 ELÉCTRICO MAX | AH11: ELECTRICO | AI11: 200567 | AJ11: 2024 | AK11: 45622 | AL11: 0 | AM11: 1001 | AN11: 4500424209 | AO11: AVSA | AQ11: X | AR11: COMUNIDAD VALENCIANA | AS11: VR7CBZYAXRT152191 | AT11: 5.1 | AU11: 10 | AV11: 16.4 | AW11: 13073 | AX11: 4523.258 | AY11: M1 | AZ11: CORRECTO ALQUILER | BA11: =+IF(Tabla467824[[#This Row],[TIPO VEHÍCULO]]=Tabla467824[[#This Row],[Columna2]], "IGUAL", "DISTINTO") -> IGUAL | BB11: =+IF(Tabla467824[[#This Row],[Columna4]]=Tabla467824[[#This Row],[Combustible2]], "IGUAL", "DISTINTO") -> IGUAL | BC11: CAE500008 | BD11: {=IFERROR(INDEX('[1]Anexos FICHA TRA050'!$D$27:$D$44, MATCH(Tabla467824[[#This Row],[Columna5]]&Tabla467824[[#This Row],[Columna4]], '[1]Anexos FICHA TRA050'!$E$27:$E$44&'[1]Anexos FICHA TRA050'!$F$27:$F$44, 0)), "")} -> 6.99 | BE11: =IFERROR(INDEX('[1]Anexos FICHA TRA050'!$B$4:$B$7, MATCH(Tabla467824[[#This Row],[Columna4]], '[1]Anexos FICHA TRA050'!$C$4:$C$7, 0)), "") -> 10 | BF11: =IFERROR(INDEX('[1]Anexos FICHA TRA050'!$C$14:$C$22, MATCH(Tabla467824[[#This Row],[Columna5]], '[1]Anexos FICHA TRA050'!$D$14:$D$22, 0)), "") -> 17.92 | BG11: =IFERROR(INDEX('[1]Anexos FICHA TRA050'!$C$49:$C$54, MATCH(Tabla467824[[#This Row],[Columna5]], '[1]Anexos FICHA TRA050'!$D$49:$D$54, 0)), "") -> 13073 | BH11: =+(((Tabla467824[[#This Row],[CVA2]]*Tabla467824[[#This Row],[f2]])-Tabla467824[[#This Row],[CVN2]])/100)*Tabla467824[[#This Row],[L2]] -> 6795.3454 | BK11: =+IF(Tabla467824[[#This Row],[F]]=Tabla467824[[#This Row],[f2]], "IGUAL", "DISTINTO") -> IGUAL | BL11: =+IF(Tabla467824[[#This Row],[CVN]]=Tabla467824[[#This Row],[CVN2]], "IGUAL", "DISTINTO") -> DISTINTO | BM11: =+IF(Tabla467824[[#This Row],[L]]=Tabla467824[[#This Row],[L2]], "IGUAL", "DISTINTO") -> IGUAL
A12: 9 | B12: CAE500010 | C12: 8213KFW | D12: L3e | E12: GASOLINA | F12: GASOLINA | G12: L | H12: X | K12: X | L12: X | M12: X | O12: PROPIEDAD | P12: 5 | Q12: PROPIEDAD | R12: CANCELADO POR SINIESTRO | S12: 43073 | T12: 44974 | U12: 1901 | V12: 2023 | W12: 6 | X12: GASOLINA | Y12: KYMCO | Z12: AGILITY CITY 125 CC | AA12: 1021 | AB12: MEDICION AVANZADA CONTAD. | AC12: 357108 | AD12: 4 | AE12: 0692MWT | AF12: RENAULT | AG12: KANGOO VAN E-TECH ELECTRIC | AH12: ELECTRICO | AI12: 357706 | AJ12: 2024 | AK12: 45625 | AL12: 1 | AM12: 1021 | AN12: 4500426794 | AO12: MEDICION AVANZADA CONTAD. | AQ12: X | AR12: COMUNIDAD VALENCIANA | AS12: VF1RFK00173824842 | AT12: 2.9 | AU12: 9.19 | AV12: 17.3 | AW12: 2831 | AX12: 264.72681 | AY12: L3e | AZ12: CORRECTO PROPIEDAD | BA12: =+IF(Tabla467824[[#This Row],[TIPO VEHÍCULO]]=Tabla467824[[#This Row],[Columna2]], "IGUAL", "DISTINTO") -> IGUAL | BB12: =+IF(Tabla467824[[#This Row],[Columna4]]=Tabla467824[[#This Row],[Combustible2]], "IGUAL", "DISTINTO") -> IGUAL | BC12: CAE500010 | BD12: {=IFERROR(INDEX('[1]Anexos FICHA TRA050'!$D$27:$D$44, MATCH(Tabla467824[[#This Row],[Columna5]]&Tabla467824[[#This Row],[Columna4]], '[1]Anexos FICHA TRA050'!$E$27:$E$44&'[1]Anexos FICHA TRA050'!$F$27:$F$44, 0)), "")} -> 2.9 | BE12: =IFERROR(INDEX('[1]Anexos FICHA TRA050'!$B$4:$B$7, MATCH(Tabla467824[[#This Row],[Columna4]], '[1]Anexos FICHA TRA050'!$C$4:$C$7, 0)), "") -> 9.19 | BF12: =IFERROR(INDEX('[1]Anexos FICHA TRA050'!$C$14:$C$22, MATCH(Tabla467824[[#This Row],[Columna5]], '[1]Anexos FICHA TRA050'!$D$14:$D$22, 0)), "") -> 4.84 | BG12: =IFERROR(INDEX('[1]Anexos FICHA TRA050'!$C$49:$C$54, MATCH(Tabla467824[[#This Row],[Columna5]], '[1]Anexos FICHA TRA050'!$D$49:$D$54, 0)), "") -> 2831 | BH12: =+(((Tabla467824[[#This Row],[CVA2]]*Tabla467824[[#This Row],[f2]])-Tabla467824[[#This Row],[CVN2]])/100)*Tabla467824[[#This Row],[L2]] -> 617.46941 | BK12: =+IF(Tabla467824[[#This Row],[F]]=Tabla467824[[#This Row],[f2]], "IGUAL", "DISTINTO") -> IGUAL | BL12: =+IF(Tabla467824[[#This Row],[CVN]]=Tabla467824[[#This Row],[CVN2]], "IGUAL", "DISTINTO") -> DISTINTO | BM12: =+IF(Tabla467824[[#This Row],[L]]=Tabla467824[[#This Row],[L2]], "IGUAL", "DISTINTO") -> IGUAL
A13: 10 | B13: CAE500011 | C13: 0909HZB | D13: L3e | E13: GASOLINA | F13: GASOLINA | G13: L | H13: X | K13: X | L13: X | M13: X | O13: PROPIEDAD | P13: 5 | Q13: PROPIEDAD | R13: CANCELADO | S13: 42641 | T13: 45561 | U13: 2920 | V13: 2024 | W13: 4 | X13: GASOLINA | Y13: KYMCO | Z13: AGILITY CITY 125 CC | AA13: 1021 | AB13: MEDICION AVANZADA CONTAD. | AC13: 357108 | AD13: 5 | AE13: 0773MXH | AF13: RENAULT | AG13: KANGOO VAN E-TECH ELECTRIC | AH13: ELECTRICO | AI13: 357708 | AJ13: 2024 | AK13: 45646 | AL13: 0 | AM13: 1021 | AN13: 4500426849 | AO13: MEDICION AVANZADA CONTAD. | AQ13: X | AR13: COMUNIDAD VALENCIANA | AS13: VF1RFK00473824852 | AT13: 2.9 | AU13: 9.19 | AV13: 17.3 | AW13: 2831 | AX13: 264.72681 | AY13: L3e | AZ13: CORRECTO PROPIEDAD | BA13: =+IF(Tabla467824[[#This Row],[TIPO VEHÍCULO]]=Tabla467824[[#This Row],[Columna2]], "IGUAL", "DISTINTO") -> IGUAL | BB13: =+IF(Tabla467824[[#This Row],[Columna4]]=Tabla467824[[#This Row],[Combustible2]], "IGUAL", "DISTINTO") -> IGUAL | BC13: CAE500011 | BD13: {=IFERROR(INDEX('[1]Anexos FICHA TRA050'!$D$27:$D$44, MATCH(Tabla467824[[#This Row],[Columna5]]&Tabla467824[[#This Row],[Columna4]], '[1]Anexos FICHA TRA050'!$E$27:$E$44&'[1]Anexos FICHA TRA050'!$F$27:$F$44, 0)), "")} -> 2.9 | BE13: =IFERROR(INDEX('[1]Anexos FICHA TRA050'!$B$4:$B$7, MATCH(Tabla467824[[#This Row],[Columna4]], '[1]Anexos FICHA TRA050'!$C$4:$C$7, 0)), "") -> 9.19 | BF13: =IFERROR(INDEX('[1]Anexos FICHA TRA050'!$C$14:$C$22, MATCH(Tabla467824[[#This Row],[Columna5]], '[1]Anexos FICHA TRA050'!$D$14:$D$22, 0)), "") -> 4.84 | BG13: =IFERROR(INDEX('[1]Anexos FICHA TRA050'!$C$49:$C$54, MATCH(Tabla467824[[#This Row],[Columna5]], '[1]Anexos FICHA TRA050'!$D$49:$D$54, 0)), "") -> 2831 | BH13: =+(((Tabla467824[[#This Row],[CVA2]]*Tabla467824[[#This Row],[f2]])-Tabla467824[[#This Row],[CVN2]])/100)*Tabla467824[[#This Row],[L2]] -> 617.46941 | BK13: =+IF(Tabla467824[[#This Row],[F]]=Tabla467824[[#This Row],[f2]], "IGUAL", "DISTINTO") -> IGUAL | BL13: =+IF(Tabla467824[[#This Row],[CVN]]=Tabla467824[[#This Row],[CVN2]], "IGUAL", "DISTINTO") -> DISTINTO | BM13: =+IF(Tabla467824[[#This Row],[L]]=Tabla467824[[#This Row],[L2]], "IGUAL", "DISTINTO") -> IGUAL
A14: 11 | B14: CAE500012 | C14: 1987HGR | D14: L3e | E14: GASOLINA | F14: GASOLINA | G14: L | H14: X | K14: X | L14: X | M14: X | O14: PROPIEDAD | P14: 5 | Q14: PROPIEDAD | R14: CANCELADO | S14: 40830 | T14: 45561 | U14: 4731 | V14: 2024 | W14: 4 | X14: GASOLINA | Y14: KYMCO | Z14: AGILITY CITY 125 CC | AA14: 1021 | AB14: MEDICION AVANZADA CONTAD. | AC14: 357108 | AD14: 6 | AE14: 0823MXH | AF14: RENAULT | AG14: KANGOO VAN E-TECH ELECTRIC | AH14: ELECTRICO | AI14: 357752 | AJ14: 2024 | AK14: 45646 | AL14: 0 | AM14: 1021 | AN14: 4500426870 | AO14: MEDICION AVANZADA CONTAD. | AQ14: X | AR14: COMUNIDAD VALENCIANA | AS14: VF1RFK00873824854 | AT14: 2.9 | AU14: 9.19 | AV14: 17.3 | AW14: 2831 | AX14: 264.72681 | AY14: L3e | AZ14: CORRECTO PROPIEDAD | BA14: =+IF(Tabla467824[[#This Row],[TIPO VEHÍCULO]]=Tabla467824[[#This Row],[Columna2]], "IGUAL", "DISTINTO") -> IGUAL | BB14: =+IF(Tabla467824[[#This Row],[Columna4]]=Tabla467824[[#This Row],[Combustible2]], "IGUAL", "DISTINTO") -> IGUAL | BC14: CAE500012 | BD14: {=IFERROR(INDEX('[1]Anexos FICHA TRA050'!$D$27:$D$44, MATCH(Tabla467824[[#This Row],[Columna5]]&Tabla467824[[#This Row],[Columna4]], '[1]Anexos FICHA TRA050'!$E$27:$E$44&'[1]Anexos FICHA TRA050'!$F$27:$F$44, 0)), "")} -> 2.9 | BE14: =IFERROR(INDEX('[1]Anexos FICHA TRA050'!$B$4:$B$7, MATCH(Tabla467824[[#This Row],[Columna4]], '[1]Anexos FICHA TRA050'!$C$4:$C$7, 0)), "") -> 9.19 | BF14: =IFERROR(INDEX('[1]Anexos FICHA TRA050'!$C$14:$C$22, MATCH(Tabla467824[[#This Row],[Columna5]], '[1]Anexos FICHA TRA050'!$D$14:$D$22, 0)), "") -> 4.84 | BG14: =IFERROR(INDEX('[1]Anexos FICHA TRA050'!$C$49:$C$54, MATCH(Tabla467824[[#This Row],[Columna5]], '[1]Anexos FICHA TRA050'!$D$49:$D$54, 0)), "") -> 2831 | BH14: =+(((Tabla467824[[#This Row],[CVA2]]*Tabla467824[[#This Row],[f2]])-Tabla467824[[#This Row],[CVN2]])/100)*Tabla467824[[#This Row],[L2]] -> 617.46941 | BK14: =+IF(Tabla467824[[#This Row],[F]]=Tabla467824[[#This Row],[f2]], "IGUAL", "DISTINTO") -> IGUAL | BL14: =+IF(Tabla467824[[#This Row],[CVN]]=Tabla467824[[#This Row],[CVN2]], "IGUAL", "DISTINTO") -> DISTINTO | BM14: =+IF(Tabla467824[[#This Row],[L]]=Tabla467824[[#This Row],[L2]], "IGUAL", "DISTINTO") -> IGUAL
A15: 12 | B15: CAE500013 | C15: 8449HKF | D15: L3e | E15: GASOLINA | F15: GASOLINA | G15: L | K15: X | L15: X | M15: X | N15: X | O15: PROPIEDAD | P15: 5 | Q15: PROPIEDAD | R15: CANCELADO | S15: 41017 | T15: 45561 | U15: 4544 | V15: 2024 | W15: 4 | X15: GASOLINA | Y15: KYMCO | Z15: AGILITY CITY 125 CC | AA15: 1021 | AB15: MEDICION AVANZADA CONTAD. | AC15: 357108 | AD15: 7 | AE15: 0971MXH | AF15: RENAULT | AG15: KANGOO VAN E-TECH ELECTRIC | AH15: ELECTRICO | AI15: 357708 | AJ15: 2024 | AK15: 45646 | AL15: 0 | AM15: 1021 | AN15: 4500426847 | AO15: MEDICION AVANZADA CONTAD. | AQ15: X | AR15: COMUNIDAD VALENCIANA | AS15: VF1RFK00073824847 | AT15: 2.9 | AU15: 9.19 | AV15: 17.3 | AW15: 2831 | AX15: 264.72681 | AY15: L3e | AZ15: CORRECTO PROPIEDAD | BA15: =+IF(Tabla467824[[#This Row],[TIPO VEHÍCULO]]=Tabla467824[[#This Row],[Columna2]], "IGUAL", "DISTINTO") -> IGUAL | BB15: =+IF(Tabla467824[[#This Row],[Columna4]]=Tabla467824[[#This Row],[Combustible2]], "IGUAL", "DISTINTO") -> IGUAL | BC15: CAE500013 | BD15: {=IFERROR(INDEX('[1]Anexos FICHA TRA050'!$D$27:$D$44, MATCH(Tabla467824[[#This Row],[Columna5]]&Tabla467824[[#This Row],[Columna4]], '[1]Anexos FICHA TRA050'!$E$27:$E$44&'[1]Anexos FICHA TRA050'!$F$27:$F$44, 0)), "")} -> 2.9 | BE15: =IFERROR(INDEX('[1]Anexos FICHA TRA050'!$B$4:$B$7, MATCH(Tabla467824[[#This Row],[Columna4]], '[1]Anexos FICHA TRA050'!$C$4:$C$7, 0)), "") -> 9.19 | BF15: =IFERROR(INDEX('[1]Anexos FICHA TRA050'!$C$14:$C$22, MATCH(Tabla467824[[#This Row],[Columna5]], '[1]Anexos FICHA TRA050'!$D$14:$D$22, 0)), "") -> 4.84 | BG15: =IFERROR(INDEX('[1]Anexos FICHA TRA050'!$C$49:$C$54, MATCH(Tabla467824[[#This Row],[Columna5]], '[1]Anexos FICHA TRA050'!$D$49:$D$54, 0)), "") -> 2831 | BH15: =+(((Tabla467824[[#This Row],[CVA2]]*Tabla467824[[#This Row],[f2]])-Tabla467824[[#This Row],[CVN2]])/100)*Tabla467824[[#This Row],[L2]] -> 617.46941 | BK15: =+IF(Tabla467824[[#This Row],[F]]=Tabla467824[[#This Row],[f2]], "IGUAL", "DISTINTO") -> IGUAL | BL15: =+IF(Tabla467824[[#This Row],[CVN]]=Tabla467824[[#This Row],[CVN2]], "IGUAL", "DISTINTO") -> DISTINTO | BM15: =+IF(Tabla467824[[#This Row],[L]]=Tabla467824[[#This Row],[L2]], "IGUAL", "DISTINTO") -> IGUAL
A16: 13 | B16: CAE500014 | C16: 4579KCW | D16: L3e | E16: GASOLINA | F16: GASOLINA | G16: L | H16: X | K16: X | L16: X | M16: X | O16: PROPIEDAD | P16: 5 | Q16: PROPIEDAD | R16: CANCELADO | S16: 42983 | T16: 45604 | U16: 2621 | V16: 2024 | W16: 4 | X16: GASOLINA | Y16: KYMCO | Z16: AGILITY CITY 125 CC | AA16: 1053 | AB16: ISG | AC16: 355521 | AD16: 1 | AE16: 8349MXG | AF16: RENAULT | AG16: KANGOO VAN E-TECH ELECTRIC | AH16: ELECTRICO | AI16: 355528 | AJ16: 2024 | AK16: 45646 | AL16: 0 | AM16: 1053 | AN16: 4500426779 | AO16: ISG | AQ16: X | AR16: COMUNIDAD VALENCIANA | AS16: VF1RFK00373934291 | AT16: 2.9 | AU16: 9.19 | AV16: 17.3 | AW16: 2831 | AX16: 264.72681 | AY16: L3e | AZ16: CORRECTO PROPIEDAD | BA16: =+IF(Tabla467824[[#This Row],[TIPO VEHÍCULO]]=Tabla467824[[#This Row],[Columna2]], "IGUAL", "DISTINTO") -> IGUAL | BB16: =+IF(Tabla467824[[#This Row],[Columna4]]=Tabla467824[[#This Row],[Combustible2]], "IGUAL", "DISTINTO") -> IGUAL | BC16: CAE500014 | BD16: {=IFERROR(INDEX('[1]Anexos FICHA TRA050'!$D$27:$D$44, MATCH(Tabla467824[[#This Row],[Columna5]]&Tabla467824[[#This Row],[Columna4]], '[1]Anexos FICHA TRA050'!$E$27:$E$44&'[1]Anexos FICHA TRA050'!$F$27:$F$44, 0)), "")} -> 2.9 | BE16: =IFERROR(INDEX('[1]Anexos FICHA TRA050'!$B$4:$B$7, MATCH(Tabla467824[[#This Row],[Columna4]], '[1]Anexos FICHA TRA050'!$C$4:$C$7, 0)), "") -> 9.19 | BF16: =IFERROR(INDEX('[1]Anexos FICHA TRA050'!$C$14:$C$22, MATCH(Tabla467824[[#This Row],[Columna5]], '[1]Anexos FICHA TRA050'!$D$14:$D$22, 0)), "") -> 4.84 | BG16: =IFERROR(INDEX('[1]Anexos FICHA TRA050'!$C$49:$C$54, MATCH(Tabla467824[[#This Row],[Columna5]], '[1]Anexos FICHA TRA050'!$D$49:$D$54, 0)), "") -> 2831 | BH16: =+(((Tabla467824[[#This Row],[CVA2]]*Tabla467824[[#This Row],[f2]])-Tabla467824[[#This Row],[CVN2]])/100)*Tabla467824[[#This Row],[L2]] -> 617.46941 | BK16: =+IF(Tabla467824[[#This Row],[F]]=Tabla467824[[#This Row],[f2]], "IGUAL", "DISTINTO") -> IGUAL | BL16: =+IF(Tabla467824[[#This Row],[CVN]]=Tabla467824[[#This Row],[CVN2]], "IGUAL", "DISTINTO") -> DISTINTO | BM16: =+IF(Tabla467824[[#This Row],[L]]=Tabla467824[[#This Row],[L2]], "IGUAL", "DISTINTO") -> IGUAL
A17: 14 | B17: CAE500015 | C17: 1485LSB | D17: M1 | E17: GASOLINA - Híbridos (HEV) | F17: GASOLINA - Híbridos (HEV) | G17: M1 | H17: X | I17: X | J17: X | L17: X | M17: X | O17: AYVENS | P17: 1 | Q17: RENTING | R17: DEVUELTO | S17: 44414 | T17: 45875 | U17: 1461 | V17: 2025 | W17: 7 | X17: HÍBRIDO | Y17: RENAULT | Z17: ARKANA TCE 140 CV | AA17: 1200 | AB17: EMIVASA | AC17: 12009006 | AD17: 1 | AE17: 3143MWZ | AF17: CITROEN | AG17: Ë-C3 ELÉCTRICO MAX | AH17: ELECTRICO | AI17: 100011 | AJ17: 2024 | AK17: 45638 | AL17: -1 | AM17: 1200 | AN17: 4500424885 | AO17: EMIVASA | AQ17: X | AR17: COMUNIDAD VALENCIANA | AS17: VR7CBZYA5RT154432 | AT17: 5.1 | AU17: 9.19 | AV17: 16.4 | AW17: 13073 | AX17: 3983.2124 | AY17: M1 | AZ17: CORRECTO ALQUILER | BA17: =+IF(Tabla467824[[#This Row],[TIPO VEHÍCULO]]=Tabla467824[[#This Row],[Columna2]], "IGUAL", "DISTINTO") -> IGUAL | BB17: =+IF(Tabla467824[[#This Row],[Columna4]]=Tabla467824[[#This Row],[Combustible2]], "IGUAL", "DISTINTO") -> DISTINTO | BC17: CAE500015 | BD17: {=IFERROR(INDEX('[1]Anexos FICHA TRA050'!$D$27:$D$44, MATCH(Tabla467824[[#This Row],[Columna5]]&Tabla467824[[#This Row],[Columna4]], '[1]Anexos FICHA TRA050'!$E$27:$E$44&'[1]Anexos FICHA TRA050'!$F$27:$F$44, 0)), "")} -> 5.135 | BE17: =+'[1]Anexos FICHA TRA050'!B5 -> 9.19 | BF17: =IFERROR(INDEX('[1]Anexos FICHA TRA050'!$C$14:$C$22, MATCH(Tabla467824[[#This Row],[Columna5]], '[1]Anexos FICHA TRA050'!$D$14:$D$22, 0)), "") -> 17.92 | BG17: =IFERROR(INDEX('[1]Anexos FICHA TRA050'!$C$49:$C$54, MATCH(Tabla467824[[#This Row],[Columna5]], '[1]Anexos FICHA TRA050'!$D$49:$D$54, 0)), "") -> 13073 | BH17: =+(((Tabla467824[[#This Row],[CVA2]]*Tabla467824[[#This Row],[f2]])-Tabla467824[[#This Row],[CVN2]])/100)*Tabla467824[[#This Row],[L2]] -> 3826.5521 | BK17: =+IF(Tabla467824[[#This Row],[F]]=Tabla467824[[#This Row],[f2]], "IGUAL", "DISTINTO") -> IGUAL | BL17: =+IF(Tabla467824[[#This Row],[CVN]]=Tabla467824[[#This Row],[CVN2]], "IGUAL", "DISTINTO") -> DISTINTO | BM17: =+IF(Tabla467824[[#This Row],[L]]=Tabla467824[[#This Row],[L2]], "IGUAL", "DISTINTO") -> IGUAL
A18: 15 | B18: CAE500016 | C18: 3931LLT | D18: M1 | E18: GASOLINA | F18: GASOLINA | G18: M1 | H18: X | J18: X | L18: X | O18: AYVENS | P18: 1 | Q18: RENTING | R18: DEVUELTO | S18: 44224 | T18: 45685 | U18: 1461 | V18: 2025 | W18: 7 | X18: GASOLINA | Y18: SEAT | Z18: ARONA 1.0 TSI 115 CV | AA18: 1203 | AB18: E.Mixta Metropolitana, SA | AC18: 12039060 | AD18: 1 | AE18: 6082MWV | AF18: CITROEN | AG18: Ë-C3 ELÉCTRICO MAX | AH18: ELECTRICO | AI18: 12039060 | AJ18: 2024 | AK18: 45625 | AL18: -1 | AM18: 1203 | AN18: 4500424805 | AO18: E.Mixta Metropolitana, SA | AQ18: X | AR18: COMUNIDAD VALENCIANA | AS18: VR7CBZYA7RT153038 | AT18: 5.1 | AU18: 9.19 | AV18: 16.4 | AW18: 13073 | AX18: 3983.2124 | AY18: M1 | AZ18: CORRECTO ALQUILER | BA18: =+IF(Tabla467824[[#This Row],[TIPO VEHÍCULO]]=Tabla467824[[#This Row],[Columna2]], "IGUAL", "DISTINTO") -> IGUAL | BB18: =+IF(Tabla467824[[#This Row],[Columna4]]=Tabla467824[[#This Row],[Combustible2]], "IGUAL", "DISTINTO") -> IGUAL | BC18: CAE500016 | BD18: {=IFERROR(INDEX('[1]Anexos FICHA TRA050'!$D$27:$D$44, MATCH(Tabla467824[[#This Row],[Columna5]]&Tabla467824[[#This Row],[Columna4]], '[1]Anexos FICHA TRA050'!$E$27:$E$44&'[1]Anexos FICHA TRA050'!$F$27:$F$44, 0)), "")} -> 7.89 | BE18: =IFERROR(INDEX('[1]Anexos FICHA TRA050'!$B$4:$B$7, MATCH(Tabla467824[[#This Row],[Columna4]], '[1]Anexos FICHA TRA050'!$C$4:$C$7, 0)), "") -> 9.19 | BF18: =IFERROR(INDEX('[1]Anexos FICHA TRA050'!$C$14:$C$22, MATCH(Tabla467824[[#This Row],[Columna5]], '[1]Anexos FICHA TRA050'!$D$14:$D$22, 0)), "") -> 17.92 | BG18: =IFERROR(INDEX('[1]Anexos FICHA TRA050'!$C$49:$C$54, MATCH(Tabla467824[[#This Row],[Columna5]], '[1]Anexos FICHA TRA050'!$D$49:$D$54, 0)), "") -> 13073 | BH18: =+(((Tabla467824[[#This Row],[CVA2]]*Tabla467824[[#This Row],[f2]])-Tabla467824[[#This Row],[CVN2]])/100)*Tabla467824[[#This Row],[L2]] -> 7136.433 | BK18: =+IF(Tabla467824[[#This Row],[F]]=Tabla467824[[#This Row],[f2]], "IGUAL", "DISTINTO") -> IGUAL | BL18: =+IF(Tabla467824[[#This Row],[CVN]]=Tabla467824[[#This Row],[CVN2]], "IGUAL", "DISTINTO") -> DISTINTO | BM18: =+IF(Tabla467824[[#This Row],[L]]=Tabla467824[[#This Row],[L2]], "IGUAL", "DISTINTO") -> IGUAL
A19: 16 | B19: CAE500017 | C19: 5829LLX | D19: M1 | E19: GASOLINA | F19: GASOLINA | G19: M1 | H19: X | J19: X | L19: X | M19: X | O19: AYVENS | P19: 1 | Q19: RENTING | R19: DEVUELTO | S19: 44215 | T19: 45676 | U19: 1461 | V19: 2025 | W19: 7 | X19: GASOLINA | Y19: SEAT | Z19: ARONA 1.0 TSI 115 CV | AA19: 1001 | AB19: AVSA | AC19: 200590 | AD19: 3 | AE19: 9050MWN | AF19: CITROEN | AG19: Ë-C3 ELÉCTRICO MAX | AH19: ELECTRICO | AI19: 200541 | AJ19: 2024 | AK19: 45622 | AL19: -1 | AM19: 1001 | AN19: 4500424807 | AO19: AVSA | AQ19: X | AR19: COMUNIDAD VALENCIANA | AS19: VR7CBZYA1RT152189 | AT19: 5.1 | AU19: 9.19 | AV19: 16.4 | AW19: 13073 | AX19: 3983.2124 | AY19: M1 | AZ19: CORRECTO ALQUILER | BA19: =+IF(Tabla467824[[#This Row],[TIPO VEHÍCULO]]=Tabla467824[[#This Row],[Columna2]], "IGUAL", "DISTINTO") -> IGUAL | BB19: =+IF(Tabla467824[[#This Row],[Columna4]]=Tabla467824[[#This Row],[Combustible2]], "IGUAL", "DISTINTO") -> IGUAL | BC19: CAE500017 | BD19: {=IFERROR(INDEX('[1]Anexos FICHA TRA050'!$D$27:$D$44, MATCH(Tabla467824[[#This Row],[Columna5]]&Tabla467824[[#This Row],[Columna4]], '[1]Anexos FICHA TRA050'!$E$27:$E$44&'[1]Anexos FICHA TRA050'!$F$27:$F$44, 0)), "")} -> 7.89 | BE19: =IFERROR(INDEX('[1]Anexos FICHA TRA050'!$B$4:$B$7, MATCH(Tabla467824[[#This Row],[Columna4]], '[1]Anexos FICHA TRA050'!$C$4:$C$7, 0)), "") -> 9.19 | BF19: =IFERROR(INDEX('[1]Anexos FICHA TRA050'!$C$14:$C$22, MATCH(Tabla467824[[#This Row],[Columna5]], '[1]Anexos FICHA TRA050'!$D$14:$D$22, 0)), "") -> 17.92 | BG19: =IFERROR(INDEX('[1]Anexos FICHA TRA050'!$C$49:$C$54, MATCH(Tabla467824[[#This Row],[Columna5]], '[1]Anexos FICHA TRA050'!$D$49:$D$54, 0)), "") -> 13073 | BH19: =+(((Tabla467824[[#This Row],[CVA2]]*Tabla467824[[#This Row],[f2]])-Tabla467824[[#This Row],[CVN2]])/100)*Tabla467824[[#This Row],[L2]] -> 7136.433 | BK19: =+IF(Tabla467824[[#This Row],[F]]=Tabla467824[[#This Row],[f2]], "IGUAL", "DISTINTO") -> IGUAL | BL19: =+IF(Tabla467824[[#This Row],[CVN]]=Tabla467824[[#This Row],[CVN2]], "IGUAL", "DISTINTO") -> DISTINTO | BM19: =+IF(Tabla467824[[#This Row],[L]]=Tabla467824[[#This Row],[L2]], "IGUAL", "DISTINTO") -> IGUAL
A20: 17 | B20: CAE500018 | C20: 3904LLT | D20: M1 | E20: GASOLINA | F20: GASOLINA | G20: M1 | H20: X | J20: X | L20: X | M20: X | O20: AYVENS | P20: 1 | Q20: RENTING | R20: DEVUELTO | S20: 44224 | T20: 45689 | U20: 1465 | V20: 2025 | W20: 7 | X20: GASOLINA | Y20: SEAT | Z20: ARONA 1.0 TSI 115 CV | AA20: 1200 | AB20: EMIVASA | AC20: 12009060 | AD20: 2 | AE20: 3133MWZ | AF20: CITROEN | AG20: Ë-C3 ELÉCTRICO MAX | AH20: ELECTRICO | AI20: 200020 | AJ20: 2024 | AK20: 45638 | AL20: -1 | AM20: 1200 | AN20: 4500424896 | AO20: EMIVASA | AQ20: X | AR20: COMUNIDAD VALENCIANA | AS20: VR7CBZYA2RT154436 | AT20: 5.1 | AU20: 9.19 | AV20: 16.4 | AW20: 13073 | AX20: 3983.2124 | AY20: M1 | AZ20: CORRECTO ALQUILER | BA20: =+IF(Tabla467824[[#This Row],[TIPO VEHÍCULO]]=Tabla467824[[#This Row],[Columna2]], "IGUAL", "DISTINTO") -> IGUAL | BB20: =+IF(Tabla467824[[#This Row],[Columna4]]=Tabla467824[[#This Row],[Combustible2]], "IGUAL", "DISTINTO") -> IGUAL | BC20: CAE500018 | BD20: {=IFERROR(INDEX('[1]Anexos FICHA TRA050'!$D$27:$D$44, MATCH(Tabla467824[[#This Row],[Columna5]]&Tabla467824[[#This Row],[Columna4]], '[1]Anexos FICHA TRA050'!$E$27:$E$44&'[1]Anexos FICHA TRA050'!$F$27:$F$44, 0)), "")} -> 7.89 | BE20: =IFERROR(INDEX('[1]Anexos FICHA TRA050'!$B$4:$B$7, MATCH(Tabla467824[[#This Row],[Columna4]], '[1]Anexos FICHA TRA050'!$C$4:$C$7, 0)), "") -> 9.19 | BF20: =IFERROR(INDEX('[1]Anexos FICHA TRA050'!$C$14:$C$22, MATCH(Tabla467824[[#This Row],[Columna5]], '[1]Anexos FICHA TRA050'!$D$14:$D$22, 0)), "") -> 17.92 | BG20: =IFERROR(INDEX('[1]Anexos FICHA TRA050'!$C$49:$C$54, MATCH(Tabla467824[[#This Row],[Columna5]], '[1]Anexos FICHA TRA050'!$D$49:$D$54, 0)), "") -> 13073 | BH20: =+(((Tabla467824[[#This Row],[CVA2]]*Tabla467824[[#This Row],[f2]])-Tabla467824[[#This Row],[CVN2]])/100)*Tabla467824[[#This Row],[L2]] -> 7136.433 | BK20: =+IF(Tabla467824[[#This Row],[F]]=Tabla467824[[#This Row],[f2]], "IGUAL", "DISTINTO") -> IGUAL | BL20: =+IF(Tabla467824[[#This Row],[CVN]]=Tabla467824[[#This Row],[CVN2]], "IGUAL", "DISTINTO") -> DISTINTO | BM20: =+IF(Tabla467824[[#This Row],[L]]=Tabla467824[[#This Row],[L2]], "IGUAL", "DISTINTO") -> IGUAL
A21: 18 | B21: CAE500019 | C21: 9417LKC | D21: M1 | E21: DIESEL | F21: DIESEL | G21: M1 | H21: X | J21: X | L21: X | O21: AYVENS | P21: 1 | Q21: RENTING | R21: DEVUELTO | S21: 44133 | T21: 45594 | U21: 1461 | V21: 2024 | W21: 7 | X21: DIESEL | Y21: SEAT | Z21: ARONA 1.6 TDI 95 CV | AA21: 1200 | AB21: EMIVASA | AC21: 12009060 | AD21: 3 | AE21: 3105MWZ | AF21: CITROEN | AG21: Ë-C3 ELÉCTRICO MAX | AH21: ELECTRICO | AI21: 200020 | AJ21: 2024 | AK21: 45638 | AL21: 0 | AM21: 1200 | AN21: 4500424877 | AO21: EMIVASA | AQ21: X | AR21: COMUNIDAD VALENCIANA | AS21: VR7CBZYA3RT153022 | AT21: 5.1 | AU21: 10 | AV21: 16.4 | AW21: 13073 | AX21: 4523.258 | AY21: M1 | AZ21: CORRECTO ALQUILER | BA21: =+IF(Tabla467824[[#This Row],[TIPO VEHÍCULO]]=Tabla467824[[#This Row],[Columna2]], "IGUAL", "DISTINTO") -> IGUAL | BB21: =+IF(Tabla467824[[#This Row],[Columna4]]=Tabla467824[[#This Row],[Combustible2]], "IGUAL", "DISTINTO") -> IGUAL | BC21: CAE500019 | BD21: {=IFERROR(INDEX('[1]Anexos FICHA TRA050'!$D$27:$D$44, MATCH(Tabla467824[[#This Row],[Columna5]]&Tabla467824[[#This Row],[Columna4]], '[1]Anexos FICHA TRA050'!$E$27:$E$44&'[1]Anexos FICHA TRA050'!$F$27:$F$44, 0)), "")} -> 6.99 | BE21: =IFERROR(INDEX('[1]Anexos FICHA TRA050'!$B$4:$B$7, MATCH(Tabla467824[[#This Row],[Columna4]], '[1]Anexos FICHA TRA050'!$C$4:$C$7, 0)), "") -> 10 | BF21: =IFERROR(INDEX('[1]Anexos FICHA TRA050'!$C$14:$C$22, MATCH(Tabla467824[[#This Row],[Columna5]], '[1]Anexos FICHA TRA050'!$D$14:$D$22, 0)), "") -> 17.92 | BG21: =IFERROR(INDEX('[1]Anexos FICHA TRA050'!$C$49:$C$54, MATCH(Tabla467824[[#This Row],[Columna5]], '[1]Anexos FICHA TRA050'!$D$49:$D$54, 0)), "") -> 13073 | BH21: =+(((Tabla467824[[#This Row],[CVA2]]*Tabla467824[[#This Row],[f2]])-Tabla467824[[#This Row],[CVN2]])/100)*Tabla467824[[#This Row],[L2]] -> 6795.3454 | BK21: =+IF(Tabla467824[[#This Row],[F]]=Tabla467824[[#This Row],[f2]], "IGUAL", "DISTINTO") -> IGUAL | BL21: =+IF(Tabla467824[[#This Row],[CVN]]=Tabla467824[[#This Row],[CVN2]], "IGUAL", "DISTINTO") -> DISTINTO | BM21: =+IF(Tabla467824[[#This Row],[L]]=Tabla467824[[#This Row],[L2]], "IGUAL", "DISTINTO") -> IGUAL
A22: 19 | B22: CAE500020 | C22: 9418LKC | D22: M1 | E22: DIESEL | F22: DIESEL | G22: M1 | H22: X | J22: X | L22: X | M22: X | O22: AYVENS | P22: 1 | Q22: RENTING | R22: DEVUELTO | S22: 44133 | T22: 45594 | U22: 1461 | V22: 2024 | W22: 7 | X22: DIESEL | Y22: SEAT | Z22: ARONA 1.6 TDI 95 CV | AA22: 1001 | AB22: AVSA | AC22: 101702 | AD22: 4 | AE22: 6028MWV | AF22: CITROEN | AG22: Ë-C3 ELÉCTRICO MAX | AH22: ELECTRICO | AI22: 200590 | AJ22: 2024 | AK22: 45622 | AL22: 0 | AM22: 1001 | AN22: 4500424796 | AO22: AVSA | AQ22: X | AR22: COMUNIDAD VALENCIANA | AS22: VR7CBZYA2RT152184 | AT22: 5.1 | AU22: 10 | AV22: 16.4 | AW22: 13073 | AX22: 4523.258 | AY22: M1 | AZ22: CORRECTO ALQUILER | BA22: =+IF(Tabla467824[[#This Row],[TIPO VEHÍCULO]]=Tabla467824[[#This Row],[Columna2]], "IGUAL", "DISTINTO") -> IGUAL | BB22: =+IF(Tabla467824[[#This Row],[Columna4]]=Tabla467824[[#This Row],[Combustible2]], "IGUAL", "DISTINTO") -> IGUAL | BC22: CAE500020 | BD22: {=IFERROR(INDEX('[1]Anexos FICHA TRA050'!$D$27:$D$44, MATCH(Tabla467824[[#This Row],[Columna5]]&Tabla467824[[#This Row],[Columna4]], '[1]Anexos FICHA TRA050'!$E$27:$E$44&'[1]Anexos FICHA TRA050'!$F$27:$F$44, 0)), "")} -> 6.99 | BE22: =IFERROR(INDEX('[1]Anexos FICHA TRA050'!$B$4:$B$7, MATCH(Tabla467824[[#This Row],[Columna4]], '[1]Anexos FICHA TRA050'!$C$4:$C$7, 0)), "") -> 10 | BF22: =IFERROR(INDEX('[1]Anexos FICHA TRA050'!$C$14:$C$22, MATCH(Tabla467824[[#This Row],[Columna5]], '[1]Anexos FICHA TRA050'!$D$14:$D$22, 0)), "") -> 17.92 | BG22: =IFERROR(INDEX('[1]Anexos FICHA TRA050'!$C$49:$C$54, MATCH(Tabla467824[[#This Row],[Columna5]], '[1]Anexos FICHA TRA050'!$D$49:$D$54, 0)), "") -> 13073 | BH22: =+(((Tabla467824[[#This Row],[CVA2]]*Tabla467824[[#This Row],[f2]])-Tabla467824[[#This Row],[CVN2]])/100)*Tabla467824[[#This Row],[L2]] -> 6795.3454 | BK22: =+IF(Tabla467824[[#This Row],[F]]=Tabla467824[[#This Row],[f2]], "IGUAL", "DISTINTO") -> IGUAL | BL22: =+IF(Tabla467824[[#This Row],[CVN]]=Tabla467824[[#This Row],[CVN2]], "IGUAL", "DISTINTO") -> DISTINTO | BM22: =+IF(Tabla467824[[#This Row],[L]]=Tabla467824[[#This Row],[L2]], "IGUAL", "DISTINTO") -> IGUAL
A23: 20 | B23: CAE500030 | C23: 9428LKC | D23: M1 | E23: DIESEL | F23: DIESEL | G23: M1 | H23: X | L23: x | M23: x | O23: AYVENS | P23: 1 | Q23: RENTING | R23: CANCELADO POR SINIESTRO | S23: 44133 | T23: 45594 | U23: 1461 | V23: 2024 | W23: 6 | X23: DIESEL | Y23: SEAT | Z23: ARONA 1.6 TDI 95 CV | AA23: 1001 | AB23: AVSA | AC23: 200750 | AD23: 5 | AE23: 6029MWV | AF23: CITROEN | AG23: Ë-C3 ELÉCTRICO MAX | AH23: ELECTRICO | AI23: 200714 | AJ23: 2024 | AK23: 45625 | AL23: 0 | AM23: 1001 | AN23: 4500424793 | AO23: AVSA | AQ23: X | AR23: COMUNIDAD VALENCIANA | AS23: VR7CBZYA7RT152178 | AT23: 5.1 | AU23: 10 | AV23: 16.4 | AW23: 13073 | AX23: 4523.258 | AY23: M1 | AZ23: FALSO ALQUILER | BA23: =+IF(Tabla467824[[#This Row],[TIPO VEHÍCULO]]=Tabla467824[[#This Row],[Columna2]], "IGUAL", "DISTINTO") -> IGUAL | BB23: =+IF(Tabla467824[[#This Row],[Columna4]]=Tabla467824[[#This Row],[Combustible2]], "IGUAL", "DISTINTO") -> IGUAL | BC23: CAE500030 | BD23: {=IFERROR(INDEX('[1]Anexos FICHA TRA050'!$D$27:$D$44, MATCH(Tabla467824[[#This Row],[Columna5]]&Tabla467824[[#This Row],[Columna4]], '[1]Anexos FICHA TRA050'!$E$27:$E$44&'[1]Anexos FICHA TRA050'!$F$27:$F$44, 0)), "")} -> 6.99 | BE23: =IFERROR(INDEX('[1]Anexos FICHA TRA050'!$B$4:$B$7, MATCH(Tabla467824[[#This Row],[Columna4]], '[1]Anexos FICHA TRA050'!$C$4:$C$7, 0)), "") -> 10 | BF23: =IFERROR(INDEX('[1]Anexos FICHA TRA050'!$C$14:$C$22, MATCH(Tabla467824[[#This Row],[Columna5]], '[1]Anexos FICHA TRA050'!$D$14:$D$22, 0)), "") -> 17.92 | BG23: =IFERROR(INDEX('[1]Anexos FICHA TRA050'!$C$49:$C$54, MATCH(Tabla467824[[#This Row],[Columna5]], '[1]Anexos FICHA TRA050'!$D$49:$D$54, 0)), "") -> 13073 | BH23: =+(((Tabla467824[[#This Row],[CVA2]]*Tabla467824[[#This Row],[f2]])-Tabla467824[[#This Row],[CVN2]])/100)*Tabla467824[[#This Row],[L2]] -> 6795.3454 | BK23: =+IF(Tabla467824[[#This Row],[F]]=Tabla467824[[#This Row],[f2]], "IGUAL", "DISTINTO") -> IGUAL | BL23: =+IF(Tabla467824[[#This Row],[CVN]]=Tabla467824[[#This Row],[CVN2]], "IGUAL", "DISTINTO") -> DISTINTO | BM23: =+IF(Tabla467824[[#This Row],[L]]=Tabla467824[[#This Row],[L2]], "IGUAL", "DISTINTO") -> IGUAL
A24: 21 | B24: CAE500044 | C24: 9431LKC | D24: M1 | E24: DIESEL | F24: DIESEL | G24: M1 | H24: X | J24: X | L24: X | M24: X | O24: AYVENS | P24: 1 | Q24: RENTING | R24: DEVUELTO | S24: 44133 | T24: 45594 | U24: 1461 | V24: 2024 | W24: 7 | X24: DIESEL | Y24: SEAT | Z24: ARONA 1.6 TDI 95 CV | AA24: 1001 | AB24: AVSA | AC24: 200300 | AD24: 6 | AE24: 6042MWV | AF24: CITROEN | AG24: Ë-C3 ELÉCTRICO MAX | AH24: ELECTRICO | AI24: 201510 | AJ24: 2024 | AK24: 45625 | AL24: 0 | AM24: 1001 | AN24: 4500424791 | AO24: AVSA | AQ24: X | AR24: COMUNIDAD VALENCIANA | AS24: VR7CBZYA0RT152183 | AT24: 5.1 | AU24: 10 | AV24: 16.4 | AW24: 13073 | AX24: 4523.258 | AY24: M1 | AZ24: CORRECTO ALQUILER | BA24: =+IF(Tabla467824[[#This Row],[TIPO VEHÍCULO]]=Tabla467824[[#This Row],[Columna2]], "IGUAL", "DISTINTO") -> IGUAL | BB24: =+IF(Tabla467824[[#This Row],[Columna4]]=Tabla467824[[#This Row],[Combustible2]], "IGUAL", "DISTINTO") -> IGUAL | BC24: CAE500044 | BD24: {=IFERROR(INDEX('[1]Anexos FICHA TRA050'!$D$27:$D$44, MATCH(Tabla467824[[#This Row],[Columna5]]&Tabla467824[[#This Row],[Columna4]], '[1]Anexos FICHA TRA050'!$E$27:$E$44&'[1]Anexos FICHA TRA050'!$F$27:$F$44, 0)), "")} -> 6.99 | BE24: =IFERROR(INDEX('[1]Anexos FICHA TRA050'!$B$4:$B$7, MATCH(Tabla467824[[#This Row],[Columna4]], '[1]Anexos FICHA TRA050'!$C$4:$C$7, 0)), "") -> 10 | BF24: =IFERROR(INDEX('[1]Anexos FICHA TRA050'!$C$14:$C$22, MATCH(Tabla467824[[#This Row],[Columna5]], '[1]Anexos FICHA TRA050'!$D$14:$D$22, 0)), "") -> 17.92 | BG24: =IFERROR(INDEX('[1]Anexos FICHA TRA050'!$C$49:$C$54, MATCH(Tabla467824[[#This Row],[Columna5]], '[1]Anexos FICHA TRA050'!$D$49:$D$54, 0)), "") -> 13073 | BH24: =+(((Tabla467824[[#This Row],[CVA2]]*Tabla467824[[#This Row],[f2]])-Tabla467824[[#This Row],[CVN2]])/100)*Tabla467824[[#This Row],[L2]] -> 6795.3454 | BK24: =+IF(Tabla467824[[#This Row],[F]]=Tabla467824[[#This Row],[f2]], "IGUAL", "DISTINTO") -> IGUAL | BL24: =+IF(Tabla467824[[#This Row],[CVN]]=Tabla467824[[#This Row],[CVN2]], "IGUAL", "DISTINTO") -> DISTINTO | BM24: =+IF(Tabla467824[[#This Row],[L]]=Tabla467824[[#This Row],[L2]], "IGUAL", "DISTINTO") -> IGUAL
A25: 22 | B25: CAE500045 | C25: 9494LKC | D25: M1 | E25: DIESEL | F25: DIESEL | G25: M1 | H25: X | J25: X | L25: X | M25: X | O25: AYVENS | P25: 1 | Q25: RENTING | R25: DEVUELTO | S25: 44133 | T25: 45594 | U25: 1461 | V25: 2024 | W25: 7 | X25: DIESEL | Y25: SEAT | Z25: ARONA 1.6 TDI 95 CV | AA25: 1001 | AB25: AVSA | AC25: 200542 | AD25: 7 | AE25: 6046MWV | AF25: CITROEN | AG25: Ë-C3 ELÉCTRICO MAX | AH25: ELECTRICO | AI25: 200560 | AJ25: 2024 | AK25: 45625 | AL25: 0 | AM25: 1001 | AN25: 4500424792 | AO25: AVSA | AQ25: X | AR25: COMUNIDAD VALENCIANA | AS25: VR7CBZYA9RT152182 | AT25: 5.1 | AU25: 10 | AV25: 16.4 | AW25: 13073 | AX25: 4523.258 | AY25: M1 | AZ25: CORRECTO ALQUILER | BA25: =+IF(Tabla467824[[#This Row],[TIPO VEHÍCULO]]=Tabla467824[[#This Row],[Columna2]], "IGUAL", "DISTINTO") -> IGUAL | BB25: =+IF(Tabla467824[[#This Row],[Columna4]]=Tabla467824[[#This Row],[Combustible2]], "IGUAL", "DISTINTO") -> IGUAL | BC25: CAE500045 | BD25: {=IFERROR(INDEX('[1]Anexos FICHA TRA050'!$D$27:$D$44, MATCH(Tabla467824[[#This Row],[Columna5]]&Tabla467824[[#This Row],[Columna4]], '[1]Anexos FICHA TRA050'!$E$27:$E$44&'[1]Anexos FICHA TRA050'!$F$27:$F$44, 0)), "")} -> 6.99 | BE25: =IFERROR(INDEX('[1]Anexos FICHA TRA050'!$B$4:$B$7, MATCH(Tabla467824[[#This Row],[Columna4]], '[1]Anexos FICHA TRA050'!$C$4:$C$7, 0)), "") -> 10 | BF25: =IFERROR(INDEX('[1]Anexos FICHA TRA050'!$C$14:$C$22, MATCH(Tabla467824[[#This Row],[Columna5]], '[1]Anexos FICHA TRA050'!$D$14:$D$22, 0)), "") -> 17.92 | BG25: =IFERROR(INDEX('[1]Anexos FICHA TRA050'!$C$49:$C$54, MATCH(Tabla467824[[#This Row],[Columna5]], '[1]Anexos FICHA TRA050'!$D$49:$D$54, 0)), "") -> 13073 | BH25: =+(((Tabla467824[[#This Row],[CVA2]]*Tabla467824[[#This Row],[f2]])-Tabla467824[[#This Row],[CVN2]])/100)*Tabla467824[[#This Row],[L2]] -> 6795.3454 | BK25: =+IF(Tabla467824[[#This Row],[F]]=Tabla467824[[#This Row],[f2]], "IGUAL", "DISTINTO") -> IGUAL | BL25: =+IF(Tabla467824[[#This Row],[CVN]]=Tabla467824[[#This Row],[CVN2]], "IGUAL", "DISTINTO") -> DISTINTO | BM25: =+IF(Tabla467824[[#This Row],[L]]=Tabla467824[[#This Row],[L2]], "IGUAL", "DISTINTO") -> IGUAL
A26: 23 | B26: CAE500046 | C26: 0818LKK | D26: M1 | E26: DIESEL | F26: DIESEL | G26: M1 | H26: X | J26: X | L26: X | M26: X | O26: AYVENS | P26: 1 | Q26: RENTING | R26: DEVUELTO | S26: 44134 | T26: 45595 | U26: 1461 | V26: 2024 | W26: 7 | X26: DIESEL | Y26: SEAT | Z26: ARONA 1.6 TDI 95 CV | AA26: 1021 | AB26: MEDICION AVANZADA CONTAD. | AC26: 357108 | AD26: 8 | AE26: 6492MWV | AF26: CITROEN | AG26: Ë-C3 ELÉCTRICO MAX | AH26: ELECTRICO | AI26: 357108 | AJ26: 2024 | AK26: 45625 | AL26: 0 | AM26: 1021 | AN26: 4500424794 | AO26: MEDICION AVANZADA CONTAD. | AQ26: X | AR26: COMUNIDAD VALENCIANA | AS26: VR7CBZYA5RT154429 | AT26: 5.1 | AU26: 10 | AV26: 16.4 | AW26: 13073 | AX26: 4523.258 | AY26: M1 | AZ26: CORRECTO ALQUILER | BA26: =+IF(Tabla467824[[#This Row],[TIPO VEHÍCULO]]=Tabla467824[[#This Row],[Columna2]], "IGUAL", "DISTINTO") -> IGUAL | BB26: =+IF(Tabla467824[[#This Row],[Columna4]]=Tabla467824[[#This Row],[Combustible2]], "IGUAL", "DISTINTO") -> IGUAL | BC26: CAE500046 | BD26: {=IFERROR(INDEX('[1]Anexos FICHA TRA050'!$D$27:$D$44, MATCH(Tabla467824[[#This Row],[Columna5]]&Tabla467824[[#This Row],[Columna4]], '[1]Anexos FICHA TRA050'!$E$27:$E$44&'[1]Anexos FICHA TRA050'!$F$27:$F$44, 0)), "")} -> 6.99 | BE26: =IFERROR(INDEX('[1]Anexos FICHA TRA050'!$B$4:$B$7, MATCH(Tabla467824[[#This Row],[Columna4]], '[1]Anexos FICHA TRA050'!$C$4:$C$7, 0)), "") -> 10 | BF26: =IFERROR(INDEX('[1]Anexos FICHA TRA050'!$C$14:$C$22, MATCH(Tabla467824[[#This Row],[Columna5]], '[1]Anexos FICHA TRA050'!$D$14:$D$22, 0)), "") -> 17.92 | BG26: =IFERROR(INDEX('[1]Anexos FICHA TRA050'!$C$49:$C$54, MATCH(Tabla467824[[#This Row],[Columna5]], '[1]Anexos FICHA TRA050'!$D$49:$D$54, 0)), "") -> 13073 | BH26: =+(((Tabla467824[[#This Row],[CVA2]]*Tabla467824[[#This Row],[f2]])-Tabla467824[[#This Row],[CVN2]])/100)*Tabla467824[[#This Row],[L2]] -> 6795.3454 | BK26: =+IF(Tabla467824[[#This Row],[F]]=Tabla467824[[#This Row],[f2]], "IGUAL", "DISTINTO") -> IGUAL | BL26: =+IF(Tabla467824[[#This Row],[CVN]]=Tabla467824[[#This Row],[CVN2]], "IGUAL", "DISTINTO") -> DISTINTO | BM26: =+IF(Tabla467824[[#This Row],[L]]=Tabla467824[[#This Row],[L2]], "IGUAL", "DISTINTO") -> IGUAL
A27: 24 | B27: CAE500047 | C27: 4170LKY | D27: M1 | E27: DIESEL | F27: DIESEL | G27: M1 | H27: X | J27: X | L27: X | M27: X | O27: AYVENS | P27: 1 | Q27: RENTING | R27: DEVUELTO | S27: 44166 | T27: 45627 | U27: 1461 | V27: 2024 | W27: 7 | X27: DIESEL | Y27: SEAT | Z27: ARONA 1.6 TDI 95 CV | AA27: 1200 | AB27: EMIVASA | AC27: 12009060 | AD27: 4 | AE27: 3121MWZ | AF27: CITROEN | AG27: Ë-C3 ELÉCTRICO MAX | AH27: ELECTRICO | AI27: 100041 | AJ27: 2024 | AK27: 45638 | AL27: 0 | AM27: 1200 | AN27: 4500424898 | AO27: EMIVASA | AQ27: X | AR27: COMUNIDAD VALENCIANA | AS27: VR7CBZYA1RT153035 | AT27: 5.1 | AU27: 10 | AV27: 16.4 | AW27: 13073 | AX27: 4523.258 | AY27: M1 | AZ27: CORRECTO ALQUILER | BA27: =+IF(Tabla467824[[#This Row],[TIPO VEHÍCULO]]=Tabla467824[[#This Row],[Columna2]], "IGUAL", "DISTINTO") -> IGUAL | BB27: =+IF(Tabla467824[[#This Row],[Columna4]]=Tabla467824[[#This Row],[Combustible2]], "IGUAL", "DISTINTO") -> IGUAL | BC27: CAE500047 | BD27: {=IFERROR(INDEX('[1]Anexos FICHA TRA050'!$D$27:$D$44, MATCH(Tabla467824[[#This Row],[Columna5]]&Tabla467824[[#This Row],[Columna4]], '[1]Anexos FICHA TRA050'!$E$27:$E$44&'[1]Anexos FICHA TRA050'!$F$27:$F$44, 0)), "")} -> 6.99 | BE27: =IFERROR(INDEX('[1]Anexos FICHA TRA050'!$B$4:$B$7, MATCH(Tabla467824[[#This Row],[Columna4]], '[1]Anexos FICHA TRA050'!$C$4:$C$7, 0)), "") -> 10 | BF27: =IFERROR(INDEX('[1]Anexos FICHA TRA050'!$C$14:$C$22, MATCH(Tabla467824[[#This Row],[Columna5]], '[1]Anexos FICHA TRA050'!$D$14:$D$22, 0)), "") -> 17.92 | BG27: =IFERROR(INDEX('[1]Anexos FICHA TRA050'!$C$49:$C$54, MATCH(Tabla467824[[#This Row],[Columna5]], '[1]Anexos FICHA TRA050'!$D$49:$D$54, 0)), "") -> 13073 | BH27: =+(((Tabla467824[[#This Row],[CVA2]]*Tabla467824[[#This Row],[f2]])-Tabla467824[[#This Row],[CVN2]])/100)*Tabla467824[[#This Row],[L2]] -> 6795.3454 | BK27: =+IF(Tabla467824[[#This Row],[F]]=Tabla467824[[#This Row],[f2]], "IGUAL", "DISTINTO") -> IGUAL | BL27: =+IF(Tabla467824[[#This Row],[CVN]]=Tabla467824[[#This Row],[CVN2]], "IGUAL", "DISTINTO") -> DISTINTO | BM27: =+IF(Tabla467824[[#This Row],[L]]=Tabla467824[[#This Row],[L2]], "IGUAL", "DISTINTO") -> IGUAL
A28: 25 | B28: CAE500050 | C28: 8030LKY | D28: M1 | E28: DIESEL | F28: DIESEL | G28: M1 | H28: X | J28: X | L28: X | M28: X | O28: AYVENS | P28: 1 | Q28: RENTING | R28: DEVUELTO | S28: 44166 | T28: 45627 | U28: 1461 | V28: 2024 | W28: 7 | X28: DIESEL | Y28: SEAT | Z28: ARONA 1.6 TDI 95 CV | AA28: 1021 | AB28: MEDICION AVANZADA CONTAD. | AC28: 357107 | AD28: 9 | AE28: 6493MWV | AF28: CITROEN | AG28: Ë-C3 ELÉCTRICO MAX | AH28: ELECTRICO | AI28: 357107 | AJ28: 2024 | AK28: 45625 | AL28: 0 | AM28: 1021 | AN28: 4500424809 | AO28: MEDICION AVANZADA CONTAD. | AQ28: X | AR28: COMUNIDAD VALENCIANA | AS28: VR7CBZYA2RT152198 | AT28: 5.1 | AU28: 10 | AV28: 16.4 | AW28: 13073 | AX28: 4523.258 | AY28: M1 | AZ28: CORRECTO ALQUILER | BA28: =+IF(Tabla467824[[#This Row],[TIPO VEHÍCULO]]=Tabla467824[[#This Row],[Columna2]], "IGUAL", "DISTINTO") -> IGUAL | BB28: =+IF(Tabla467824[[#This Row],[Columna4]]=Tabla467824[[#This Row],[Combustible2]], "IGUAL", "DISTINTO") -> IGUAL | BC28: CAE500050 | BD28: {=IFERROR(INDEX('[1]Anexos FICHA TRA050'!$D$27:$D$44, MATCH(Tabla467824[[#This Row],[Columna5]]&Tabla467824[[#This Row],[Columna4]], '[1]Anexos FICHA TRA050'!$E$27:$E$44&'[1]Anexos FICHA TRA050'!$F$27:$F$44, 0)), "")} -> 6.99 | BE28: =IFERROR(INDEX('[1]Anexos FICHA TRA050'!$B$4:$B$7, MATCH(Tabla467824[[#This Row],[Columna4]], '[1]Anexos FICHA TRA050'!$C$4:$C$7, 0)), "") -> 10 | BF28: =IFERROR(INDEX('[1]Anexos FICHA TRA050'!$C$14:$C$22, MATCH(Tabla467824[[#This Row],[Columna5]], '[1]Anexos FICHA TRA050'!$D$14:$D$22, 0)), "") -> 17.92 | BG28: =IFERROR(INDEX('[1]Anexos FICHA TRA050'!$C$49:$C$54, MATCH(Tabla467824[[#This Row],[Columna5]], '[1]Anexos FICHA TRA050'!$D$49:$D$54, 0)), "") -> 13073 | BH28: =+(((Tabla467824[[#This Row],[CVA2]]*Tabla467824[[#This Row],[f2]])-Tabla467824[[#This Row],[CVN2]])/100)*Tabla467824[[#This Row],[L2]] -> 6795.3454 | BK28: =+IF(Tabla467824[[#This Row],[F]]=Tabla467824[[#This Row],[f2]], "IGUAL", "DISTINTO") -> IGUAL | BL28: =+IF(Tabla467824[[#This Row],[CVN]]=Tabla467824[[#This Row],[CVN2]], "IGUAL", "DISTINTO") -> DISTINTO | BM28: =+IF(Tabla467824[[#This Row],[L]]=Tabla467824[[#This Row],[L2]], "IGUAL", "DISTINTO") -> IGUAL
A29: 26 | B29: CAE500051 | C29: 8066LKY | D29: M1 | E29: DIESEL | F29: DIESEL | G29: M1 | H29: X | J29: X | L29: X | M29: X | O29: AYVENS | P29: 1 | Q29: RENTING | R29: DEVUELTO | S29: 44166 | T29: 45627 | U29: 1461 | V29: 2024 | W29: 7 | X29: DIESEL | Y29: SEAT | Z29: ARONA 1.6 TDI 95 CV | AA29: 1200 | AB29: EMIVASA | AC29: 12009060 | AD29: 5 | AE29: 3122MWZ | AF29: CITROEN | AG29: Ë-C3 ELÉCTRICO MAX | AH29: ELECTRICO | AI29: 200028 | AJ29: 2024 | AK29: 45638 | AL29: 0 | AM29: 1200 | AN29: 4500424889 | AO29: EMIVASA | AQ29: X | AR29: COMUNIDAD VALENCIANA | AS29: VR7CBZYA7RT154433 | AT29: 5.1 | AU29: 10 | AV29: 16.4 | AW29: 13073 | AX29: 4523.258 | AY29: M1 | AZ29: CORRECTO ALQUILER | BA29: =+IF(Tabla467824[[#This Row],[TIPO VEHÍCULO]]=Tabla467824[[#This Row],[Columna2]], "IGUAL", "DISTINTO") -> IGUAL | BB29: =+IF(Tabla467824[[#This Row],[Columna4]]=Tabla467824[[#This Row],[Combustible2]], "IGUAL", "DISTINTO") -> IGUAL | BC29: CAE500051 | BD29: {=IFERROR(INDEX('[1]Anexos FICHA TRA050'!$D$27:$D$44, MATCH(Tabla467824[[#This Row],[Columna5]]&Tabla467824[[#This Row],[Columna4]], '[1]Anexos FICHA TRA050'!$E$27:$E$44&'[1]Anexos FICHA TRA050'!$F$27:$F$44, 0)), "")} -> 6.99 | BE29: =IFERROR(INDEX('[1]Anexos FICHA TRA050'!$B$4:$B$7, MATCH(Tabla467824[[#This Row],[Columna4]], '[1]Anexos FICHA TRA050'!$C$4:$C$7, 0)), "") -> 10 | BF29: =IFERROR(INDEX('[1]Anexos FICHA TRA050'!$C$14:$C$22, MATCH(Tabla467824[[#This Row],[Columna5]], '[1]Anexos FICHA TRA050'!$D$14:$D$22, 0)), "") -> 17.92 | BG29: =IFERROR(INDEX('[1]Anexos FICHA TRA050'!$C$49:$C$54, MATCH(Tabla467824[[#This Row],[Columna5]], '[1]Anexos FICHA TRA050'!$D$49:$D$54, 0)), "") -> 13073 | BH29: =+(((Tabla467824[[#This Row],[CVA2]]*Tabla467824[[#This Row],[f2]])-Tabla467824[[#This Row],[CVN2]])/100)*Tabla467824[[#This Row],[L2]] -> 6795.3454 | BK29: =+IF(Tabla467824[[#This Row],[F]]=Tabla467824[[#This Row],[f2]], "IGUAL", "DISTINTO") -> IGUAL | BL29: =+IF(Tabla467824[[#This Row],[CVN]]=Tabla467824[[#This Row],[CVN2]], "IGUAL", "DISTINTO") -> DISTINTO | BM29: =+IF(Tabla467824[[#This Row],[L]]=Tabla467824[[#This Row],[L2]], "IGUAL", "DISTINTO") -> IGUAL
A30: 27 | B30: CAE500054 | C30: 0269LLK | D30: M1 | E30: DIESEL | F30: DIESEL | G30: M1 | H30: X | J30: X | L30: X | M30: X | O30: AYVENS | P30: 1 | Q30: RENTING | R30: DEVUELTO | S30: 44179 | T30: 45640 | U30: 1461 | V30: 2024 | W30: 7 | X30: DIESEL | Y30: SEAT | Z30: ARONA 1.6 TDI 95 CV | AA30: 1001 | AB30: AVSA | AC30: 201701 | AD30: 8 | AE30: 6094MWV | AF30: CITROEN | AG30: Ë-C3 ELÉCTRICO MAX | AH30: ELECTRICO | AI30: 200317 | AJ30: 2024 | AK30: 45625 | AL30: 0 | AM30: 1001 | AN30: 4500426700 | AO30: AVSA | AQ30: X | AR30: COMUNIDAD VALENCIANA | AS30: VR7CBZYA4ST000168 | AT30: 5.1 | AU30: 10 | AV30: 16.4 | AW30: 13073 | AX30: 4523.258 | AY30: M1 | AZ30: CORRECTO ALQUILER | BA30: =+IF(Tabla467824[[#This Row],[TIPO VEHÍCULO]]=Tabla467824[[#This Row],[Columna2]], "IGUAL", "DISTINTO") -> IGUAL | BB30: =+IF(Tabla467824[[#This Row],[Columna4]]=Tabla467824[[#This Row],[Combustible2]], "IGUAL", "DISTINTO") -> IGUAL | BC30: CAE500054 | BD30: {=IFERROR(INDEX('[1]Anexos FICHA TRA050'!$D$27:$D$44, MATCH(Tabla467824[[#This Row],[Columna5]]&Tabla467824[[#This Row],[Columna4]], '[1]Anexos FICHA TRA050'!$E$27:$E$44&'[1]Anexos FICHA TRA050'!$F$27:$F$44, 0)), "")} -> 6.99 | BE30: =IFERROR(INDEX('[1]Anexos FICHA TRA050'!$B$4:$B$7, MATCH(Tabla467824[[#This Row],[Columna4]], '[1]Anexos FICHA TRA050'!$C$4:$C$7, 0)), "") -> 10 | BF30: =IFERROR(INDEX('[1]Anexos FICHA TRA050'!$C$14:$C$22, MATCH(Tabla467824[[#This Row],[Columna5]], '[1]Anexos FICHA TRA050'!$D$14:$D$22, 0)), "") -> 17.92 | BG30: =IFERROR(INDEX('[1]Anexos FICHA TRA050'!$C$49:$C$54, MATCH(Tabla467824[[#This Row],[Columna5]], '[1]Anexos FICHA TRA050'!$D$49:$D$54, 0)), "") -> 13073 | BH30: =+(((Tabla467824[[#This Row],[CVA2]]*Tabla467824[[#This Row],[f2]])-Tabla467824[[#This Row],[CVN2]])/100)*Tabla467824[[#This Row],[L2]] -> 6795.3454 | BK30: =+IF(Tabla467824[[#This Row],[F]]=Tabla467824[[#This Row],[f2]], "IGUAL", "DISTINTO") -> IGUAL | BL30: =+IF(Tabla467824[[#This Row],[CVN]]=Tabla467824[[#This Row],[CVN2]], "IGUAL", "DISTINTO") -> DISTINTO | BM30: =+IF(Tabla467824[[#This Row],[L]]=Tabla467824[[#This Row],[L2]], "IGUAL", "DISTINTO") -> IGUAL
A31: 28 | B31: CAE500055 | C31: 9413LKC | D31: M1 | E31: DIESEL | F31: DIESEL | G31: M1 | H31: X | J31: X | L31: X | M31: X | O31: AYVENS | P31: 1 | Q31: RENTING | R31: DEVUELTO | S31: 44153 | T31: 45614 | U31: 1461 | V31: 2024 | W31: 7 | X31: DIESEL | Y31: SEAT | Z31: ARONA 1.6 TDI 95 CV | AA31: 1505 | AB31: CGAC | AC31: 205567 | AD31: 3 | AE31: 8606MWT | AF31: RENAULT | AG31: KANGOO VAN E-TECH ELECTRIC | AH31: ELECTRICO | AI31: 355577 | AJ31: 2024 | AK31: 45625 | AL31: 0 | AM31: 1505 | AN31: 4500426774 | AO31: CGAC | AQ31: X | AR31: CATALUÑA | AS31: VF1RFK00073824797 | AT31: 5.1 | AU31: 10 | AV31: 17.3 | AW31: 13073 | AX31: 4405.601 | AY31: M1 | AZ31: CORRECTO ALQUILER | BA31: =+IF(Tabla467824[[#This Row],[TIPO VEHÍCULO]]=Tabla467824[[#This Row],[Columna2]], "IGUAL", "DISTINTO") -> IGUAL | BB31: =+IF(Tabla467824[[#This Row],[Columna4]]=Tabla467824[[#This Row],[Combustible2]], "IGUAL", "DISTINTO") -> IGUAL | BC31: CAE500055 | BD31: {=IFERROR(INDEX('[1]Anexos FICHA TRA050'!$D$27:$D$44, MATCH(Tabla467824[[#This Row],[Columna5]]&Tabla467824[[#This Row],[Columna4]], '[1]Anexos FICHA TRA050'!$E$27:$E$44&'[1]Anexos FICHA TRA050'!$F$27:$F$44, 0)), "")} -> 6.99 | BE31: =IFERROR(INDEX('[1]Anexos FICHA TRA050'!$B$4:$B$7, MATCH(Tabla467824[[#This Row],[Columna4]], '[1]Anexos FICHA TRA050'!$C$4:$C$7, 0)), "") -> 10 | BF31: =IFERROR(INDEX('[1]Anexos FICHA TRA050'!$C$14:$C$22, MATCH(Tabla467824[[#This Row],[Columna5]], '[1]Anexos FICHA TRA050'!$D$14:$D$22, 0)), "") -> 17.92 | BG31: =IFERROR(INDEX('[1]Anexos FICHA TRA050'!$C$49:$C$54, MATCH(Tabla467824[[#This Row],[Columna5]], '[1]Anexos FICHA TRA050'!$D$49:$D$54, 0)), "") -> 13073 | BH31: =+(((Tabla467824[[#This Row],[CVA2]]*Tabla467824[[#This Row],[f2]])-Tabla467824[[#This Row],[CVN2]])/100)*Tabla467824[[#This Row],[L2]] -> 6795.3454 | BK31: =+IF(Tabla467824[[#This Row],[F]]=Tabla467824[[#This Row],[f2]], "IGUAL", "DISTINTO") -> IGUAL | BL31: =+IF(Tabla467824[[#This Row],[CVN]]=Tabla467824[[#This Row],[CVN2]], "IGUAL", "DISTINTO") -> DISTINTO | BM31: =+IF(Tabla467824[[#This Row],[L]]=Tabla467824[[#This Row],[L2]], "IGUAL", "DISTINTO") -> IGUAL
A32: 29 | B32: CAE500056 | C32: 9455LKC | D32: M1 | E32: DIESEL | F32: DIESEL | G32: M1 | H32: X | J32: X | L32: X | M32: X | O32: AYVENS | P32: 1 | Q32: RENTING | R32: DEVUELTO | S32: 44153 | T32: 45614 | U32: 1461 | V32: 2024 | W32: 7 | X32: DIESEL | Y32: SEAT | Z32: ARONA 1.6 TDI 95 CV | AA32: 1064 | AB32: AYWA SER.AMBIENTALES SL | AC32: 10649080 | AD32: 1 | AE32: 3147MXJ | AF32: RENAULT | AG32: KANGOO VAN E-TECH ELECTRIC | AH32: ELECTRICO | AI32: DEFINIR | AJ32: 2024 | AK32: 45649 | AL32: 0 | AM32: 1064 | AN32: X | AO32: AYWA SER.AMBIENTALES SL | AQ32: X | AR32: COMUNIDAD VALENCIANA | AS32: VF1RFK00073934300 | AT32: 5.1 | AU32: 10 | AV32: 17.3 | AW32: 13073 | AX32: 4405.601 | AY32: M1 | AZ32: CORRECTO ALQUILER | BA32: =+IF(Tabla467824[[#This Row],[TIPO VEHÍCULO]]=Tabla467824[[#This Row],[Columna2]], "IGUAL", "DISTINTO") -> IGUAL | BB32: =+IF(Tabla467824[[#This Row],[Columna4]]=Tabla467824[[#This Row],[Combustible2]], "IGUAL", "DISTINTO") -> IGUAL | BC32: CAE500056 | BD32: {=IFERROR(INDEX('[1]Anexos FICHA TRA050'!$D$27:$D$44, MATCH(Tabla467824[[#This Row],[Columna5]]&Tabla467824[[#This Row],[Columna4]], '[1]Anexos FICHA TRA050'!$E$27:$E$44&'[1]Anexos FICHA TRA050'!$F$27:$F$44, 0)), "")} -> 6.99 | BE32: =IFERROR(INDEX('[1]Anexos FICHA TRA050'!$B$4:$B$7, MATCH(Tabla467824[[#This Row],[Columna4]], '[1]Anexos FICHA TRA050'!$C$4:$C$7, 0)), "") -> 10 | BF32: =IFERROR(INDEX('[1]Anexos FICHA TRA050'!$C$14:$C$22, MATCH(Tabla467824[[#This Row],[Columna5]], '[1]Anexos FICHA TRA050'!$D$14:$D$22, 0)), "") -> 17.92 | BG32: =IFERROR(INDEX('[1]Anexos FICHA TRA050'!$C$49:$C$54, MATCH(Tabla467824[[#This Row],[Columna5]], '[1]Anexos FICHA TRA050'!$D$49:$D$54, 0)), "") -> 13073 | BH32: =+(((Tabla467824[[#This Row],[CVA2]]*Tabla467824[[#This Row],[f2]])-Tabla467824[[#This Row],[CVN2]])/100)*Tabla467824[[#This Row],[L2]] -> 6795.3454 | BK32: =+IF(Tabla467824[[#This Row],[F]]=Tabla467824[[#This Row],[f2]], "IGUAL", "DISTINTO") -> IGUAL | BL32: =+IF(Tabla467824[[#This Row],[CVN]]=Tabla467824[[#This Row],[CVN2]], "IGUAL", "DISTINTO") -> DISTINTO | BM32: =+IF(Tabla467824[[#This Row],[L]]=Tabla467824[[#This Row],[L2]], "IGUAL", "DISTINTO") -> IGUAL
A33: 30 | B33: CAE500057 | C33: 5243LKX | D33: M1 | E33: DIESEL | F33: DIESEL | G33: M1 | H33: X | J33: X | L33: X | M33: X | O33: AYVENS | P33: 1 | Q33: RENTING | R33: DEVUELTO | S33: 44166 | T33: 45627 | U33: 1461 | V33: 2024 | W33: 7 | X33: DIESEL | Y33: SEAT | Z33: ARONA 1.6 TDI 95 CV | AA33: 1066 | AB33: CANALIZ. CIVILES S.A. | AC33: 10669100 | AD33: 2 | AE33: 8658MWT | AF33: RENAULT | AG33: KANGOO VAN E-TECH ELECTRIC | AH33: ELECTRICO | AI33: 356006 | AJ33: 2024 | AK33: 45625 | AL33: 0 | AM33: 1066 | AN33: 4500426798 | AO33: CANALIZ. CIVILES S.A. | AQ33: X | AR33: COMUNIDAD VALENCIANA | AS33: VF1RFK00273824820 | AT33: 5.1 | AU33: 10 | AV33: 17.3 | AW33: 13073 | AX33: 4405.601 | AY33: M1 | AZ33: CORRECTO ALQUILER | BA33: =+IF(Tabla467824[[#This Row],[TIPO VEHÍCULO]]=Tabla467824[[#This Row],[Columna2]], "IGUAL", "DISTINTO") -> IGUAL | BB33: =+IF(Tabla467824[[#This Row],[Columna4]]=Tabla467824[[#This Row],[Combustible2]], "IGUAL", "DISTINTO") -> IGUAL | BC33: CAE500057 | BD33: {=IFERROR(INDEX('[1]Anexos FICHA TRA050'!$D$27:$D$44, MATCH(Tabla467824[[#This Row],[Columna5]]&Tabla467824[[#This Row],[Columna4]], '[1]Anexos FICHA TRA050'!$E$27:$E$44&'[1]Anexos FICHA TRA050'!$F$27:$F$44, 0)), "")} -> 6.99 | BE33: =IFERROR(INDEX('[1]Anexos FICHA TRA050'!$B$4:$B$7, MATCH(Tabla467824[[#This Row],[Columna4]], '[1]Anexos FICHA TRA050'!$C$4:$C$7, 0)), "") -> 10 | BF33: =IFERROR(INDEX('[1]Anexos FICHA TRA050'!$C$14:$C$22, MATCH(Tabla467824[[#This Row],[Columna5]], '[1]Anexos FICHA TRA050'!$D$14:$D$22, 0)), "") -> 17.92 | BG33: =IFERROR(INDEX('[1]Anexos FICHA TRA050'!$C$49:$C$54, MATCH(Tabla467824[[#This Row],[Columna5]], '[1]Anexos FICHA TRA050'!$D$49:$D$54, 0)), "") -> 13073 | BH33: =+(((Tabla467824[[#This Row],[CVA2]]*Tabla467824[[#This Row],[f2]])-Tabla467824[[#This Row],[CVN2]])/100)*Tabla467824[[#This Row],[L2]] -> 6795.3454 | BK33: =+IF(Tabla467824[[#This Row],[F]]=Tabla467824[[#This Row],[f2]], "IGUAL", "DISTINTO") -> IGUAL | BL33: =+IF(Tabla467824[[#This Row],[CVN]]=Tabla467824[[#This Row],[CVN2]], "IGUAL", "DISTINTO") -> DISTINTO | BM33: =+IF(Tabla467824[[#This Row],[L]]=Tabla467824[[#This Row],[L2]], "IGUAL", "DISTINTO") -> IGUAL
A34: 31 | B34: CAE500058 | C34: 5255LKX | D34: M1 | E34: DIESEL | F34: DIESEL | G34: M1 | H34: X | J34: X | L34: X | M34: X | O34: AYVENS | P34: 1 | Q34: RENTING | R34: DEVUELTO | S34: 44215 | T34: 45676 | U34: 1461 | V34: 2025 | W34: 7 | X34: DIESEL | Y34: SEAT | Z34: ARONA 1.6 TDI 95 CV | AA34: 1001 | AB34: AVSA | AC34: 200784 | AD34: 9 | AE34: 6370MXF | AF34: RENAULT | AG34: KANGOO VAN E-TECH ELECTRIC | AH34: ELECTRICO | AI34: 350535 | AJ34: 2024 | AK34: 45645 | AL34: -1 | AM34: 1001 | AN34: 4500426771 | AO34: AVSA | AQ34: X | AR34: COMUNIDAD VALENCIANA | AS34: VF1RFK00373824888 | AT34: 5.1 | AU34: 10 | AV34: 17.3 | AW34: 13073 | AX34: 4405.601 | AY34: M1 | AZ34: CORRECTO ALQUILER | BA34: =+IF(Tabla467824[[#This Row],[TIPO VEHÍCULO]]=Tabla467824[[#This Row],[Columna2]], "IGUAL", "DISTINTO") -> IGUAL | BB34: =+IF(Tabla467824[[#This Row],[Columna4]]=Tabla467824[[#This Row],[Combustible2]], "IGUAL", "DISTINTO") -> IGUAL | BC34: CAE500058 | BD34: {=IFERROR(INDEX('[1]Anexos FICHA TRA050'!$D$27:$D$44, MATCH(Tabla467824[[#This Row],[Columna5]]&Tabla467824[[#This Row],[Columna4]], '[1]Anexos FICHA TRA050'!$E$27:$E$44&'[1]Anexos FICHA TRA050'!$F$27:$F$44, 0)), "")} -> 6.99 | BE34: =IFERROR(INDEX('[1]Anexos FICHA TRA050'!$B$4:$B$7, MATCH(Tabla467824[[#This Row],[Columna4]], '[1]Anexos FICHA TRA050'!$C$4:$C$7, 0)), "") -> 10 | BF34: =IFERROR(INDEX('[1]Anexos FICHA TRA050'!$C$14:$C$22, MATCH(Tabla467824[[#This Row],[Columna5]], '[1]Anexos FICHA TRA050'!$D$14:$D$22, 0)), "") -> 17.92 | BG34: =IFERROR(INDEX('[1]Anexos FICHA TRA050'!$C$49:$C$54, MATCH(Tabla467824[[#This Row],[Columna5]], '[1]Anexos FICHA TRA050'!$D$49:$D$54, 0)), "") -> 13073 | BH34: =+(((Tabla467824[[#This Row],[CVA2]]*Tabla467824[[#This Row],[f2]])-Tabla467824[[#This Row],[CVN2]])/100)*Tabla467824[[#This Row],[L2]] -> 6795.3454 | BK34: =+IF(Tabla467824[[#This Row],[F]]=Tabla467824[[#This Row],[f2]], "IGUAL", "DISTINTO") -> IGUAL | BL34: =+IF(Tabla467824[[#This Row],[CVN]]=Tabla467824[[#This Row],[CVN2]], "IGUAL", "DISTINTO") -> DISTINTO | BM34: =+IF(Tabla467824[[#This Row],[L]]=Tabla467824[[#This Row],[L2]], "IGUAL", "DISTINTO") -> IGUAL
A35: 32 | B35: CAE500059 | C35: 9276LMB | D35: M1 | E35: DIESEL | F35: DIESEL | G35: M1 | H35: X | J35: X | L35: x | M35: x | O35: AYVENS | P35: 1 | Q35: RENTING | R35: DEVUELTO | S35: 44215 | T35: 45676 | U35: 1461 | V35: 2025 | W35: 7 | X35: DIESEL | Y35: SEAT | Z35: ARONA 1.6 TDI 95 CV | AA35: 1053 | AB35: ISG | AC35: 355528 | AD35: 2 | AE35: 8392MXG | AF35: RENAULT | AG35: KANGOO VAN E-TECH ELECTRIC | AH35: ELECTRICO | AI35: 355457 | AJ35: 2024 | AK35: 45646 | AL35: -1 | AM35: 1053 | AN35: 4500426874 | AO35: ISG | AQ35: X | AR35: COMUNIDAD VALENCIANA | AS35: VF1RFK00273934282 | AT35: 5.1 | AU35: 10 | AV35: 17.3 | AW35: 13073 | AX35: 4405.601 | AY35: M1 | AZ35: CORRECTO ALQUILER | BA35: =+IF(Tabla467824[[#This Row],[TIPO VEHÍCULO]]=Tabla467824[[#This Row],[Columna2]], "IGUAL", "DISTINTO") -> IGUAL | BB35: =+IF(Tabla467824[[#This Row],[Columna4]]=Tabla467824[[#This Row],[Combustible2]], "IGUAL", "DISTINTO") -> IGUAL | BC35: CAE500059 | BD35: {=IFERROR(INDEX('[1]Anexos FICHA TRA050'!$D$27:$D$44, MATCH(Tabla467824[[#This Row],[Columna5]]&Tabla467824[[#This Row],[Columna4]], '[1]Anexos FICHA TRA050'!$E$27:$E$44&'[1]Anexos FICHA TRA050'!$F$27:$F$44, 0)), "")} -> 6.99 | BE35: =IFERROR(INDEX('[1]Anexos FICHA TRA050'!$B$4:$B$7, MATCH(Tabla467824[[#This Row],[Columna4]], '[1]Anexos FICHA TRA050'!$C$4:$C$7, 0)), "") -> 10 | BF35: =IFERROR(INDEX('[1]Anexos FICHA TRA050'!$C$14:$C$22, MATCH(Tabla467824[[#This Row],[Columna5]], '[1]Anexos FICHA TRA050'!$D$14:$D$22, 0)), "") -> 17.92 | BG35: =IFERROR(INDEX('[1]Anexos FICHA TRA050'!$C$49:$C$54, MATCH(Tabla467824[[#This Row],[Columna5]], '[1]Anexos FICHA TRA050'!$D$49:$D$54, 0)), "") -> 13073 | BH35: =+(((Tabla467824[[#This Row],[CVA2]]*Tabla467824[[#This Row],[f2]])-Tabla467824[[#This Row],[CVN2]])/100)*Tabla467824[[#This Row],[L2]] -> 6795.3454 | BK35: =+IF(Tabla467824[[#This Row],[F]]=Tabla467824[[#This Row],[f2]], "IGUAL", "DISTINTO") -> IGUAL | BL35: =+IF(Tabla467824[[#This Row],[CVN]]=Tabla467824[[#This Row],[CVN2]], "IGUAL", "DISTINTO") -> DISTINTO | BM35: =+IF(Tabla467824[[#This Row],[L]]=Tabla467824[[#This Row],[L2]], "IGUAL", "DISTINTO") -> IGUAL
A36: 33 | B36: CAE500060 | C36: 4988LLY | D36: M1 | E36: DIESEL | F36: DIESEL | G36: M1 | H36: X | J36: X | L36: X | M36: X | O36: AYVENS | P36: 1 | Q36: RENTING | R36: DEVUELTO | S36: 44215 | T36: 45676 | U36: 1461 | V36: 2025 | W36: 7 | X36: DIESEL | Y36: SEAT | Z36: ARONA 1.6 TDI 95 CV | AA36: 1004 | AB36: G.O.MEDIOAMBIENTE S.L. | AC36: 204427 | AD36: 1 | AE36: 6051KRV | AF36: RENAULT | AG36: ZOE 40 | AH36: ELECTRICO | AI36: 724317 | AJ36: 2024 | AK36: 43435 | AL36: -1 | AM36: 1004 | AN36: 4500399254 | AO36: G.O.MEDIOAMBIENTE S.L. | AQ36: X | AR36: COMUNIDAD VALENCIANA | AS36: VF1AG000561226133 | AT36: 5.1 | AU36: 10 | AV36: 13.3 | AW36: 13073 | AX36: 4928.521 | AY36: M1 | AZ36: CORRECTO ALQUILER | BA36: =+IF(Tabla467824[[#This Row],[TIPO VEHÍCULO]]=Tabla467824[[#This Row],[Columna2]], "IGUAL", "DISTINTO") -> IGUAL | BB36: =+IF(Tabla467824[[#This Row],[Columna4]]=Tabla467824[[#This Row],[Combustible2]], "IGUAL", "DISTINTO") -> IGUAL | BC36: CAE500060 | BD36: {=IFERROR(INDEX('[1]Anexos FICHA TRA050'!$D$27:$D$44, MATCH(Tabla467824[[#This Row],[Columna5]]&Tabla467824[[#This Row],[Columna4]], '[1]Anexos FICHA TRA050'!$E$27:$E$44&'[1]Anexos FICHA TRA050'!$F$27:$F$44, 0)), "")} -> 6.99 | BE36: =IFERROR(INDEX('[1]Anexos FICHA TRA050'!$B$4:$B$7, MATCH(Tabla467824[[#This Row],[Columna4]], '[1]Anexos FICHA TRA050'!$C$4:$C$7, 0)), "") -> 10 | BF36: =IFERROR(INDEX('[1]Anexos FICHA TRA050'!$C$14:$C$22, MATCH(Tabla467824[[#This Row],[Columna5]], '[1]Anexos FICHA TRA050'!$D$14:$D$22, 0)), "") -> 17.92 | BG36: =IFERROR(INDEX('[1]Anexos FICHA TRA050'!$C$49:$C$54, MATCH(Tabla467824[[#This Row],[Columna5]], '[1]Anexos FICHA TRA050'!$D$49:$D$54, 0)), "") -> 13073 | BH36: =+(((Tabla467824[[#This Row],[CVA2]]*Tabla467824[[#This Row],[f2]])-Tabla467824[[#This Row],[CVN2]])/100)*Tabla467824[[#This Row],[L2]] -> 6795.3454 | BK36: =+IF(Tabla467824[[#This Row],[F]]=Tabla467824[[#This Row],[f2]], "IGUAL", "DISTINTO") -> IGUAL | BL36: =+IF(Tabla467824[[#This Row],[CVN]]=Tabla467824[[#This Row],[CVN2]], "IGUAL", "DISTINTO") -> DISTINTO | BM36: =+IF(Tabla467824[[#This Row],[L]]=Tabla467824[[#This Row],[L2]], "IGUAL", "DISTINTO") -> IGUAL
A37: 34 | B37: CAE500061 | C37: 0251LLK | D37: M1 | E37: DIESEL | F37: DIESEL | G37: M1 | H37: X | J37: X | L37: X | M37: X | O37: AYVENS | P37: 1 | Q37: RENTING | R37: CANCELADO POR SINIESTRO | S37: 44237 | T37: 45698 | U37: 1461 | V37: 2025 | W37: 6 | X37: DIESEL | Y37: SEAT | Z37: ARONA 1.6 TDI 95 CV | AA37: 1053 | AB37: ISG | AC37: 355539 | AD37: 3 | AE37: 0602KHK | AF37: RENAULT | AG37: ZOE 40 | AH37: ELECTRICO | AI37: 355539 | AJ37: 2024 | AK37: 43140 | AL37: -1 | AM37: 1053 | AN37: 4500409585 | AO37: ISG | AQ37: X | AR37: COMUNIDAD VALENCIANA | AS37: VF1AGVYF059267878 | AT37: 5.1 | AU37: 10 | AV37: 13.3 | AW37: 13073 | AX37: 4928.521 | AY37: M1 | AZ37: CORRECTO ALQUILER | BA37: =+IF(Tabla467824[[#This Row],[TIPO VEHÍCULO]]=Tabla467824[[#This Row],[Columna2]], "IGUAL", "DISTINTO") -> IGUAL | BB37: =+IF(Tabla467824[[#This Row],[Columna4]]=Tabla467824[[#This Row],[Combustible2]], "IGUAL", "DISTINTO") -> IGUAL | BC37: CAE500061 | BD37: {=IFERROR(INDEX('[1]Anexos FICHA TRA050'!$D$27:$D$44, MATCH(Tabla467824[[#This Row],[Columna5]]&Tabla467824[[#This Row],[Columna4]], '[1]Anexos FICHA TRA050'!$E$27:$E$44&'[1]Anexos FICHA TRA050'!$F$27:$F$44, 0)), "")} -> 6.99 | BE37: =IFERROR(INDEX('[1]Anexos FICHA TRA050'!$B$4:$B$7, MATCH(Tabla467824[[#This Row],[Columna4]], '[1]Anexos FICHA TRA050'!$C$4:$C$7, 0)), "") -> 10 | BF37: =IFERROR(INDEX('[1]Anexos FICHA TRA050'!$C$14:$C$22, MATCH(Tabla467824[[#This Row],[Columna5]], '[1]Anexos FICHA TRA050'!$D$14:$D$22, 0)), "") -> 17.92 | BG37: =IFERROR(INDEX('[1]Anexos FICHA TRA050'!$C$49:$C$54, MATCH(Tabla467824[[#This Row],[Columna5]], '[1]Anexos FICHA TRA050'!$D$49:$D$54, 0)), "") -> 13073 | BH37: =+(((Tabla467824[[#This Row],[CVA2]]*Tabla467824[[#This Row],[f2]])-Tabla467824[[#This Row],[CVN2]])/100)*Tabla467824[[#This Row],[L2]] -> 6795.3454 | BK37: =+IF(Tabla467824[[#This Row],[F]]=Tabla467824[[#This Row],[f2]], "IGUAL", "DISTINTO") -> IGUAL | BL37: =+IF(Tabla467824[[#This Row],[CVN]]=Tabla467824[[#This Row],[CVN2]], "IGUAL", "DISTINTO") -> DISTINTO | BM37: =+IF(Tabla467824[[#This Row],[L]]=Tabla467824[[#This Row],[L2]], "IGUAL", "DISTINTO") -> IGUAL
A38: 35 | B38: CAE500064 | C38: 0246LLK | D38: M1 | E38: DIESEL | F38: DIESEL | G38: M1 | H38: X | J38: X | L38: X | M38: X | O38: AYVENS | P38: 1 | Q38: RENTING | R38: DEVUELTO | S38: 44186 | T38: 45647 | U38: 1461 | V38: 2024 | W38: 7 | X38: DIESEL | Y38: SEAT | Z38: ARONA 1.6 TDI 95 CV | AA38: 1004 | AB38: G.O.MEDIOAMBIENTE S.L. | AC38: 200101 | AD38: 2 | AE38: 6727LMH | AF38: SILENCE | AG38: SEAT MO E 125 CC | AH38: ELECTRICO | AI38: 724236 | AJ38: 2024 | AK38: 45391 | AL38: 0 | AM38: 1004 | AN38: 4500398936 | AO38: G.O.MEDIOAMBIENTE S.L. | AQ38: X | AR38: COMUNIDAD VALENCIANA | AS38: UCYS01S0ZMB000266 | AT38: 5.1 | AU38: 10 | AV38: 7 | AW38: 13073 | AX38: 5752.12 | AY38: M1 | AZ38: CORRECTO ALQUILER | BA38: =+IF(Tabla467824[[#This Row],[TIPO VEHÍCULO]]=Tabla467824[[#This Row],[Columna2]], "IGUAL", "DISTINTO") -> IGUAL | BB38: =+IF(Tabla467824[[#This Row],[Columna4]]=Tabla467824[[#This Row],[Combustible2]], "IGUAL", "DISTINTO") -> IGUAL | BC38: CAE500064 | BD38: {=IFERROR(INDEX('[1]Anexos FICHA TRA050'!$D$27:$D$44, MATCH(Tabla467824[[#This Row],[Columna5]]&Tabla467824[[#This Row],[Columna4]], '[1]Anexos FICHA TRA050'!$E$27:$E$44&'[1]Anexos FICHA TRA050'!$F$27:$F$44, 0)), "")} -> 6.99 | BE38: =IFERROR(INDEX('[1]Anexos FICHA TRA050'!$B$4:$B$7, MATCH(Tabla467824[[#This Row],[Columna4]], '[1]Anexos FICHA TRA050'!$C$4:$C$7, 0)), "") -> 10 | BF38: =IFERROR(INDEX('[1]Anexos FICHA TRA050'!$C$14:$C$22, MATCH(Tabla467824[[#This Row],[Columna5]], '[1]Anexos FICHA TRA050'!$D$14:$D$22, 0)), "") -> 17.92 | BG38: =IFERROR(INDEX('[1]Anexos FICHA TRA050'!$C$49:$C$54, MATCH(Tabla467824[[#This Row],[Columna5]], '[1]Anexos FICHA TRA050'!$D$49:$D$54, 0)), "") -> 13073 | BH38: =+(((Tabla467824[[#This Row],[CVA2]]*Tabla467824[[#This Row],[f2]])-Tabla467824[[#This Row],[CVN2]])/100)*Tabla467824[[#This Row],[L2]] -> 6795.3454 | BK38: =+IF(Tabla467824[[#This Row],[F]]=Tabla467824[[#This Row],[f2]], "IGUAL", "DISTINTO") -> IGUAL | BL38: =+IF(Tabla467824[[#This Row],[CVN]]=Tabla467824[[#This Row],[CVN2]], "IGUAL", "DISTINTO") -> DISTINTO | BM38: =+IF(Tabla467824[[#This Row],[L]]=Tabla467824[[#This Row],[L2]], "IGUAL", "DISTINTO") -> IGUAL
A39: 36 | B39: CAE500065 | C39: 4456KVD | D39: M1 | E39: DIESEL | F39: DIESEL | G39: M1 | H39: X | I39: X | J39: X | L39: X | M39: X | O39: AYVENS | P39: 1 | Q39: RENTING | R39: DEVUELTO | S39: 43578 | T39: 45039 | U39: 1461 | V39: 2023 | W39: 7 | X39: DIESEL | Y39: OPEL | Z39: ASTRA 1.6 CDTI 110 CV | AA39: 1066 | AB39: CANALIZ. CIVILES S.A. | AC39: 10669101 | AD39: 3 | AE39: 6022MWV | AF39: CITROEN | AG39: Ë-C3 ELÉCTRICO MAX | AH39: ELECTRICO | AI39: 10669120 | AJ39: 2024 | AK39: 45625 | AL39: 1 | AM39: 1066 | AN39: 4500426701 | AO39: CANALIZ. CIVILES S.A. | AQ39: X | AR39: COMUNIDAD VALENCIANA | AS39: VR7CBZYA1ST000158 | AT39: 5.1 | AU39: 10 | AV39: 16.4 | AW39: 13073 | AX39: 4523.258 | AY39: M1 | AZ39: CORRECTO ALQUILER | BA39: =+IF(Tabla467824[[#This Row],[TIPO VEHÍCULO]]=Tabla467824[[#This Row],[Columna2]], "IGUAL", "DISTINTO") -> IGUAL | BB39: =+IF(Tabla467824[[#This Row],[Columna4]]=Tabla467824[[#This Row],[Combustible2]], "IGUAL", "DISTINTO") -> IGUAL | BC39: CAE500065 | BD39: {=IFERROR(INDEX('[1]Anexos FICHA TRA050'!$D$27:$D$44, MATCH(Tabla467824[[#This Row],[Columna5]]&Tabla467824[[#This Row],[Columna4]], '[1]Anexos FICHA TRA050'!$E$27:$E$44&'[1]Anexos FICHA TRA050'!$F$27:$F$44, 0)), "")} -> 6.99 | BE39: =IFERROR(INDEX('[1]Anexos FICHA TRA050'!$B$4:$B$7, MATCH(Tabla467824[[#This Row],[Columna4]], '[1]Anexos FICHA TRA050'!$C$4:$C$7, 0)), "") -> 10 | BF39: =IFERROR(INDEX('[1]Anexos FICHA TRA050'!$C$14:$C$22, MATCH(Tabla467824[[#This Row],[Columna5]], '[1]Anexos FICHA TRA050'!$D$14:$D$22, 0)), "") -> 17.92 | BG39: =IFERROR(INDEX('[1]Anexos FICHA TRA050'!$C$49:$C$54, MATCH(Tabla467824[[#This Row],[Columna5]], '[1]Anexos FICHA TRA050'!$D$49:$D$54, 0)), "") -> 13073 | BH39: =+(((Tabla467824[[#This Row],[CVA2]]*Tabla467824[[#This Row],[f2]])-Tabla467824[[#This Row],[CVN2]])/100)*Tabla467824[[#This Row],[L2]] -> 6795.3454 | BK39: =+IF(Tabla467824[[#This Row],[F]]=Tabla467824[[#This Row],[f2]], "IGUAL", "DISTINTO") -> IGUAL | BL39: =+IF(Tabla467824[[#This Row],[CVN]]=Tabla467824[[#This Row],[CVN2]], "IGUAL", "DISTINTO") -> DISTINTO | BM39: =+IF(Tabla467824[[#This Row],[L]]=Tabla467824[[#This Row],[L2]], "IGUAL", "DISTINTO") -> IGUAL
A40: 37 | B40: CAE500066 | C40: 8298KZS | D40: M1 | E40: DIESEL | F40: DIESEL | G40: M1 | H40: X | J40: X | L40: X | M40: X | O40: AYVENS | P40: 1 | Q40: RENTING | R40: DEVUELTO | S40: 43726 | T40: 45553 | U40: 1827 | V40: 2024 | W40: 7 | X40: DIESEL | Y40: OPEL | Z40: ASTRA 1.6 CDTI 110 CV | AA40: 1001 | AB40: AVSA | AC40: 10019946 | AD40: 10 | AE40: 6007MWV | AF40: CITROEN | AG40: Ë-C3 ELÉCTRICO MAX | AH40: ELECTRICO | AI40: 200738 | AJ40: 2024 | AK40: 45622 | AL40: 0 | AM40: 1001 | AN40: 4500424789 | AO40: AVSA | AQ40: X | AR40: COMUNIDAD VALENCIANA | AS40: VR7CBZYA9RT152179 | AT40: 5.1 | AU40: 10 | AV40: 16.4 | AW40: 13073 | AX40: 4523.258 | AY40: M1 | AZ40: CORRECTO ALQUILER | BA40: =+IF(Tabla467824[[#This Row],[TIPO VEHÍCULO]]=Tabla467824[[#This Row],[Columna2]], "IGUAL", "DISTINTO") -> IGUAL | BB40: =+IF(Tabla467824[[#This Row],[Columna4]]=Tabla467824[[#This Row],[Combustible2]], "IGUAL", "DISTINTO") -> IGUAL | BC40: CAE500066 | BD40: {=IFERROR(INDEX('[1]Anexos FICHA TRA050'!$D$27:$D$44, MATCH(Tabla467824[[#This Row],[Columna5]]&Tabla467824[[#This Row],[Columna4]], '[1]Anexos FICHA TRA050'!$E$27:$E$44&'[1]Anexos FICHA TRA050'!$F$27:$F$44, 0)), "")} -> 6.99 | BE40: =IFERROR(INDEX('[1]Anexos FICHA TRA050'!$B$4:$B$7, MATCH(Tabla467824[[#This Row],[Columna4]], '[1]Anexos FICHA TRA050'!$C$4:$C$7, 0)), "") -> 10 | BF40: =IFERROR(INDEX('[1]Anexos FICHA TRA050'!$C$14:$C$22, MATCH(Tabla467824[[#This Row],[Columna5]], '[1]Anexos FICHA TRA050'!$D$14:$D$22, 0)), "") -> 17.92 | BG40: =IFERROR(INDEX('[1]Anexos FICHA TRA050'!$C$49:$C$54, MATCH(Tabla467824[[#This Row],[Columna5]], '[1]Anexos FICHA TRA050'!$D$49:$D$54, 0)), "") -> 13073 | BH40: =+(((Tabla467824[[#This Row],[CVA2]]*Tabla467824[[#This Row],[f2]])-Tabla467824[[#This Row],[CVN2]])/100)*Tabla467824[[#This Row],[L2]] -> 6795.3454 | BK40: =+IF(Tabla467824[[#This Row],[F]]=Tabla467824[[#This Row],[f2]], "IGUAL", "DISTINTO") -> IGUAL | BL40: =+IF(Tabla467824[[#This Row],[CVN]]=Tabla467824[[#This Row],[CVN2]], "IGUAL", "DISTINTO") -> DISTINTO | BM40: =+IF(Tabla467824[[#This Row],[L]]=Tabla467824[[#This Row],[L2]], "IGUAL", "DISTINTO") -> IGUAL
A41: 38 | B41: CAE500067 | C41: 9019LBN | D41: M1 | E41: DIESEL | F41: DIESEL | G41: M1 | H41: X | I41: X | J41: X | L41: X | M41: X | O41: AYVENS | P41: 1 | Q41: RENTING | R41: DEVUELTO | S41: 43749 | T41: 45576 | U41: 1827 | V41: 2024 | W41: 7 | X41: DIESEL | Y41: OPEL | Z41: ASTRA 1.6 CDTI 110 CV | AA41: 1004 | AB41: G.O.MEDIOAMBIENTE S.L. | AC41: 10049946 | AD41: 3 | AE41: 6442MWV | AF41: CITROEN | AG41: Ë-C3 ELÉCTRICO MAX | AH41: ELECTRICO | AI41: 204427 | AJ41: 2024 | AK41: 45625 | AL41: 0 | AM41: 1004 | AN41: 4500424798 | AO41: G.O.MEDIOAMBIENTE S.L. | AQ41: X | AR41: COMUNIDAD VALENCIANA | AS41: VR7CBZYA9RT153042 | AT41: 5.1 | AU41: 10 | AV41: 16.4 | AW41: 13073 | AX41: 4523.258 | AY41: M1 | AZ41: CORRECTO ALQUILER | BA41: =+IF(Tabla467824[[#This Row],[TIPO VEHÍCULO]]=Tabla467824[[#This Row],[Columna2]], "IGUAL", "DISTINTO") -> IGUAL | BB41: =+IF(Tabla467824[[#This Row],[Columna4]]=Tabla467824[[#This Row],[Combustible2]], "IGUAL", "DISTINTO") -> IGUAL | BC41: CAE500067 | BD41: {=IFERROR(INDEX('[1]Anexos FICHA TRA050'!$D$27:$D$44, MATCH(Tabla467824[[#This Row],[Columna5]]&Tabla467824[[#This Row],[Columna4]], '[1]Anexos FICHA TRA050'!$E$27:$E$44&'[1]Anexos FICHA TRA050'!$F$27:$F$44, 0)), "")} -> 6.99 | BE41: =IFERROR(INDEX('[1]Anexos FICHA TRA050'!$B$4:$B$7, MATCH(Tabla467824[[#This Row],[Columna4]], '[1]Anexos FICHA TRA050'!$C$4:$C$7, 0)), "") -> 10 | BF41: =IFERROR(INDEX('[1]Anexos FICHA TRA050'!$C$14:$C$22, MATCH(Tabla467824[[#This Row],[Columna5]], '[1]Anexos FICHA TRA050'!$D$14:$D$22, 0)), "") -> 17.92 | BG41: =IFERROR(INDEX('[1]Anexos FICHA TRA050'!$C$49:$C$54, MATCH(Tabla467824[[#This Row],[Columna5]], '[1]Anexos FICHA TRA050'!$D$49:$D$54, 0)), "") -> 13073 | BH41: =+(((Tabla467824[[#This Row],[CVA2]]*Tabla467824[[#This Row],[f2]])-Tabla467824[[#This Row],[CVN2]])/100)*Tabla467824[[#This Row],[L2]] -> 6795.3454 | BK41: =+IF(Tabla467824[[#This Row],[F]]=Tabla467824[[#This Row],[f2]], "IGUAL", "DISTINTO") -> IGUAL | BL41: =+IF(Tabla467824[[#This Row],[CVN]]=Tabla467824[[#This Row],[CVN2]], "IGUAL", "DISTINTO") -> DISTINTO | BM41: =+IF(Tabla467824[[#This Row],[L]]=Tabla467824[[#This Row],[L2]], "IGUAL", "DISTINTO") -> IGUAL
A42: 39 | B42: CAE500068 | C42: 9105KTC | D42: M1 | E42: DIESEL | F42: DIESEL | G42: M1 | H42: X | I42: X | J42: X | L42: X | M42: X | O42: AYVENS | P42: 1 | Q42: RENTING | R42: CANCELADO POR SINIESTRO | S42: 43522 | T42: 45348 | U42: 1826 | V42: 2024 | W42: 6 | X42: DIESEL | Y42: OPEL | Z42: ASTRA 1.6 CDTI 110 CV | AA42: 1004 | AB42: G.O.MEDIOAMBIENTE S.L. | AC42: 10049946 | AD42: 4 | AE42: 1178MSX | AF42: NISSAN | AG42: TOWNSTAR | AH42: ELECTRICO | AI42: 724557 | AJ42: 2024 | AK42: 45483 | AL42: 0 | AM42: 1004 | AN42: 4500407442 | AO42: G.O.MEDIOAMBIENTE S.L. | AQ42: X | AR42: COMUNIDAD VALENCIANA | AS42: VNVNFK00X70248339 | AT42: 5.1 | AU42: 10 | AV42: 20 | AW42: 13073 | AX42: 4052.63 | AY42: M1 | AZ42: CORRECTO ALQUILER | BA42: =+IF(Tabla467824[[#This Row],[TIPO VEHÍCULO]]=Tabla467824[[#This Row],[Columna2]], "IGUAL", "DISTINTO") -> IGUAL | BB42: =+IF(Tabla467824[[#This Row],[Columna4]]=Tabla467824[[#This Row],[Combustible2]], "IGUAL", "DISTINTO") -> IGUAL | BC42: CAE500068 | BD42: {=IFERROR(INDEX('[1]Anexos FICHA TRA050'!$D$27:$D$44, MATCH(Tabla467824[[#This Row],[Columna5]]&Tabla467824[[#This Row],[Columna4]], '[1]Anexos FICHA TRA050'!$E$27:$E$44&'[1]Anexos FICHA TRA050'!$F$27:$F$44, 0)), "")} -> 6.99 | BE42: =IFERROR(INDEX('[1]Anexos FICHA TRA050'!$B$4:$B$7, MATCH(Tabla467824[[#This Row],[Columna4]], '[1]Anexos FICHA TRA050'!$C$4:$C$7, 0)), "") -> 10 | BF42: =IFERROR(INDEX('[1]Anexos FICHA TRA050'!$C$14:$C$22, MATCH(Tabla467824[[#This Row],[Columna5]], '[1]Anexos FICHA TRA050'!$D$14:$D$22, 0)), "") -> 17.92 | BG42: =IFERROR(INDEX('[1]Anexos FICHA TRA050'!$C$49:$C$54, MATCH(Tabla467824[[#This Row],[Columna5]], '[1]Anexos FICHA TRA050'!$D$49:$D$54, 0)), "") -> 13073 | BH42: =+(((Tabla467824[[#This Row],[CVA2]]*Tabla467824[[#This Row],[f2]])-Tabla467824[[#This Row],[CVN2]])/100)*Tabla467824[[#This Row],[L2]] -> 6795.3454 | BK42: =+IF(Tabla467824[[#This Row],[F]]=Tabla467824[[#This Row],[f2]], "IGUAL", "DISTINTO") -> IGUAL | BL42: =+IF(Tabla467824[[#This Row],[CVN]]=Tabla467824[[#This Row],[CVN2]], "IGUAL", "DISTINTO") -> DISTINTO | BM42: =+IF(Tabla467824[[#This Row],[L]]=Tabla467824[[#This Row],[L2]], "IGUAL", "DISTINTO") -> IGUAL
A43: 40 | B43: CAE500069 | C43: 4793KWD | D43: M1 | E43: DIESEL | F43: DIESEL | G43: M1 | H43: X | J43: X | L43: X | M43: X | O43: AYVENS | P43: 1 | Q43: RENTING | R43: DEVUELTO | S43: 43584 | T43: 45045 | U43: 1461 | V43: 2023 | W43: 7 | X43: DIESEL | Y43: OPEL | Z43: ASTRA 1.6 CDTI 110 CV | AA43: 1001 | AB43: AVSA | AC43: 200783 | AD43: 11 | AE43: 2705MXG | AF43: RENAULT | AG43: KANGOO VAN E-TECH ELECTRIC | AH43: ELECTRICO | AI43: 200567 | AJ43: 2024 | AK43: 45645 | AL43: 1 | AM43: 1001 | AN43: 4500426873 | AO43: AVSA | AQ43: X | AR43: COMUNIDAD VALENCIANA | AS43: VF1RFK00073934264 | AT43: 5.1 | AU43: 10 | AV43: 17.3 | AW43: 13073 | AX43: 4405.601 | AY43: M1 | AZ43: CORRECTO ALQUILER | BA43: =+IF(Tabla467824[[#This Row],[TIPO VEHÍCULO]]=Tabla467824[[#This Row],[Columna2]], "IGUAL", "DISTINTO") -> IGUAL | BB43: =+IF(Tabla467824[[#This Row],[Columna4]]=Tabla467824[[#This Row],[Combustible2]], "IGUAL", "DISTINTO") -> IGUAL | BC43: CAE500069 | BD43: {=IFERROR(INDEX('[1]Anexos FICHA TRA050'!$D$27:$D$44, MATCH(Tabla467824[[#This Row],[Columna5]]&Tabla467824[[#This Row],[Columna4]], '[1]Anexos FICHA TRA050'!$E$27:$E$44&'[1]Anexos FICHA TRA050'!$F$27:$F$44, 0)), "")} -> 6.99 | BE43: =IFERROR(INDEX('[1]Anexos FICHA TRA050'!$B$4:$B$7, MATCH(Tabla467824[[#This Row],[Columna4]], '[1]Anexos FICHA TRA050'!$C$4:$C$7, 0)), "") -> 10 | BF43: =IFERROR(INDEX('[1]Anexos FICHA TRA050'!$C$14:$C$22, MATCH(Tabla467824[[#This Row],[Columna5]], '[1]Anexos FICHA TRA050'!$D$14:$D$22, 0)), "") -> 17.92 | BG43: =IFERROR(INDEX('[1]Anexos FICHA TRA050'!$C$49:$C$54, MATCH(Tabla467824[[#This Row],[Columna5]], '[1]Anexos FICHA TRA050'!$D$49:$D$54, 0)), "") -> 13073 | BH43: =+(((Tabla467824[[#This Row],[CVA2]]*Tabla467824[[#This Row],[f2]])-Tabla467824[[#This Row],[CVN2]])/100)*Tabla467824[[#This Row],[L2]] -> 6795.3454 | BK43: =+IF(Tabla467824[[#This Row],[F]]=Tabla467824[[#This Row],[f2]], "IGUAL", "DISTINTO") -> IGUAL | BL43: =+IF(Tabla467824[[#This Row],[CVN]]=Tabla467824[[#This Row],[CVN2]], "IGUAL", "DISTINTO") -> DISTINTO | BM43: =+IF(Tabla467824[[#This Row],[L]]=Tabla467824[[#This Row],[L2]], "IGUAL", "DISTINTO") -> IGUAL
A44: 41 | B44: CAE500070 | C44: 4296LBD | D44: M1 | E44: DIESEL | F44: DIESEL | G44: M1 | H44: X | J44: X | L44: X | M44: X | O44: AYVENS | P44: 1 | Q44: RENTING | R44: DEVUELTO | S44: 43747 | T44: 45208 | U44: 1461 | V44: 2023 | W44: 7 | X44: DIESEL | Y44: OPEL | Z44: ASTRA 1.6 CDTI 110 CV | AA44: 1066 | AB44: CANALIZ. CIVILES S.A. | AC44: 10669121 | AD44: 4 | AE44: 8626MWT | AF44: RENAULT | AG44: KANGOO VAN E-TECH ELECTRIC | AH44: ELECTRICO | AI44: 356006 | AJ44: 2024 | AK44: 45625 | AL44: 1 | AM44: 1066 | AN44: 4500426766 | AO44: CANALIZ. CIVILES S.A. | AQ44: X | AR44: COMUNIDAD VALENCIANA | AS44: VF1RFK00X73824810 | AT44: 5.1 | AU44: 10 | AV44: 17.3 | AW44: 13073 | AX44: 4405.601 | AY44: M1 | AZ44: CORRECTO ALQUILER | BA44: =+IF(Tabla467824[[#This Row],[TIPO VEHÍCULO]]=Tabla467824[[#This Row],[Columna2]], "IGUAL", "DISTINTO") -> IGUAL | BB44: =+IF(Tabla467824[[#This Row],[Columna4]]=Tabla467824[[#This Row],[Combustible2]], "IGUAL", "DISTINTO") -> IGUAL | BC44: CAE500070 | BD44: {=IFERROR(INDEX('[1]Anexos FICHA TRA050'!$D$27:$D$44, MATCH(Tabla467824[[#This Row],[Columna5]]&Tabla467824[[#This Row],[Columna4]], '[1]Anexos FICHA TRA050'!$E$27:$E$44&'[1]Anexos FICHA TRA050'!$F$27:$F$44, 0)), "")} -> 6.99 | BE44: =IFERROR(INDEX('[1]Anexos FICHA TRA050'!$B$4:$B$7, MATCH(Tabla467824[[#This Row],[Columna4]], '[1]Anexos FICHA TRA050'!$C$4:$C$7, 0)), "") -> 10 | BF44: =IFERROR(INDEX('[1]Anexos FICHA TRA050'!$C$14:$C$22, MATCH(Tabla467824[[#This Row],[Columna5]], '[1]Anexos FICHA TRA050'!$D$14:$D$22, 0)), "") -> 17.92 | BG44: =IFERROR(INDEX('[1]Anexos FICHA TRA050'!$C$49:$C$54, MATCH(Tabla467824[[#This Row],[Columna5]], '[1]Anexos FICHA TRA050'!$D$49:$D$54, 0)), "") -> 13073 | BH44: =+(((Tabla467824[[#This Row],[CVA2]]*Tabla467824[[#This Row],[f2]])-Tabla467824[[#This Row],[CVN2]])/100)*Tabla467824[[#This Row],[L2]] -> 6795.3454 | BK44: =+IF(Tabla467824[[#This Row],[F]]=Tabla467824[[#This Row],[f2]], "IGUAL", "DISTINTO") -> IGUAL | BL44: =+IF(Tabla467824[[#This Row],[CVN]]=Tabla467824[[#This Row],[CVN2]], "IGUAL", "DISTINTO") -> DISTINTO | BM44: =+IF(Tabla467824[[#This Row],[L]]=Tabla467824[[#This Row],[L2]], "IGUAL", "DISTINTO") -> IGUAL
A45: 42 | B45: CAE500071 | C45: 7017KWW | D45: M1 | E45: DIESEL | F45: DIESEL | G45: M1 | H45: X | J45: X | L45: X | M45: X | O45: AYVENS | P45: 1 | Q45: RENTING | R45: DEVUELTO | S45: 43619 | T45: 45476 | U45: 1857 | V45: 2024 | W45: 7 | X45: DIESEL | Y45: OPEL | Z45: ASTRA 1.6 CDTI 110 CV | AA45: 1001 | AB45: AVSA | AC45: 10019946 | AD45: 12 | AE45: 5360MXF | AF45: RENAULT | AG45: KANGOO VAN E-TECH ELECTRIC | AH45: ELECTRICO | AI45: 350535 | AJ45: 2024 | AK45: 45645 | AL45: 0 | AM45: 1001 | AN45: 4500426758 | AO45: AVSA | AQ45: X | AR45: COMUNIDAD VALENCIANA | AS45: VF1RFK00873824885 | AT45: 5.1 | AU45: 10 | AV45: 17.3 | AW45: 13073 | AX45: 4405.601 | AY45: M1 | AZ45: CORRECTO ALQUILER | BA45: =+IF(Tabla467824[[#This Row],[TIPO VEHÍCULO]]=Tabla467824[[#This Row],[Columna2]], "IGUAL", "DISTINTO") -> IGUAL | BB45: =+IF(Tabla467824[[#This Row],[Columna4]]=Tabla467824[[#This Row],[Combustible2]], "IGUAL", "DISTINTO") -> IGUAL | BC45: CAE500071 | BD45: {=IFERROR(INDEX('[1]Anexos FICHA TRA050'!$D$27:$D$44, MATCH(Tabla467824[[#This Row],[Columna5]]&Tabla467824[[#This Row],[Columna4]], '[1]Anexos FICHA TRA050'!$E$27:$E$44&'[1]Anexos FICHA TRA050'!$F$27:$F$44, 0)), "")} -> 6.99 | BE45: =IFERROR(INDEX('[1]Anexos FICHA TRA050'!$B$4:$B$7, MATCH(Tabla467824[[#This Row],[Columna4]], '[1]Anexos FICHA TRA050'!$C$4:$C$7, 0)), "") -> 10 | BF45: =IFERROR(INDEX('[1]Anexos FICHA TRA050'!$C$14:$C$22, MATCH(Tabla467824[[#This Row],[Columna5]], '[1]Anexos FICHA TRA050'!$D$14:$D$22, 0)), "") -> 17.92 | BG45: =IFERROR(INDEX('[1]Anexos FICHA TRA050'!$C$49:$C$54, MATCH(Tabla467824[[#This Row],[Columna5]], '[1]Anexos FICHA TRA050'!$D$49:$D$54, 0)), "") -> 13073 | BH45: =+(((Tabla467824[[#This Row],[CVA2]]*Tabla467824[[#This Row],[f2]])-Tabla467824[[#This Row],[CVN2]])/100)*Tabla467824[[#This Row],[L2]] -> 6795.3454 | BK45: =+IF(Tabla467824[[#This Row],[F]]=Tabla467824[[#This Row],[f2]], "IGUAL", "DISTINTO") -> IGUAL | BL45: =+IF(Tabla467824[[#This Row],[CVN]]=Tabla467824[[#This Row],[CVN2]], "IGUAL", "DISTINTO") -> DISTINTO | BM45: =+IF(Tabla467824[[#This Row],[L]]=Tabla467824[[#This Row],[L2]], "IGUAL", "DISTINTO") -> IGUAL
A46: 43 | B46: CAE500072 | C46: 8891LBN | D46: M1 | E46: DIESEL | F46: DIESEL | G46: M1 | H46: X | I46: X | J46: X | L46: X | M46: X | O46: AYVENS | P46: 1 | Q46: RENTING | R46: DEVUELTO | S46: 43749 | T46: 45576 | U46: 1827 | V46: 2024 | W46: 7 | X46: DIESEL | Y46: OPEL | Z46: ASTRA 1.6 CDTI 110 CV | AA46: 1002 | AB46: G.O.INVERSIONES S.L. | AC46: 10029200 | AD46: 1 | AE46: 6952MXF | AF46: RENAULT | AG46: KANGOO VAN E-TECH ELECTRIC | AH46: ELECTRICO | AI46: 200370 | AJ46: 2024 | AK46: 45645 | AL46: 0 | AM46: 1002 | AN46: 4500426808 | AO46: G.O.INVERSIONES S.L. | AQ46: X | AR46: COMUNIDAD VALENCIANA | AS46: VF1RFK00873934304 | AT46: 5.1 | AU46: 10 | AV46: 17.3 | AW46: 13073 | AX46: 4405.601 | AY46: M1 | AZ46: CORRECTO ALQUILER | BA46: =+IF(Tabla467824[[#This Row],[TIPO VEHÍCULO]]=Tabla467824[[#This Row],[Columna2]], "IGUAL", "DISTINTO") -> IGUAL | BB46: =+IF(Tabla467824[[#This Row],[Columna4]]=Tabla467824[[#This Row],[Combustible2]], "IGUAL", "DISTINTO") -> IGUAL | BC46: CAE500072 | BD46: {=IFERROR(INDEX('[1]Anexos FICHA TRA050'!$D$27:$D$44, MATCH(Tabla467824[[#This Row],[Columna5]]&Tabla467824[[#This Row],[Columna4]], '[1]Anexos FICHA TRA050'!$E$27:$E$44&'[1]Anexos FICHA TRA050'!$F$27:$F$44, 0)), "")} -> 6.99 | BE46: =IFERROR(INDEX('[1]Anexos FICHA TRA050'!$B$4:$B$7, MATCH(Tabla467824[[#This Row],[Columna4]], '[1]Anexos FICHA TRA050'!$C$4:$C$7, 0)), "") -> 10 | BF46: =IFERROR(INDEX('[1]Anexos FICHA TRA050'!$C$14:$C$22, MATCH(Tabla467824[[#This Row],[Columna5]], '[1]Anexos FICHA TRA050'!$D$14:$D$22, 0)), "") -> 17.92 | BG46: =IFERROR(INDEX('[1]Anexos FICHA TRA050'!$C$49:$C$54, MATCH(Tabla467824[[#This Row],[Columna5]], '[1]Anexos FICHA TRA050'!$D$49:$D$54, 0)), "") -> 13073 | BH46: =+(((Tabla467824[[#This Row],[CVA2]]*Tabla467824[[#This Row],[f2]])-Tabla467824[[#This Row],[CVN2]])/100)*Tabla467824[[#This Row],[L2]] -> 6795.3454 | BK46: =+IF(Tabla467824[[#This Row],[F]]=Tabla467824[[#This Row],[f2]], "IGUAL", "DISTINTO") -> IGUAL | BL46: =+IF(Tabla467824[[#This Row],[CVN]]=Tabla467824[[#This Row],[CVN2]], "IGUAL", "DISTINTO") -> DISTINTO | BM46: =+IF(Tabla467824[[#This Row],[L]]=Tabla467824[[#This Row],[L2]], "IGUAL", "DISTINTO") -> IGUAL
A47: 44 | B47: CAE500074 | C47: 7190JDY | D47: M/G | E47: GASOLINA | F47: GASOLINA | L47: X | O47: OTROS | P47: 8 | Q47: OTROS AUTORIZADOS | R47: CANCELADO | S47: 42116 | T47: 45382 | U47: 3266 | V47: 2024 | W47: 4 | X47: HÍBRIDO | Y47: TOYOTA | Z47: AURIS | AA47: 1001 | AB47: AVSA | AC47: 10019946 | AD47: 13 | AE47: 2737MXG | AF47: RENAULT | AG47: KANGOO VAN E-TECH ELECTRIC | AH47: ELECTRICO | AI47: 100599 | AJ47: 2024 | AK47: 45645 | AL47: 0 | AM47: 1001 | AN47: 4500426786 | AO47: AVSA | AQ47: X | AR47: COMUNIDAD VALENCIANA | AS47: VF1RFK00573824889 | AT47: 5.1 | AU47: 9.19 | AV47: 17.3 | AW47: 13073 | AX47: 3865.5554 | AY47: M1 | AZ47: FALSO ALQUILER | BA47: =+IF(Tabla467824[[#This Row],[TIPO VEHÍCULO]]=Tabla467824[[#This Row],[Columna2]], "IGUAL", "DISTINTO") -> DISTINTO | BB47: =+IF(Tabla467824[[#This Row],[Columna4]]=Tabla467824[[#This Row],[Combustible2]], "IGUAL", "DISTINTO") -> DISTINTO | BC47: CAE500074 | BD47: {=IFERROR(INDEX('[1]Anexos FICHA TRA050'!$D$27:$D$44, MATCH(Tabla467824[[#This Row],[Columna5]]&Tabla467824[[#This Row],[Columna4]], '[1]Anexos FICHA TRA050'!$E$27:$E$44&'[1]Anexos FICHA TRA050'!$F$27:$F$44, 0)), "")} | BE47: =IFERROR(INDEX('[1]Anexos FICHA TRA050'!$B$4:$B$7, MATCH(Tabla467824[[#This Row],[Columna4]], '[1]Anexos FICHA TRA050'!$C$4:$C$7, 0)), "") -> 9.19 | BF47: =IFERROR(INDEX('[1]Anexos FICHA TRA050'!$C$14:$C$22, MATCH(Tabla467824[[#This Row],[Columna5]], '[1]Anexos FICHA TRA050'!$D$14:$D$22, 0)), "") | BG47: =IFERROR(INDEX('[1]Anexos FICHA TRA050'!$C$49:$C$54, MATCH(Tabla467824[[#This Row],[Columna5]], '[1]Anexos FICHA TRA050'!$D$49:$D$54, 0)), "") | BH47: =+(((Tabla467824[[#This Row],[CVA2]]*Tabla467824[[#This Row],[f2]])-Tabla467824[[#This Row],[CVN2]])/100)*Tabla467824[[#This Row],[L2]] -> #VALUE! | BI47: Es GASOLINA, pone M/G | BK47: =+IF(Tabla467824[[#This Row],[F]]=Tabla467824[[#This Row],[f2]], "IGUAL", "DISTINTO") -> IGUAL | BL47: =+IF(Tabla467824[[#This Row],[CVN]]=Tabla467824[[#This Row],[CVN2]], "IGUAL", "DISTINTO") -> DISTINTO | BM47: =+IF(Tabla467824[[#This Row],[L]]=Tabla467824[[#This Row],[L2]], "IGUAL", "DISTINTO") -> DISTINTO
A48: 45 | B48: CAE500075 | C48: 4161FVT | D48: N1 | E48: GASOIL | F48: DIESEL | G48: N1 | H48: X | I48: X | J48: X | L48: X | M48: X | O48: TLM | P48: 3 | Q48: ALQUILER | R48: DEVUELTO | S48: 45075 | T48: 45189 | U48: 114 | V48: 2023 | W48: 7 | X48: DIESEL | Y48: NISSAN | Z48: CABSTAR 130 CV | AA48: 1066 | AB48: CANALIZ. CIVILES S.A. | AC48: 356004 | AD48: 5 | AE48: 6037MWV | AF48: CITROEN | AG48: Ë-C3 ELÉCTRICO MAX | AH48: ELECTRICO | AI48: 356010 | AJ48: 2024 | AK48: 45625 | AL48: 1 | AM48: 1066 | AN48: 4500426703 | AO48: CANALIZ. CIVILES S.A. | AQ48: X | AR48: COMUNIDAD VALENCIANA | AS48: VR7CBZYA9ST000165 | AT48: 5.6 | AU48: 10 | AV48: 16.4 | AW48: 15815 | AX48: 6262.74 | AY48: N1 | AZ48: CORRECTO ALQUILER | BA48: =+IF(Tabla467824[[#This Row],[TIPO VEHÍCULO]]=Tabla467824[[#This Row],[Columna2]], "IGUAL", "DISTINTO") -> IGUAL | BB48: =+IF(Tabla467824[[#This Row],[Columna4]]=Tabla467824[[#This Row],[Combustible2]], "IGUAL", "DISTINTO") -> IGUAL | BC48: CAE500075 | BD48: {=IFERROR(INDEX('[1]Anexos FICHA TRA050'!$D$27:$D$44, MATCH(Tabla467824[[#This Row],[Columna5]]&Tabla467824[[#This Row],[Columna4]], '[1]Anexos FICHA TRA050'!$E$27:$E$44&'[1]Anexos FICHA TRA050'!$F$27:$F$44, 0)), "")} -> 5.63 | BE48: =IFERROR(INDEX('[1]Anexos FICHA TRA050'!$B$4:$B$7, MATCH(Tabla467824[[#This Row],[Columna4]], '[1]Anexos FICHA TRA050'!$C$4:$C$7, 0)), "") -> 10 | BF48: =IFERROR(INDEX('[1]Anexos FICHA TRA050'!$C$14:$C$22, MATCH(Tabla467824[[#This Row],[Columna5]], '[1]Anexos FICHA TRA050'!$D$14:$D$22, 0)), "") -> 20.84 | BG48: =IFERROR(INDEX('[1]Anexos FICHA TRA050'!$C$49:$C$54, MATCH(Tabla467824[[#This Row],[Columna5]], '[1]Anexos FICHA TRA050'!$D$49:$D$54, 0)), "") -> 15815 | BH48: =+(((Tabla467824[[#This Row],[CVA2]]*Tabla467824[[#This Row],[f2]])-Tabla467824[[#This Row],[CVN2]])/100)*Tabla467824[[#This Row],[L2]] -> 5607.999 | BK48: =+IF(Tabla467824[[#This Row],[F]]=Tabla467824[[#This Row],[f2]], "IGUAL", "DISTINTO") -> IGUAL | BL48: =+IF(Tabla467824[[#This Row],[CVN]]=Tabla467824[[#This Row],[CVN2]], "IGUAL", "DISTINTO") -> DISTINTO | BM48: =+IF(Tabla467824[[#This Row],[L]]=Tabla467824[[#This Row],[L2]], "IGUAL", "DISTINTO") -> IGUAL
A49: 46 | B49: CAE500077 | C49: 4836MGD | D49: M1 | E49: DIESEL | F49: DIESEL | G49: M1 | H49: X | J49: X | L49: X | M49: X | O49: AYVENS | P49: 3 | Q49: ALQUILER | R49: DEVUELTO | S49: 45202 | T49: 45278 | U49: 76 | V49: 2023 | W49: 7 | X49: DIESEL | Y49: RENAULT | Z49: CLIO 1.5 DCI 100 CV | AA49: 1505 | AB49: CGAC | AC49: 355589 | AD49: 4 | AE49: 2087MJP | AF49: RENAULT | AG49: KANGOO VAN E-TECH | AH49: ELECTRICO | AI49: 725465 | AJ49: 2023 | AK49: 45135 | AL49: 0 | AM49: 1505 | AN49: 4500351520 | AO49: CGAC | AQ49: X | AR49: CATALUÑA | AS49: VF1RFK00670686992 | AT49: 5.1 | AU49: 10 | AV49: 17.3 | AW49: 13073 | AX49: 4405.601 | AY49: M1 | AZ49: CORRECTO ALQUILER | BA49: =+IF(Tabla467824[[#This Row],[TIPO VEHÍCULO]]=Tabla467824[[#This Row],[Columna2]], "IGUAL", "DISTINTO") -> IGUAL | BB49: =+IF(Tabla467824[[#This Row],[Columna4]]=Tabla467824[[#This Row],[Combustible2]], "IGUAL", "DISTINTO") -> IGUAL | BC49: CAE500077 | BD49: {=IFERROR(INDEX('[1]Anexos FICHA TRA050'!$D$27:$D$44, MATCH(Tabla467824[[#This Row],[Columna5]]&Tabla467824[[#This Row],[Columna4]], '[1]Anexos FICHA TRA050'!$E$27:$E$44&'[1]Anexos FICHA TRA050'!$F$27:$F$44, 0)), "")} -> 6.99 | BE49: =IFERROR(INDEX('[1]Anexos FICHA TRA050'!$B$4:$B$7, MATCH(Tabla467824[[#This Row],[Columna4]], '[1]Anexos FICHA TRA050'!$C$4:$C$7, 0)), "") -> 10 | BF49: =IFERROR(INDEX('[1]Anexos FICHA TRA050'!$C$14:$C$22, MATCH(Tabla467824[[#This Row],[Columna5]], '[1]Anexos FICHA TRA050'!$D$14:$D$22, 0)), "") -> 17.92 | BG49: =IFERROR(INDEX('[1]Anexos FICHA TRA050'!$C$49:$C$54, MATCH(Tabla467824[[#This Row],[Columna5]], '[1]Anexos FICHA TRA050'!$D$49:$D$54, 0)), "") -> 13073 | BH49: =+(((Tabla467824[[#This Row],[CVA2]]*Tabla467824[[#This Row],[f2]])-Tabla467824[[#This Row],[CVN2]])/100)*Tabla467824[[#This Row],[L2]] -> 6795.3454 | BK49: =+IF(Tabla467824[[#This Row],[F]]=Tabla467824[[#This Row],[f2]], "IGUAL", "DISTINTO") -> IGUAL | BL49: =+IF(Tabla467824[[#This Row],[CVN]]=Tabla467824[[#This Row],[CVN2]], "IGUAL", "DISTINTO") -> DISTINTO | BM49: =+IF(Tabla467824[[#This Row],[L]]=Tabla467824[[#This Row],[L2]], "IGUAL", "DISTINTO") -> IGUAL
A50: 47 | B50: CAE500080 | C50: 7621KGX | D50: M1 | E50: DIESEL | F50: DIESEL | G50: M1 | J50: X | M50: x | N50: x | O50: AYVENS | P50: 3 | Q50: ALQUILER | R50: DEVUELTO | S50: 44958 | T50: 44984 | U50: 26 | V50: 2023 | W50: 7 | X50: DIESEL | Y50: RENAULT | Z50: CLIO 1.5 DCI 75 CV | AA50: 1505 | AB50: CGAC | AC50: 725485 | AD50: 5 | AE50: 0767MJM | AF50: PEUGEOT | AG50: E-PARTNER PRO 100 KW | AH50: ELECTRICO | AI50: 725455 | AJ50: 2023 | AK50: 45133 | AL50: 0 | AM50: 1505 | AN50: 4500370216 | AO50: CGAC | AQ50: X | AR50: CATALUÑA | AS50: VR3EAZKXZPJ701046 | AT50: 5.1 | AU50: 10 | AV50: 22.7 | AW50: 13073 | AX50: 3699.659 | AY50: M1 | AZ50: FALSO ALQUILER | BA50: =+IF(Tabla467824[[#This Row],[TIPO VEHÍCULO]]=Tabla467824[[#This Row],[Columna2]], "IGUAL", "DISTINTO") -> IGUAL | BB50: =+IF(Tabla467824[[#This Row],[Columna4]]=Tabla467824[[#This Row],[Combustible2]], "IGUAL", "DISTINTO") -> IGUAL | BC50: CAE500080 | BD50: {=IFERROR(INDEX('[1]Anexos FICHA TRA050'!$D$27:$D$44, MATCH(Tabla467824[[#This Row],[Columna5]]&Tabla467824[[#This Row],[Columna4]], '[1]Anexos FICHA TRA050'!$E$27:$E$44&'[1]Anexos FICHA TRA050'!$F$27:$F$44, 0)), "")} -> 6.99 | BE50: =IFERROR(INDEX('[1]Anexos FICHA TRA050'!$B$4:$B$7, MATCH(Tabla467824[[#This Row],[Columna4]], '[1]Anexos FICHA TRA050'!$C$4:$C$7, 0)), "") -> 10 | BF50: =IFERROR(INDEX('[1]Anexos FICHA TRA050'!$C$14:$C$22, MATCH(Tabla467824[[#This Row],[Columna5]], '[1]Anexos FICHA TRA050'!$D$14:$D$22, 0)), "") -> 17.92 | BG50: =IFERROR(INDEX('[1]Anexos FICHA TRA050'!$C$49:$C$54, MATCH(Tabla467824[[#This Row],[Columna5]], '[1]Anexos FICHA TRA050'!$D$49:$D$54, 0)), "") -> 13073 | BH50: =+(((Tabla467824[[#This Row],[CVA2]]*Tabla467824[[#This Row],[f2]])-Tabla467824[[#This Row],[CVN2]])/100)*Tabla467824[[#This Row],[L2]] -> 6795.3454 | BK50: =+IF(Tabla467824[[#This Row],[F]]=Tabla467824[[#This Row],[f2]], "IGUAL", "DISTINTO") -> IGUAL | BL50: =+IF(Tabla467824[[#This Row],[CVN]]=Tabla467824[[#This Row],[CVN2]], "IGUAL", "DISTINTO") -> DISTINTO | BM50: =+IF(Tabla467824[[#This Row],[L]]=Tabla467824[[#This Row],[L2]], "IGUAL", "DISTINTO") -> IGUAL
A51: 48 | B51: CAE500081 | C51: 7706KJH | D51: M1 | E51: DIESEL | F51: DIESEL | G51: M1 | J51: x | M51: x | N51: x | O51: AYVENS | P51: 3 | Q51: ALQUILER | R51: DEVUELTO | S51: 44958 | T51: 44984 | U51: 26 | V51: 2023 | W51: 7 | X51: DIESEL | Y51: RENAULT | Z51: CLIO 1.5 DCI 75 CV | AA51: 1505 | AB51: CGAC | AC51: 725485 | AD51: 6 | AE51: 0777MJM | AF51: PEUGEOT | AG51: E-PARTNER PRO 100 KW | AH51: ELECTRICO | AI51: 725455 | AJ51: 2023 | AK51: 45133 | AL51: 0 | AM51: 1505 | AN51: 4500370232 | AO51: CGAC | AQ51: X | AR51: CATALUÑA | AS51: VR3EAZKXZPJ701037 | AT51: 5.1 | AU51: 10 | AV51: 22.7 | AW51: 13073 | AX51: 3699.659 | AY51: M1 | AZ51: FALSO ALQUILER | BA51: =+IF(Tabla467824[[#This Row],[TIPO VEHÍCULO]]=Tabla467824[[#This Row],[Columna2]], "IGUAL", "DISTINTO") -> IGUAL | BB51: =+IF(Tabla467824[[#This Row],[Columna4]]=Tabla467824[[#This Row],[Combustible2]], "IGUAL", "DISTINTO") -> IGUAL | BC51: CAE500081 | BD51: {=IFERROR(INDEX('[1]Anexos FICHA TRA050'!$D$27:$D$44, MATCH(Tabla467824[[#This Row],[Columna5]]&Tabla467824[[#This Row],[Columna4]], '[1]Anexos FICHA TRA050'!$E$27:$E$44&'[1]Anexos FICHA TRA050'!$F$27:$F$44, 0)), "")} -> 6.99 | BE51: =IFERROR(INDEX('[1]Anexos FICHA TRA050'!$B$4:$B$7, MATCH(Tabla467824[[#This Row],[Columna4]], '[1]Anexos FICHA TRA050'!$C$4:$C$7, 0)), "") -> 10 | BF51: =IFERROR(INDEX('[1]Anexos FICHA TRA050'!$C$14:$C$22, MATCH(Tabla467824[[#This Row],[Columna5]], '[1]Anexos FICHA TRA050'!$D$14:$D$22, 0)), "") -> 17.92 | BG51: =IFERROR(INDEX('[1]Anexos FICHA TRA050'!$C$49:$C$54, MATCH(Tabla467824[[#This Row],[Columna5]], '[1]Anexos FICHA TRA050'!$D$49:$D$54, 0)), "") -> 13073 | BH51: =+(((Tabla467824[[#This Row],[CVA2]]*Tabla467824[[#This Row],[f2]])-Tabla467824[[#This Row],[CVN2]])/100)*Tabla467824[[#This Row],[L2]] -> 6795.3454 | BK51: =+IF(Tabla467824[[#This Row],[F]]=Tabla467824[[#This Row],[f2]], "IGUAL", "DISTINTO") -> IGUAL | BL51: =+IF(Tabla467824[[#This Row],[CVN]]=Tabla467824[[#This Row],[CVN2]], "IGUAL", "DISTINTO") -> DISTINTO | BM51: =+IF(Tabla467824[[#This Row],[L]]=Tabla467824[[#This Row],[L2]], "IGUAL", "DISTINTO") -> IGUAL
A52: 49 | B52: CAE500082 | C52: 5351MGK | D52: M1 | E52: DIESEL | F52: DIESEL | G52: M1 | H52: X | I52: X | J52: X | L52: X | M52: X | O52: AYVENS | P52: 3 | Q52: ALQUILER | R52: DEVUELTO | S52: 45202 | T52: 45372 | U52: 170 | V52: 2024 | W52: 7 | X52: DIESEL | Y52: RENAULT | Z52: CLIO DCI 100 CV | AA52: 1505 | AB52: CGAC | AC52: 355589 | AD52: 7 | AE52: 1666MGR | AF52: OPEL | AG52: VIVARO E-FURGON | AH52: ELECTRICO | AI52: 725485 | AJ52: 2023 | AK52: 45051 | AL52: -1 | AM52: 1505 | AN52: 4500352855 | AO52: CGAC | AQ52: X | AR52: CATALUÑA | AS52: VXEV1ZKXZPZ019578 | AT52: 5.1 | AU52: 10 | AV52: 28.1 | AW52: 13073 | AX52: 2993.717 | AY52: M1 | AZ52: CORRECTO ALQUILER | BA52: =+IF(Tabla467824[[#This Row],[TIPO VEHÍCULO]]=Tabla467824[[#This Row],[Columna2]], "IGUAL", "DISTINTO") -> IGUAL | BB52: =+IF(Tabla467824[[#This Row],[Columna4]]=Tabla467824[[#This Row],[Combustible2]], "IGUAL", "DISTINTO") -> IGUAL | BC52: CAE500082 | BD52: {=IFERROR(INDEX('[1]Anexos FICHA TRA050'!$D$27:$D$44, MATCH(Tabla467824[[#This Row],[Columna5]]&Tabla467824[[#This Row],[Columna4]], '[1]Anexos FICHA TRA050'!$E$27:$E$44&'[1]Anexos FICHA TRA050'!$F$27:$F$44, 0)), "")} -> 6.99 | BE52: =IFERROR(INDEX('[1]Anexos FICHA TRA050'!$B$4:$B$7, MATCH(Tabla467824[[#This Row],[Columna4]], '[1]Anexos FICHA TRA050'!$C$4:$C$7, 0)), "") -> 10 | BF52: =IFERROR(INDEX('[1]Anexos FICHA TRA050'!$C$14:$C$22, MATCH(Tabla467824[[#This Row],[Columna5]], '[1]Anexos FICHA TRA050'!$D$14:$D$22, 0)), "") -> 17.92 | BG52: =IFERROR(INDEX('[1]Anexos FICHA TRA050'!$C$49:$C$54, MATCH(Tabla467824[[#This Row],[Columna5]], '[1]Anexos FICHA TRA050'!$D$49:$D$54, 0)), "") -> 13073 | BH52: =+(((Tabla467824[[#This Row],[CVA2]]*Tabla467824[[#This Row],[f2]])-Tabla467824[[#This Row],[CVN2]])/100)*Tabla467824[[#This Row],[L2]] -> 6795.3454 | BK52: =+IF(Tabla467824[[#This Row],[F]]=Tabla467824[[#This Row],[f2]], "IGUAL", "DISTINTO") -> IGUAL | BL52: =+IF(Tabla467824[[#This Row],[CVN]]=Tabla467824[[#This Row],[CVN2]], "IGUAL", "DISTINTO") -> DISTINTO | BM52: =+IF(Tabla467824[[#This Row],[L]]=Tabla467824[[#This Row],[L2]], "IGUAL", "DISTINTO") -> IGUAL
A53: 50 | B53: CAE500083 | C53: 5262MGK | D53: M1 | E53: DIESEL | F53: DIESEL | G53: M1 | H53: X | J53: X | L53: X | M53: X | O53: AYVENS | P53: 3 | Q53: ALQUILER | R53: DEVUELTO | S53: 45202 | T53: 45259 | U53: 57 | V53: 2023 | W53: 7 | X53: DIESEL | Y53: RENAULT | Z53: CLIO DCI 100 CV | AA53: 1505 | AB53: CGAC | AC53: 355589 | AD53: 8 | AE53: 1258MJM | AF53: PEUGEOT | AG53: E-EXPERT PRO 100 KW | AH53: ELECTRICO | AI53: 725441 | AJ53: 2023 | AK53: 45133 | AL53: 0 | AM53: 1505 | AN53: 4500370368 | AO53: CGAC | AQ53: X | AR53: CATALUÑA | AS53: VF3V1ZKXZPZ027825 | AT53: 5.1 | AU53: 10 | AV53: 28.2 | AW53: 13073 | AX53: 2980.644 | AY53: M1 | AZ53: CORRECTO ALQUILER | BA53: =+IF(Tabla467824[[#This Row],[TIPO VEHÍCULO]]=Tabla467824[[#This Row],[Columna2]], "IGUAL", "DISTINTO") -> IGUAL | BB53: =+IF(Tabla467824[[#This Row],[Columna4]]=Tabla467824[[#This Row],[Combustible2]], "IGUAL", "DISTINTO") -> IGUAL | BC53: CAE500083 | BD53: {=IFERROR(INDEX('[1]Anexos FICHA TRA050'!$D$27:$D$44, MATCH(Tabla467824[[#This Row],[Columna5]]&Tabla467824[[#This Row],[Columna4]], '[1]Anexos FICHA TRA050'!$E$27:$E$44&'[1]Anexos FICHA TRA050'!$F$27:$F$44, 0)), "")} -> 6.99 | BE53: =IFERROR(INDEX('[1]Anexos FICHA TRA050'!$B$4:$B$7, MATCH(Tabla467824[[#This Row],[Columna4]], '[1]Anexos FICHA TRA050'!$C$4:$C$7, 0)), "") -> 10 | BF53: =IFERROR(INDEX('[1]Anexos FICHA TRA050'!$C$14:$C$22, MATCH(Tabla467824[[#This Row],[Columna5]], '[1]Anexos FICHA TRA050'!$D$14:$D$22, 0)), "") -> 17.92 | BG53: =IFERROR(INDEX('[1]Anexos FICHA TRA050'!$C$49:$C$54, MATCH(Tabla467824[[#This Row],[Columna5]], '[1]Anexos FICHA TRA050'!$D$49:$D$54, 0)), "") -> 13073 | BH53: =+(((Tabla467824[[#This Row],[CVA2]]*Tabla467824[[#This Row],[f2]])-Tabla467824[[#This Row],[CVN2]])/100)*Tabla467824[[#This Row],[L2]] -> 6795.3454 | BK53: =+IF(Tabla467824[[#This Row],[F]]=Tabla467824[[#This Row],[f2]], "IGUAL", "DISTINTO") -> IGUAL | BL53: =+IF(Tabla467824[[#This Row],[CVN]]=Tabla467824[[#This Row],[CVN2]], "IGUAL", "DISTINTO") -> DISTINTO | BM53: =+IF(Tabla467824[[#This Row],[L]]=Tabla467824[[#This Row],[L2]], "IGUAL", "DISTINTO") -> IGUAL
A54: 51 | B54: CAE500084 | C54: 4655MGJ | D54: M1 | E54: DIESEL | F54: DIESEL | G54: M1 | H54: X | L54: x | M54: x | O54: AYVENS | P54: 3 | Q54: ALQUILER | R54: DEVUELTO | S54: 45202 | T54: 45382 | U54: 180 | V54: 2024 | W54: 7 | X54: DIESEL | Y54: OPEL | Z54: CORSA 1.5 D 100 CV | AA54: 1505 | AB54: CGAC | AC54: 355589 | AD54: 9 | AE54: 1667MGR | AF54: OPEL | AG54: VIVARO E-FURGON | AH54: ELECTRICO | AI54: 725465 | AJ54: 2023 | AK54: 45051 | AL54: -1 | AM54: 1505 | AN54: 4500351861 | AO54: CGAC | AQ54: X | AR54: CATALUÑA | AS54: VXEV1ZKXZPZ019580 | AT54: 5.1 | AU54: 10 | AV54: 28.1 | AW54: 13073 | AX54: 2993.717 | AY54: M1 | AZ54: FALSO ALQUILER | BA54: =+IF(Tabla467824[[#This Row],[TIPO VEHÍCULO]]=Tabla467824[[#This Row],[Columna2]], "IGUAL", "DISTINTO") -> IGUAL | BB54: =+IF(Tabla467824[[#This Row],[Columna4]]=Tabla467824[[#This Row],[Combustible2]], "IGUAL", "DISTINTO") -> IGUAL | BC54: CAE500084 | BD54: {=IFERROR(INDEX('[1]Anexos FICHA TRA050'!$D$27:$D$44, MATCH(Tabla467824[[#This Row],[Columna5]]&Tabla467824[[#This Row],[Columna4]], '[1]Anexos FICHA TRA050'!$E$27:$E$44&'[1]Anexos FICHA TRA050'!$F$27:$F$44, 0)), "")} -> 6.99 | BE54: =IFERROR(INDEX('[1]Anexos FICHA TRA050'!$B$4:$B$7, MATCH(Tabla467824[[#This Row],[Columna4]], '[1]Anexos FICHA TRA050'!$C$4:$C$7, 0)), "") -> 10 | BF54: =IFERROR(INDEX('[1]Anexos FICHA TRA050'!$C$14:$C$22, MATCH(Tabla467824[[#This Row],[Columna5]], '[1]Anexos FICHA TRA050'!$D$14:$D$22, 0)), "") -> 17.92 | BG54: =IFERROR(INDEX('[1]Anexos FICHA TRA050'!$C$49:$C$54, MATCH(Tabla467824[[#This Row],[Columna5]], '[1]Anexos FICHA TRA050'!$D$49:$D$54, 0)), "") -> 13073 | BH54: =+(((Tabla467824[[#This Row],[CVA2]]*Tabla467824[[#This Row],[f2]])-Tabla467824[[#This Row],[CVN2]])/100)*Tabla467824[[#This Row],[L2]] -> 6795.3454 | BK54: =+IF(Tabla467824[[#This Row],[F]]=Tabla467824[[#This Row],[f2]], "IGUAL", "DISTINTO") -> IGUAL | BL54: =+IF(Tabla467824[[#This Row],[CVN]]=Tabla467824[[#This Row],[CVN2]], "IGUAL", "DISTINTO") -> DISTINTO | BM54: =+IF(Tabla467824[[#This Row],[L]]=Tabla467824[[#This Row],[L2]], "IGUAL", "DISTINTO") -> IGUAL
A55: 52 | B55: CAE500086 | C55: 4223LJV | D55: N1 | E55: DIESEL | F55: DIESEL | G55: N1 | H55: X | J55: X | L55: X | M55: X | O55: VWRENTING | P55: 1 | Q55: RENTING | R55: DEVUELTO | S55: 44088 | T55: 45549 | U55: 1461 | V55: 2024 | W55: 7 | X55: DIESEL | Y55: VOLKSWAGEN | Z55: CADDY 2.0 TDI 102 CV | AA55: 1507 | AB55: EMP.AG.POTABL.MALGRAT SA | AC55: 201507 | AD55: 1 | AE55: 4621MVB | AF55: NISSAN | AG55: TOWNSTAR | AH55: ELECTRICO | AI55: 201507 | AJ55: 2024 | AK55: 45551 | AL55: 0 | AM55: 1507 | AN55: 4500413615 | AO55: EMP.AG.POTABL.MALGRAT SA | AQ55: X | AR55: CATALUÑA | AS55: VNVNFK00X70531114 | AT55: 5.6 | AU55: 10 | AV55: 20 | AW55: 15815 | AX55: 5693.4 | AY55: N1 | AZ55: CORRECTO ALQUILER | BA55: =+IF(Tabla467824[[#This Row],[TIPO VEHÍCULO]]=Tabla467824[[#This Row],[Columna2]], "IGUAL", "DISTINTO") -> IGUAL | BB55: =+IF(Tabla467824[[#This Row],[Columna4]]=Tabla467824[[#This Row],[Combustible2]], "IGUAL", "DISTINTO") -> IGUAL | BC55: CAE500086 | BD55: {=IFERROR(INDEX('[1]Anexos FICHA TRA050'!$D$27:$D$44, MATCH(Tabla467824[[#This Row],[Columna5]]&Tabla467824[[#This Row],[Columna4]], '[1]Anexos FICHA TRA050'!$E$27:$E$44&'[1]Anexos FICHA TRA050'!$F$27:$F$44, 0)), "")} -> 5.63 | BE55: =IFERROR(INDEX('[1]Anexos FICHA TRA050'!$B$4:$B$7, MATCH(Tabla467824[[#This Row],[Columna4]], '[1]Anexos FICHA TRA050'!$C$4:$C$7, 0)), "") -> 10 | BF55: =IFERROR(INDEX('[1]Anexos FICHA TRA050'!$C$14:$C$22, MATCH(Tabla467824[[#This Row],[Columna5]], '[1]Anexos FICHA TRA050'!$D$14:$D$22, 0)), "") -> 20.84 | BG55: =IFERROR(INDEX('[1]Anexos FICHA TRA050'!$C$49:$C$54, MATCH(Tabla467824[[#This Row],[Columna5]], '[1]Anexos FICHA TRA050'!$D$49:$D$54, 0)), "") -> 15815 | BH55: =+(((Tabla467824[[#This Row],[CVA2]]*Tabla467824[[#This Row],[f2]])-Tabla467824[[#This Row],[CVN2]])/100)*Tabla467824[[#This Row],[L2]] -> 5607.999 | BK55: =+IF(Tabla467824[[#This Row],[F]]=Tabla467824[[#This Row],[f2]], "IGUAL", "DISTINTO") -> IGUAL | BL55: =+IF(Tabla467824[[#This Row],[CVN]]=Tabla467824[[#This Row],[CVN2]], "IGUAL", "DISTINTO") -> DISTINTO | BM55: =+IF(Tabla467824[[#This Row],[L]]=Tabla467824[[#This Row],[L2]], "IGUAL", "DISTINTO") -> IGUAL
A56: 53 | B56: CAE500087 | C56: 3043KBJ | D56: N1 | E56: DIESEL | F56: DIESEL | G56: N1 | H56: X | I56: X | J56: X | L56: X | M56: X | O56: AYVENS | P56: 1 | Q56: RENTING | R56: DEVUELTO | S56: 42923 | T56: 45565 | U56: 2642 | V56: 2024 | W56: 7 | X56: DIESEL | Y56: VOLKSWAGEN | Z56: CADDY 4*4 2.0 TDI 122 CV | AA56: 1053 | AB56: ISG | AC56: 355458 | AD56: 4 | AE56: 6128MWV | AF56: CITROEN | AG56: Ë-C3 ELÉCTRICO MAX | AH56: ELECTRICO | AI56: 355539 | AJ56: 2024 | AK56: 45625 | AL56: 0 | AM56: 1053 | AN56: 4500424790 | AO56: ISG | AQ56: X | AR56: COMUNIDAD VALENCIANA | AS56: VR7CBZYA8RT154442 | AT56: 5.6 | AU56: 10 | AV56: 16.4 | AW56: 15815 | AX56: 6262.74 | AY56: N1 | AZ56: CORRECTO ALQUILER | BA56: =+IF(Tabla467824[[#This Row],[TIPO VEHÍCULO]]=Tabla467824[[#This Row],[Columna2]], "IGUAL", "DISTINTO") -> IGUAL | BB56: =+IF(Tabla467824[[#This Row],[Columna4]]=Tabla467824[[#This Row],[Combustible2]], "IGUAL", "DISTINTO") -> IGUAL | BC56: CAE500087 | BD56: {=IFERROR(INDEX('[1]Anexos FICHA TRA050'!$D$27:$D$44, MATCH(Tabla467824[[#This Row],[Columna5]]&Tabla467824[[#This Row],[Columna4]], '[1]Anexos FICHA TRA050'!$E$27:$E$44&'[1]Anexos FICHA TRA050'!$F$27:$F$44, 0)), "")} -> 5.63 | BE56: =IFERROR(INDEX('[1]Anexos FICHA TRA050'!$B$4:$B$7, MATCH(Tabla467824[[#This Row],[Columna4]], '[1]Anexos FICHA TRA050'!$C$4:$C$7, 0)), "") -> 10 | BF56: =IFERROR(INDEX('[1]Anexos FICHA TRA050'!$C$14:$C$22, MATCH(Tabla467824[[#This Row],[Columna5]], '[1]Anexos FICHA TRA050'!$D$14:$D$22, 0)), "") -> 20.84 | BG56: =IFERROR(INDEX('[1]Anexos FICHA TRA050'!$C$49:$C$54, MATCH(Tabla467824[[#This Row],[Columna5]], '[1]Anexos FICHA TRA050'!$D$49:$D$54, 0)), "") -> 15815 | BH56: =+(((Tabla467824[[#This Row],[CVA2]]*Tabla467824[[#This Row],[f2]])-Tabla467824[[#This Row],[CVN2]])/100)*Tabla467824[[#This Row],[L2]] -> 5607.999 | BK56: =+IF(Tabla467824[[#This Row],[F]]=Tabla467824[[#This Row],[f2]], "IGUAL", "DISTINTO") -> IGUAL | BL56: =+IF(Tabla467824[[#This Row],[CVN]]=Tabla467824[[#This Row],[CVN2]], "IGUAL", "DISTINTO") -> DISTINTO | BM56: =+IF(Tabla467824[[#This Row],[L]]=Tabla467824[[#This Row],[L2]], "IGUAL", "DISTINTO") -> IGUAL
A57: 54 | B57: CAE500088 | C57: 3598LKS | D57: N1 | E57: DIESEL | F57: DIESEL | G57: N1 | H57: X | I57: X | J57: X | L57: X | M57: X | O57: AYVENS | P57: 1 | Q57: RENTING | R57: CANCELADO POR SINIESTRO | S57: 44166 | T57: 45627 | U57: 1461 | V57: 2024 | W57: 6 | X57: DIESEL | Y57: VOLKSWAGEN | Z57: CADDY 4*4 2.0 TDI 122 CV | AA57: 1001 | AB57: AVSA | AC57: 200738 | AD57: 14 | AE57: 6087MWV | AF57: CITROEN | AG57: Ë-C3 ELÉCTRICO MAX | AH57: ELECTRICO | AI57: 200784 | AJ57: 2024 | AK57: 45625 | AL57: 0 | AM57: 1001 | AN57: 4500424802 | AO57: AVSA | AQ57: X | AR57: COMUNIDAD VALENCIANA | AS57: VR7CBZYA7RT152214 | AT57: 5.6 | AU57: 10 | AV57: 16.4 | AW57: 15815 | AX57: 6262.74 | AY57: N1 | AZ57: CORRECTO ALQUILER | BA57: =+IF(Tabla467824[[#This Row],[TIPO VEHÍCULO]]=Tabla467824[[#This Row],[Columna2]], "IGUAL", "DISTINTO") -> IGUAL | BB57: =+IF(Tabla467824[[#This Row],[Columna4]]=Tabla467824[[#This Row],[Combustible2]], "IGUAL", "DISTINTO") -> IGUAL | BC57: CAE500088 | BD57: {=IFERROR(INDEX('[1]Anexos FICHA TRA050'!$D$27:$D$44, MATCH(Tabla467824[[#This Row],[Columna5]]&Tabla467824[[#This Row],[Columna4]], '[1]Anexos FICHA TRA050'!$E$27:$E$44&'[1]Anexos FICHA TRA050'!$F$27:$F$44, 0)), "")} -> 5.63 | BE57: =IFERROR(INDEX('[1]Anexos FICHA TRA050'!$B$4:$B$7, MATCH(Tabla467824[[#This Row],[Columna4]], '[1]Anexos FICHA TRA050'!$C$4:$C$7, 0)), "") -> 10 | BF57: =IFERROR(INDEX('[1]Anexos FICHA TRA050'!$C$14:$C$22, MATCH(Tabla467824[[#This Row],[Columna5]], '[1]Anexos FICHA TRA050'!$D$14:$D$22, 0)), "") -> 20.84 | BG57: =IFERROR(INDEX('[1]Anexos FICHA TRA050'!$C$49:$C$54, MATCH(Tabla467824[[#This Row],[Columna5]], '[1]Anexos FICHA TRA050'!$D$49:$D$54, 0)), "") -> 15815 | BH57: =+(((Tabla467824[[#This Row],[CVA2]]*Tabla467824[[#This Row],[f2]])-Tabla467824[[#This Row],[CVN2]])/100)*Tabla467824[[#This Row],[L2]] -> 5607.999 | BK57: =+IF(Tabla467824[[#This Row],[F]]=Tabla467824[[#This Row],[f2]], "IGUAL", "DISTINTO") -> IGUAL | BL57: =+IF(Tabla467824[[#This Row],[CVN]]=Tabla467824[[#This Row],[CVN2]], "IGUAL", "DISTINTO") -> DISTINTO | BM57: =+IF(Tabla467824[[#This Row],[L]]=Tabla467824[[#This Row],[L2]], "IGUAL", "DISTINTO") -> IGUAL
A58: 55 | B58: CAE500089 | C58: 5013LLF | D58: N1 | E58: DIESEL | F58: DIESEL | G58: N1 | H58: X | I58: X | J58: X | L58: X | M58: X | O58: AYVENS | P58: 1 | Q58: RENTING | R58: DEVUELTO | S58: 44176 | T58: 45637 | U58: 1461 | V58: 2024 | W58: 7 | X58: DIESEL | Y58: VOLKSWAGEN | Z58: CADDY 4*4 2.0 TDI 122 CV | AA58: 1053 | AB58: ISG | AC58: 355528 | AD58: 5 | AE58: 8387MXG | AF58: RENAULT | AG58: KANGOO VAN E-TECH ELECTRIC | AH58: ELECTRICO | AI58: 355458 | AJ58: 2024 | AK58: 45646 | AL58: 0 | AM58: 1053 | AN58: 4500426879 | AO58: ISG | AQ58: X | AR58: COMUNIDAD VALENCIANA | AS58: VF1RFK00973934294 | AT58: 5.6 | AU58: 10 | AV58: 17.3 | AW58: 15815 | AX58: 6120.405 | AY58: N1 | AZ58: CORRECTO ALQUILER | BA58: =+IF(Tabla467824[[#This Row],[TIPO VEHÍCULO]]=Tabla467824[[#This Row],[Columna2]], "IGUAL", "DISTINTO") -> IGUAL | BB58: =+IF(Tabla467824[[#This Row],[Columna4]]=Tabla467824[[#This Row],[Combustible2]], "IGUAL", "DISTINTO") -> IGUAL | BC58: CAE500089 | BD58: {=IFERROR(INDEX('[1]Anexos FICHA TRA050'!$D$27:$D$44, MATCH(Tabla467824[[#This Row],[Columna5]]&Tabla467824[[#This Row],[Columna4]], '[1]Anexos FICHA TRA050'!$E$27:$E$44&'[1]Anexos FICHA TRA050'!$F$27:$F$44, 0)), "")} -> 5.63 | BE58: =IFERROR(INDEX('[1]Anexos FICHA TRA050'!$B$4:$B$7, MATCH(Tabla467824[[#This Row],[Columna4]], '[1]Anexos FICHA TRA050'!$C$4:$C$7, 0)), "") -> 10 | BF58: =IFERROR(INDEX('[1]Anexos FICHA TRA050'!$C$14:$C$22, MATCH(Tabla467824[[#This Row],[Columna5]], '[1]Anexos FICHA TRA050'!$D$14:$D$22, 0)), "") -> 20.84 | BG58: =IFERROR(INDEX('[1]Anexos FICHA TRA050'!$C$49:$C$54, MATCH(Tabla467824[[#This Row],[Columna5]], '[1]Anexos FICHA TRA050'!$D$49:$D$54, 0)), "") -> 15815 | BH58: =+(((Tabla467824[[#This Row],[CVA2]]*Tabla467824[[#This Row],[f2]])-Tabla467824[[#This Row],[CVN2]])/100)*Tabla467824[[#This Row],[L2]] -> 5607.999 | BK58: =+IF(Tabla467824[[#This Row],[F]]=Tabla467824[[#This Row],[f2]], "IGUAL", "DISTINTO") -> IGUAL | BL58: =+IF(Tabla467824[[#This Row],[CVN]]=Tabla467824[[#This Row],[CVN2]], "IGUAL", "DISTINTO") -> DISTINTO | BM58: =+IF(Tabla467824[[#This Row],[L]]=Tabla467824[[#This Row],[L2]], "IGUAL", "DISTINTO") -> IGUAL
A59: 56 | B59: CAE500091 | C59: 3569LKS | D59: N1 | E59: DIESEL | F59: DIESEL | G59: N1 | H59: X | I59: X | J59: X | L59: X | M59: X | O59: AYVENS | P59: 1 | Q59: RENTING | R59: CANCELADO POR SINIESTRO | S59: 44189 | T59: 45650 | U59: 1461 | V59: 2024 | W59: 6 | X59: DIESEL | Y59: VOLKSWAGEN | Z59: CADDY 4*4 2.0 TDI 122 CV | AA59: 1505 | AB59: CGAC | AC59: 355490 | AD59: 10 | AE59: 8616MWT | AF59: RENAULT | AG59: KANGOO VAN E-TECH ELECTRIC | AH59: ELECTRICO | AI59: 205351 | AJ59: 2024 | AK59: 45625 | AL59: 0 | AM59: 1505 | AN59: 4500426787 | AO59: CGAC | AQ59: X | AR59: CATALUÑA | AS59: VF1RFK00273824803 | AT59: 5.6 | AU59: 10 | AV59: 17.3 | AW59: 15815 | AX59: 6120.405 | AY59: N1 | AZ59: CORRECTO ALQUILER | BA59: =+IF(Tabla467824[[#This Row],[TIPO VEHÍCULO]]=Tabla467824[[#This Row],[Columna2]], "IGUAL", "DISTINTO") -> IGUAL | BB59: =+IF(Tabla467824[[#This Row],[Columna4]]=Tabla467824[[#This Row],[Combustible2]], "IGUAL", "DISTINTO") -> IGUAL | BC59: CAE500091 | BD59: {=IFERROR(INDEX('[1]Anexos FICHA TRA050'!$D$27:$D$44, MATCH(Tabla467824[[#This Row],[Columna5]]&Tabla467824[[#This Row],[Columna4]], '[1]Anexos FICHA TRA050'!$E$27:$E$44&'[1]Anexos FICHA TRA050'!$F$27:$F$44, 0)), "")} -> 5.63 | BE59: =IFERROR(INDEX('[1]Anexos FICHA TRA050'!$B$4:$B$7, MATCH(Tabla467824[[#This Row],[Columna4]], '[1]Anexos FICHA TRA050'!$C$4:$C$7, 0)), "") -> 10 | BF59: =IFERROR(INDEX('[1]Anexos FICHA TRA050'!$C$14:$C$22, MATCH(Tabla467824[[#This Row],[Columna5]], '[1]Anexos FICHA TRA050'!$D$14:$D$22, 0)), "") -> 20.84 | BG59: =IFERROR(INDEX('[1]Anexos FICHA TRA050'!$C$49:$C$54, MATCH(Tabla467824[[#This Row],[Columna5]], '[1]Anexos FICHA TRA050'!$D$49:$D$54, 0)), "") -> 15815 | BH59: =+(((Tabla467824[[#This Row],[CVA2]]*Tabla467824[[#This Row],[f2]])-Tabla467824[[#This Row],[CVN2]])/100)*Tabla467824[[#This Row],[L2]] -> 5607.999 | BK59: =+IF(Tabla467824[[#This Row],[F]]=Tabla467824[[#This Row],[f2]], "IGUAL", "DISTINTO") -> IGUAL | BL59: =+IF(Tabla467824[[#This Row],[CVN]]=Tabla467824[[#This Row],[CVN2]], "IGUAL", "DISTINTO") -> DISTINTO | BM59: =+IF(Tabla467824[[#This Row],[L]]=Tabla467824[[#This Row],[L2]], "IGUAL", "DISTINTO") -> IGUAL
A60: 57 | B60: CAE500092 | C60: 5443LLD | D60: M1 | E60: DIESEL | F60: DIESEL | G60: M1 | H60: X | I60: X | J60: X | L60: X | M60: X | O60: AYVENS | P60: 1 | Q60: RENTING | R60: DEVUELTO | S60: 44176 | T60: 45637 | U60: 1461 | V60: 2024 | W60: 7 | X60: DIESEL | Y60: VOLKSWAGEN | Z60: CADDY 4*4 2.0 TDI 122 CV KOMBI | AA60: 1001 | AB60: AVSA | AC60: 10019060 | AD60: 15 | AE60: 6089MWV | AF60: CITROEN | AG60: Ë-C3 ELÉCTRICO MAX | AH60: ELECTRICO | AI60: 101702 | AJ60: 2024 | AK60: 45625 | AL60: 0 | AM60: 1001 | AN60: 4500424812 | AO60: AVSA | AQ60: X | AR60: COMUNIDAD VALENCIANA | AS60: VR7CBZYA7RT152181 | AT60: 5.6 | AU60: 10 | AV60: 16.4 | AW60: 15815 | AX60: 6262.74 | AY60: N1 | AZ60: CORRECTO ALQUILER | BA60: =+IF(Tabla467824[[#This Row],[TIPO VEHÍCULO]]=Tabla467824[[#This Row],[Columna2]], "IGUAL", "DISTINTO") -> DISTINTO | BB60: =+IF(Tabla467824[[#This Row],[Columna4]]=Tabla467824[[#This Row],[Combustible2]], "IGUAL", "DISTINTO") -> IGUAL | BC60: CAE500092 | BD60: {=IFERROR(INDEX('[1]Anexos FICHA TRA050'!$D$27:$D$44, MATCH(Tabla467824[[#This Row],[Columna5]]&Tabla467824[[#This Row],[Columna4]], '[1]Anexos FICHA TRA050'!$E$27:$E$44&'[1]Anexos FICHA TRA050'!$F$27:$F$44, 0)), "")} -> 6.99 | BE60: =IFERROR(INDEX('[1]Anexos FICHA TRA050'!$B$4:$B$7, MATCH(Tabla467824[[#This Row],[Columna4]], '[1]Anexos FICHA TRA050'!$C$4:$C$7, 0)), "") -> 10 | BF60: =IFERROR(INDEX('[1]Anexos FICHA TRA050'!$C$14:$C$22, MATCH(Tabla467824[[#This Row],[Columna5]], '[1]Anexos FICHA TRA050'!$D$14:$D$22, 0)), "") -> 17.92 | BG60: =IFERROR(INDEX('[1]Anexos FICHA TRA050'!$C$49:$C$54, MATCH(Tabla467824[[#This Row],[Columna5]], '[1]Anexos FICHA TRA050'!$D$49:$D$54, 0)), "") -> 13073 | BH60: =+(((Tabla467824[[#This Row],[CVA2]]*Tabla467824[[#This Row],[f2]])-Tabla467824[[#This Row],[CVN2]])/100)*Tabla467824[[#This Row],[L2]] -> 6795.3454 | BK60: =+IF(Tabla467824[[#This Row],[F]]=Tabla467824[[#This Row],[f2]], "IGUAL", "DISTINTO") -> IGUAL | BL60: =+IF(Tabla467824[[#This Row],[CVN]]=Tabla467824[[#This Row],[CVN2]], "IGUAL", "DISTINTO") -> DISTINTO | BM60: =+IF(Tabla467824[[#This Row],[L]]=Tabla467824[[#This Row],[L2]], "IGUAL", "DISTINTO") -> DISTINTO
A61: 58 | B61: CAE500093 | C61: 5493LLD | D61: M1 | E61: DIESEL | F61: DIESEL | G61: M1 | H61: X | I61: X | J61: X | L61: X | M61: X | O61: AYVENS | P61: 1 | Q61: RENTING | R61: DEVUELTO | S61: 44176 | T61: 45637 | U61: 1461 | V61: 2024 | W61: 7 | X61: DIESEL | Y61: VOLKSWAGEN | Z61: CADDY 4*4 2.0 TDI 122 CV KOMBI | AA61: 1203 | AB61: E.Mixta Metropolitana, SA | AC61: 101224 | AD61: 2 | AE61: 6245MWV | AF61: CITROEN | AG61: Ë-C3 ELÉCTRICO MAX | AH61: ELECTRICO | AI61: 101243 | AJ61: 2024 | AK61: 45625 | AL61: 0 | AM61: 1203 | AN61: 4500424806 | AO61: E.Mixta Metropolitana, SA | AQ61: X | AR61: COMUNIDAD VALENCIANA | AS61: VR7CBZYA5RT153040 | AT61: 5.6 | AU61: 10 | AV61: 16.4 | AW61: 15815 | AX61: 6262.74 | AY61: N1 | AZ61: CORRECTO ALQUILER | BA61: =+IF(Tabla467824[[#This Row],[TIPO VEHÍCULO]]=Tabla467824[[#This Row],[Columna2]], "IGUAL", "DISTINTO") -> DISTINTO | BB61: =+IF(Tabla467824[[#This Row],[Columna4]]=Tabla467824[[#This Row],[Combustible2]], "IGUAL", "DISTINTO") -> IGUAL | BC61: CAE500093 | BD61: {=IFERROR(INDEX('[1]Anexos FICHA TRA050'!$D$27:$D$44, MATCH(Tabla467824[[#This Row],[Columna5]]&Tabla467824[[#This Row],[Columna4]], '[1]Anexos FICHA TRA050'!$E$27:$E$44&'[1]Anexos FICHA TRA050'!$F$27:$F$44, 0)), "")} -> 6.99 | BE61: =IFERROR(INDEX('[1]Anexos FICHA TRA050'!$B$4:$B$7, MATCH(Tabla467824[[#This Row],[Columna4]], '[1]Anexos FICHA TRA050'!$C$4:$C$7, 0)), "") -> 10 | BF61: =IFERROR(INDEX('[1]Anexos FICHA TRA050'!$C$14:$C$22, MATCH(Tabla467824[[#This Row],[Columna5]], '[1]Anexos FICHA TRA050'!$D$14:$D$22, 0)), "") -> 17.92 | BG61: =IFERROR(INDEX('[1]Anexos FICHA TRA050'!$C$49:$C$54, MATCH(Tabla467824[[#This Row],[Columna5]], '[1]Anexos FICHA TRA050'!$D$49:$D$54, 0)), "") -> 13073 | BH61: =+(((Tabla467824[[#This Row],[CVA2]]*Tabla467824[[#This Row],[f2]])-Tabla467824[[#This Row],[CVN2]])/100)*Tabla467824[[#This Row],[L2]] -> 6795.3454 | BI61: Pone M/G | BK61: =+IF(Tabla467824[[#This Row],[F]]=Tabla467824[[#This Row],[f2]], "IGUAL", "DISTINTO") -> IGUAL | BL61: =+IF(Tabla467824[[#This Row],[CVN]]=Tabla467824[[#This Row],[CVN2]], "IGUAL", "DISTINTO") -> DISTINTO | BM61: =+IF(Tabla467824[[#This Row],[L]]=Tabla467824[[#This Row],[L2]], "IGUAL", "DISTINTO") -> DISTINTO | BN61: M
A62: 59 | B62: CAE500095 | C62: 3128GKL | D62: N3 | E62: GASOIL | F62: DIESEL | G62: N3 | K62: X | L62: X | M62: X | O62: PROPIEDAD | P62: 5 | Q62: PROPIEDAD | R62: CANCELADO | S62: 39827 | T62: 45574 | U62: 5747 | V62: 2024 | W62: 4 | X62: DIESEL | Y62: RENAULT | Z62: CAMION CISTERNA 18 TN | AA62: 1053 | AB62: ISG | AC62: 357710 | AD62: 6 | AE62: 8249MXG | AF62: RENAULT | AG62: KANGOO VAN E-TECH ELECTRIC | AH62: ELECTRICO | AI62: 355528 | AJ62: 2024 | AK62: 45646 | AL62: 0 | AM62: 1053 | AN62: 4500426783 | AO62: ISG | AQ62: X | AR62: COMUNIDAD VALENCIANA | AS62: VF1RFK00273934279 | AT62: 35 | AU62: 10 | AV62: 17.3 | AW62: 53508 | AX62: 178021.12 | AY62: N3 | AZ62: CORRECTO PROPIEDAD | BA62: =+IF(Tabla467824[[#This Row],[TIPO VEHÍCULO]]=Tabla467824[[#This Row],[Columna2]], "IGUAL", "DISTINTO") -> IGUAL | BB62: =+IF(Tabla467824[[#This Row],[Columna4]]=Tabla467824[[#This Row],[Combustible2]], "IGUAL", "DISTINTO") -> IGUAL | BC62: CAE500095 | BD62: {=IFERROR(INDEX('[1]Anexos FICHA TRA050'!$D$27:$D$44, MATCH(Tabla467824[[#This Row],[Columna5]]&Tabla467824[[#This Row],[Columna4]], '[1]Anexos FICHA TRA050'!$E$27:$E$44&'[1]Anexos FICHA TRA050'!$F$27:$F$44, 0)), "")} -> 35 | BE62: =IFERROR(INDEX('[1]Anexos FICHA TRA050'!$B$4:$B$7, MATCH(Tabla467824[[#This Row],[Columna4]], '[1]Anexos FICHA TRA050'!$C$4:$C$7, 0)), "") -> 10 | BF62: =IFERROR(INDEX('[1]Anexos FICHA TRA050'!$C$14:$C$22, MATCH(Tabla467824[[#This Row],[Columna5]], '[1]Anexos FICHA TRA050'!$D$14:$D$22, 0)), "") -> 118.53 | BG62: =IFERROR(INDEX('[1]Anexos FICHA TRA050'!$C$49:$C$54, MATCH(Tabla467824[[#This Row],[Columna5]], '[1]Anexos FICHA TRA050'!$D$49:$D$54, 0)), "") -> 53508 | BH62: =+(((Tabla467824[[#This Row],[CVA2]]*Tabla467824[[#This Row],[f2]])-Tabla467824[[#This Row],[CVN2]])/100)*Tabla467824[[#This Row],[L2]] -> 123854.97 | BK62: =+IF(Tabla467824[[#This Row],[F]]=Tabla467824[[#This Row],[f2]], "IGUAL", "DISTINTO") -> IGUAL | BL62: =+IF(Tabla467824[[#This Row],[CVN]]=Tabla467824[[#This Row],[CVN2]], "IGUAL", "DISTINTO") -> DISTINTO | BM62: =+IF(Tabla467824[[#This Row],[L]]=Tabla467824[[#This Row],[L2]], "IGUAL", "DISTINTO") -> IGUAL
A63: 60 | B63: CAE500097 | C63: 9165FXM | D63: N3 | E63: GASOIL | F63: DIESEL | G63: N3 | K63: X | L63: X | M63: X | O63: PROPIEDAD | P63: 5 | Q63: PROPIEDAD | R63: CANCELADO | S63: 39407 | T63: 45341 | U63: 5934 | V63: 2024 | W63: 4 | X63: DIESEL | Y63: VOLVO | Z63: CAMION CISTERNA 26 TN | AA63: 1053 | AB63: ISG | AC63: 357710 | AD63: 7 | AE63: 6125MWV | AF63: CITROEN | AG63: Ë-C3 ELÉCTRICO MAX | AH63: ELECTRICO | AI63: 357710 | AJ63: 2024 | AK63: 45625 | AL63: 0 | AM63: 1053 | AN63: 4500424814 | AO63: ISG | AQ63: X | AR63: COMUNIDAD VALENCIANA | AS63: VR7CBZYA4RT153045 | AT63: 35 | AU63: 10 | AV63: 16.4 | AW63: 53508 | AX63: 178502.69 | AY63: N3 | AZ63: CORRECTO PROPIEDAD | BA63: =+IF(Tabla467824[[#This Row],[TIPO VEHÍCULO]]=Tabla467824[[#This Row],[Columna2]], "IGUAL", "DISTINTO") -> IGUAL | BB63: =+IF(Tabla467824[[#This Row],[Columna4]]=Tabla467824[[#This Row],[Combustible2]], "IGUAL", "DISTINTO") -> IGUAL | BC63: CAE500097 | BD63: {=IFERROR(INDEX('[1]Anexos FICHA TRA050'!$D$27:$D$44, MATCH(Tabla467824[[#This Row],[Columna5]]&Tabla467824[[#This Row],[Columna4]], '[1]Anexos FICHA TRA050'!$E$27:$E$44&'[1]Anexos FICHA TRA050'!$F$27:$F$44, 0)), "")} -> 35 | BE63: =IFERROR(INDEX('[1]Anexos FICHA TRA050'!$B$4:$B$7, MATCH(Tabla467824[[#This Row],[Columna4]], '[1]Anexos FICHA TRA050'!$C$4:$C$7, 0)), "") -> 10 | BF63: =IFERROR(INDEX('[1]Anexos FICHA TRA050'!$C$14:$C$22, MATCH(Tabla467824[[#This Row],[Columna5]], '[1]Anexos FICHA TRA050'!$D$14:$D$22, 0)), "") -> 118.53 | BG63: =IFERROR(INDEX('[1]Anexos FICHA TRA050'!$C$49:$C$54, MATCH(Tabla467824[[#This Row],[Columna5]], '[1]Anexos FICHA TRA050'!$D$49:$D$54, 0)), "") -> 53508 | BH63: =+(((Tabla467824[[#This Row],[CVA2]]*Tabla467824[[#This Row],[f2]])-Tabla467824[[#This Row],[CVN2]])/100)*Tabla467824[[#This Row],[L2]] -> 123854.97 | BK63: =+IF(Tabla467824[[#This Row],[F]]=Tabla467824[[#This Row],[f2]], "IGUAL", "DISTINTO") -> IGUAL | BL63: =+IF(Tabla467824[[#This Row],[CVN]]=Tabla467824[[#This Row],[CVN2]], "IGUAL", "DISTINTO") -> DISTINTO | BM63: =+IF(Tabla467824[[#This Row],[L]]=Tabla467824[[#This Row],[L2]], "IGUAL", "DISTINTO") -> IGUAL
A64: 61 | B64: CAE500098 | C64: V6288GB | D64: N1 | E64: DIESEL | F64: DIESEL | G64: N1 | K64: X | L64: X | M64: X | O64: PROPIEDAD | P64: 5 | Q64: PROPIEDAD | R64: CANCELADO | S64: 35926 | T64: 44972 | U64: 9046 | V64: 2023 | W64: 4 | X64: DIESEL | Y64: MITSUBISHI | Z64: CAMION CISTERNA 3.5 TN | AA64: 1053 | AB64: ISG | AC64: 357711 | AD64: 8 | AE64: 6124MWV | AF64: CITROEN | AG64: Ë-C3 ELÉCTRICO MAX | AH64: ELECTRICO | AI64: 355703 | AJ64: 2024 | AK64: 45625 | AL64: 1 | AM64: 1053 | AN64: 4500424819 | AO64: ISG | AQ64: X | AR64: COMUNIDAD VALENCIANA | AS64: VR7CBZYA3RT154445 | AT64: 35 | AU64: 10 | AV64: 16.4 | AW64: 53508 | AX64: 178502.69 | AY64: N3 | AZ64: CORRECTO PROPIEDAD | BA64: =+IF(Tabla467824[[#This Row],[TIPO VEHÍCULO]]=Tabla467824[[#This Row],[Columna2]], "IGUAL", "DISTINTO") -> DISTINTO | BB64: =+IF(Tabla467824[[#This Row],[Columna4]]=Tabla467824[[#This Row],[Combustible2]], "IGUAL", "DISTINTO") -> IGUAL | BC64: CAE500098 | BD64: {=IFERROR(INDEX('[1]Anexos FICHA TRA050'!$D$27:$D$44, MATCH(Tabla467824[[#This Row],[Columna5]]&Tabla467824[[#This Row],[Columna4]], '[1]Anexos FICHA TRA050'!$E$27:$E$44&'[1]Anexos FICHA TRA050'!$F$27:$F$44, 0)), "")} -> 5.63 | BE64: =IFERROR(INDEX('[1]Anexos FICHA TRA050'!$B$4:$B$7, MATCH(Tabla467824[[#This Row],[Columna4]], '[1]Anexos FICHA TRA050'!$C$4:$C$7, 0)), "") -> 10 | BF64: =IFERROR(INDEX('[1]Anexos FICHA TRA050'!$C$14:$C$22, MATCH(Tabla467824[[#This Row],[Columna5]], '[1]Anexos FICHA TRA050'!$D$14:$D$22, 0)), "") -> 20.84 | BG64: =IFERROR(INDEX('[1]Anexos FICHA TRA050'!$C$49:$C$54, MATCH(Tabla467824[[#This Row],[Columna5]], '[1]Anexos FICHA TRA050'!$D$49:$D$54, 0)), "") -> 15815 | BH64: =+(((Tabla467824[[#This Row],[CVA2]]*Tabla467824[[#This Row],[f2]])-Tabla467824[[#This Row],[CVN2]])/100)*Tabla467824[[#This Row],[L2]] -> 5607.999 | BI64: Es N1 | BK64: =+IF(Tabla467824[[#This Row],[F]]=Tabla467824[[#This Row],[f2]], "IGUAL", "DISTINTO") -> IGUAL | BL64: =+IF(Tabla467824[[#This Row],[CVN]]=Tabla467824[[#This Row],[CVN2]], "IGUAL", "DISTINTO") -> DISTINTO | BM64: =+IF(Tabla467824[[#This Row],[L]]=Tabla467824[[#This Row],[L2]], "IGUAL", "DISTINTO") -> DISTINTO
A65: 62 | B65: CAE500099 | C65: C0296BMW | D65: L3e | E65: GASOLINA | F65: GASOLINA | G65: L | K65: X | O65: PROPIEDAD | P65: 5 | Q65: PROPIEDAD | R65: CANCELADO | S65: 37956 | T65: 45625 | U65: 7669 | V65: 2024 | W65: 4 | X65: GASOLINA | Y65: PEUGEOT | Z65: CICLOMOTOR TREKKER 50 | AA65: 1490 | AB65: EMPRESA MIXTA CALPE | AC65: 208754 | AD65: 1 | AE65: 7151MXV | AF65: RENAULT | AG65: KANGOO VAN E-TECH | AH65: ELECTRICO | AI65: 908755 | AJ65: 2025 | AK65: 45674 | AL65: 1 | AM65: 1490 | AN65: 4500426844 | AO65: EMPRESA MIXTA CALPE | AQ65: X | AR65: COMUNIDAD VALENCIANA | AS65: VF1RFK00073824864 | AT65: 2.9 | AU65: 9.19 | AV65: 17.3 | AW65: 2831 | AX65: 264.72681 | AY65: L3e | AZ65: FALSO PROPIEDAD | BA65: =+IF(Tabla467824[[#This Row],[TIPO VEHÍCULO]]=Tabla467824[[#This Row],[Columna2]], "IGUAL", "DISTINTO") -> IGUAL | BB65: =+IF(Tabla467824[[#This Row],[Columna4]]=Tabla467824[[#This Row],[Combustible2]], "IGUAL", "DISTINTO") -> IGUAL | BC65: CAE500099 | BD65: {=IFERROR(INDEX('[1]Anexos FICHA TRA050'!$D$27:$D$44, MATCH(Tabla467824[[#This Row],[Columna5]]&Tabla467824[[#This Row],[Columna4]], '[1]Anexos FICHA TRA050'!$E$27:$E$44&'[1]Anexos FICHA TRA050'!$F$27:$F$44, 0)), "")} -> 2.9 | BE65: =IFERROR(INDEX('[1]Anexos FICHA TRA050'!$B$4:$B$7, MATCH(Tabla467824[[#This Row],[Columna4]], '[1]Anexos FICHA TRA050'!$C$4:$C$7, 0)), "") -> 9.19 | BF65: =IFERROR(INDEX('[1]Anexos FICHA TRA050'!$C$14:$C$22, MATCH(Tabla467824[[#This Row],[Columna5]], '[1]Anexos FICHA TRA050'!$D$14:$D$22, 0)), "") -> 4.84 | BG65: =IFERROR(INDEX('[1]Anexos FICHA TRA050'!$C$49:$C$54, MATCH(Tabla467824[[#This Row],[Columna5]], '[1]Anexos FICHA TRA050'!$D$49:$D$54, 0)), "") -> 2831 | BH65: =+(((Tabla467824[[#This Row],[CVA2]]*Tabla467824[[#This Row],[f2]])-Tabla467824[[#This Row],[CVN2]])/100)*Tabla467824[[#This Row],[L2]] -> 617.46941 | BK65: =+IF(Tabla467824[[#This Row],[F]]=Tabla467824[[#This Row],[f2]], "IGUAL", "DISTINTO") -> IGUAL | BL65: =+IF(Tabla467824[[#This Row],[CVN]]=Tabla467824[[#This Row],[CVN2]], "IGUAL", "DISTINTO") -> DISTINTO | BM65: =+IF(Tabla467824[[#This Row],[L]]=Tabla467824[[#This Row],[L2]], "IGUAL", "DISTINTO") -> IGUAL
A66: 63 | B66: CAE500100 | C66: 5244MGJ | D66: M1 | E66: DIESEL | F66: DIESEL | G66: M1 | H66: X | J66: X | L66: x | M66: x | O66: AYVENS | P66: 3 | Q66: ALQUILER | R66: DEVUELTO | S66: 45202 | T66: 45259 | U66: 57 | V66: 2023 | W66: 7 | X66: DIESEL | Y66: OPEL | Z66: CORSA 1.5 D 100 CV | AA66: 1505 | AB66: CGAC | AC66: 355589 | AD66: 11 | AE66: 1256MJM | AF66: PEUGEOT | AG66: E-EXPERT PRO 100 KW | AH66: ELECTRICO | AI66: 725441 | AJ66: 2023 | AK66: 45133 | AL66: 0 | AM66: 1505 | AN66: 4500370371 | AO66: CGAC | AQ66: X | AR66: CATALUÑA | AS66: VF3V1ZKXZPZ010849 | AT66: 5.1 | AU66: 10 | AV66: 28.2 | AW66: 13073 | AX66: 2980.644 | AY66: M1 | AZ66: CORRECTO ALQUILER | BA66: =+IF(Tabla467824[[#This Row],[TIPO VEHÍCULO]]=Tabla467824[[#This Row],[Columna2]], "IGUAL", "DISTINTO") -> IGUAL | BB66: =+IF(Tabla467824[[#This Row],[Columna4]]=Tabla467824[[#This Row],[Combustible2]], "IGUAL", "DISTINTO") -> IGUAL | BC66: CAE500100 | BD66: {=IFERROR(INDEX('[1]Anexos FICHA TRA050'!$D$27:$D$44, MATCH(Tabla467824[[#This Row],[Columna5]]&Tabla467824[[#This Row],[Columna4]], '[1]Anexos FICHA TRA050'!$E$27:$E$44&'[1]Anexos FICHA TRA050'!$F$27:$F$44, 0)), "")} -> 6.99 | BE66: =IFERROR(INDEX('[1]Anexos FICHA TRA050'!$B$4:$B$7, MATCH(Tabla467824[[#This Row],[Columna4]], '[1]Anexos FICHA TRA050'!$C$4:$C$7, 0)), "") -> 10 | BF66: =IFERROR(INDEX('[1]Anexos FICHA TRA050'!$C$14:$C$22, MATCH(Tabla467824[[#This Row],[Columna5]], '[1]Anexos FICHA TRA050'!$D$14:$D$22, 0)), "") -> 17.92 | BG66: =IFERROR(INDEX('[1]Anexos FICHA TRA050'!$C$49:$C$54, MATCH(Tabla467824[[#This Row],[Columna5]], '[1]Anexos FICHA TRA050'!$D$49:$D$54, 0)), "") -> 13073 | BH66: =+(((Tabla467824[[#This Row],[CVA2]]*Tabla467824[[#This Row],[f2]])-Tabla467824[[#This Row],[CVN2]])/100)*Tabla467824[[#This Row],[L2]] -> 6795.3454 | BK66: =+IF(Tabla467824[[#This Row],[F]]=Tabla467824[[#This Row],[f2]], "IGUAL", "DISTINTO") -> IGUAL | BL66: =+IF(Tabla467824[[#This Row],[CVN]]=Tabla467824[[#This Row],[CVN2]], "IGUAL", "DISTINTO") -> DISTINTO | BM66: =+IF(Tabla467824[[#This Row],[L]]=Tabla467824[[#This Row],[L2]], "IGUAL", "DISTINTO") -> IGUAL
A67: 64 | B67: CAE500101 | C67: 6742MGH | D67: M1 | E67: DIESEL | F67: DIESEL | G67: M1 | H67: X | J67: X | L67: x | M67: x | O67: AYVENS | P67: 3 | Q67: ALQUILER | R67: DEVUELTO | S67: 45204 | T67: 45259 | U67: 55 | V67: 2023 | W67: 7 | X67: DIESEL | Y67: OPEL | Z67: CORSA 1.5 D 100 CV | AA67: 1505 | AB67: CGAC | AC67: 355589 | AD67: 12 | AE67: 1261MJM | AF67: PEUGEOT | AG67: E-EXPERT PRO 100 KW | AH67: ELECTRICO | AI67: 725455 | AJ67: 2023 | AK67: 45133 | AL67: 0 | AM67: 1505 | AN67: 4500370221 | AO67: CGAC | AQ67: X | AR67: CATALUÑA | AS67: VF3V1ZKXZPZ005194 | AT67: 5.1 | AU67: 10 | AV67: 28.2 | AW67: 13073 | AX67: 2980.644 | AY67: M1 | AZ67: CORRECTO ALQUILER | BA67: =+IF(Tabla467824[[#This Row],[TIPO VEHÍCULO]]=Tabla467824[[#This Row],[Columna2]], "IGUAL", "DISTINTO") -> IGUAL | BB67: =+IF(Tabla467824[[#This Row],[Columna4]]=Tabla467824[[#This Row],[Combustible2]], "IGUAL", "DISTINTO") -> IGUAL | BC67: CAE500101 | BD67: {=IFERROR(INDEX('[1]Anexos FICHA TRA050'!$D$27:$D$44, MATCH(Tabla467824[[#This Row],[Columna5]]&Tabla467824[[#This Row],[Columna4]], '[1]Anexos FICHA TRA050'!$E$27:$E$44&'[1]Anexos FICHA TRA050'!$F$27:$F$44, 0)), "")} -> 6.99 | BE67: =IFERROR(INDEX('[1]Anexos FICHA TRA050'!$B$4:$B$7, MATCH(Tabla467824[[#This Row],[Columna4]], '[1]Anexos FICHA TRA050'!$C$4:$C$7, 0)), "") -> 10 | BF67: =IFERROR(INDEX('[1]Anexos FICHA TRA050'!$C$14:$C$22, MATCH(Tabla467824[[#This Row],[Columna5]], '[1]Anexos FICHA TRA050'!$D$14:$D$22, 0)), "") -> 17.92 | BG67: =IFERROR(INDEX('[1]Anexos FICHA TRA050'!$C$49:$C$54, MATCH(Tabla467824[[#This Row],[Columna5]], '[1]Anexos FICHA TRA050'!$D$49:$D$54, 0)), "") -> 13073 | BH67: =+(((Tabla467824[[#This Row],[CVA2]]*Tabla467824[[#This Row],[f2]])-Tabla467824[[#This Row],[CVN2]])/100)*Tabla467824[[#This Row],[L2]] -> 6795.3454 | BK67: =+IF(Tabla467824[[#This Row],[F]]=Tabla467824[[#This Row],[f2]], "IGUAL", "DISTINTO") -> IGUAL | BL67: =+IF(Tabla467824[[#This Row],[CVN]]=Tabla467824[[#This Row],[CVN2]], "IGUAL", "DISTINTO") -> DISTINTO | BM67: =+IF(Tabla467824[[#This Row],[L]]=Tabla467824[[#This Row],[L2]], "IGUAL", "DISTINTO") -> IGUAL
A68: 65 | B68: CAE500103 | C68: 5188MGJ | D68: M1 | E68: DIESEL | F68: DIESEL | G68: M1 | H68: X | J68: X | L68: x | M68: x | O68: AYVENS | P68: 3 | Q68: ALQUILER | R68: DEVUELTO | S68: 45203 | T68: 45250 | U68: 47 | V68: 2023 | W68: 7 | X68: DIESEL | Y68: OPEL | Z68: CORSA 1.5 D 100 CV | AA68: 1505 | AB68: CGAC | AC68: 355589 | AD68: 13 | AE68: 8654MCZ | AF68: RENAULT | AG68: KANGOO VAN E-TECH | AH68: ELECTRICO | AI68: 725565 | AJ68: 2023 | AK68: 44922 | AL68: 0 | AM68: 1505 | AN68: 4500348266 | AO68: CGAC | AQ68: X | AR68: CATALUÑA | AS68: VF1RFK00670026502 | AT68: 5.1 | AU68: 10 | AV68: 17.3 | AW68: 13073 | AX68: 4405.601 | AY68: M1 | AZ68: CORRECTO ALQUILER | BA68: =+IF(Tabla467824[[#This Row],[TIPO VEHÍCULO]]=Tabla467824[[#This Row],[Columna2]], "IGUAL", "DISTINTO") -> IGUAL | BB68: =+IF(Tabla467824[[#This Row],[Columna4]]=Tabla467824[[#This Row],[Combustible2]], "IGUAL", "DISTINTO") -> IGUAL | BC68: CAE500103 | BD68: {=IFERROR(INDEX('[1]Anexos FICHA TRA050'!$D$27:$D$44, MATCH(Tabla467824[[#This Row],[Columna5]]&Tabla467824[[#This Row],[Columna4]], '[1]Anexos FICHA TRA050'!$E$27:$E$44&'[1]Anexos FICHA TRA050'!$F$27:$F$44, 0)), "")} -> 6.99 | BE68: =IFERROR(INDEX('[1]Anexos FICHA TRA050'!$B$4:$B$7, MATCH(Tabla467824[[#This Row],[Columna4]], '[1]Anexos FICHA TRA050'!$C$4:$C$7, 0)), "") -> 10 | BF68: =IFERROR(INDEX('[1]Anexos FICHA TRA050'!$C$14:$C$22, MATCH(Tabla467824[[#This Row],[Columna5]], '[1]Anexos FICHA TRA050'!$D$14:$D$22, 0)), "") -> 17.92 | BG68: =IFERROR(INDEX('[1]Anexos FICHA TRA050'!$C$49:$C$54, MATCH(Tabla467824[[#This Row],[Columna5]], '[1]Anexos FICHA TRA050'!$D$49:$D$54, 0)), "") -> 13073 | BH68: =+(((Tabla467824[[#This Row],[CVA2]]*Tabla467824[[#This Row],[f2]])-Tabla467824[[#This Row],[CVN2]])/100)*Tabla467824[[#This Row],[L2]] -> 6795.3454 | BK68: =+IF(Tabla467824[[#This Row],[F]]=Tabla467824[[#This Row],[f2]], "IGUAL", "DISTINTO") -> IGUAL | BL68: =+IF(Tabla467824[[#This Row],[CVN]]=Tabla467824[[#This Row],[CVN2]], "IGUAL", "DISTINTO") -> DISTINTO | BM68: =+IF(Tabla467824[[#This Row],[L]]=Tabla467824[[#This Row],[L2]], "IGUAL", "DISTINTO") -> IGUAL
A69: 66 | B69: CAE500104 | C69: 5249MGJ | D69: M1 | E69: DIESEL | F69: DIESEL | G69: M1 | H69: X | L69: x | M69: x | O69: AYVENS | P69: 3 | Q69: ALQUILER | R69: DEVUELTO | S69: 45202 | T69: 45382 | U69: 180 | V69: 2024 | W69: 7 | X69: DIESEL | Y69: OPEL | Z69: CORSA 1.5 D 100 CV | AA69: 1505 | AB69: CGAC | AC69: 355589 | AD69: 14 | AE69: 8328MCZ | AF69: RENAULT | AG69: KANGOO VAN E-TECH | AH69: ELECTRICO | AI69: 725586 | AJ69: 2023 | AK69: 44922 | AL69: -1 | AM69: 1505 | AN69: 4500348764 | AO69: CGAC | AQ69: X | AR69: CATALUÑA | AS69: VF1RFK00169330329 | AT69: 5.1 | AU69: 10 | AV69: 17.3 | AW69: 13073 | AX69: 4405.601 | AY69: M1 | AZ69: FALSO ALQUILER | BA69: =+IF(Tabla467824[[#This Row],[TIPO VEHÍCULO]]=Tabla467824[[#This Row],[Columna2]], "IGUAL", "DISTINTO") -> IGUAL | BB69: =+IF(Tabla467824[[#This Row],[Columna4]]=Tabla467824[[#This Row],[Combustible2]], "IGUAL", "DISTINTO") -> IGUAL | BC69: CAE500104 | BD69: {=IFERROR(INDEX('[1]Anexos FICHA TRA050'!$D$27:$D$44, MATCH(Tabla467824[[#This Row],[Columna5]]&Tabla467824[[#This Row],[Columna4]], '[1]Anexos FICHA TRA050'!$E$27:$E$44&'[1]Anexos FICHA TRA050'!$F$27:$F$44, 0)), "")} -> 6.99 | BE69: =IFERROR(INDEX('[1]Anexos FICHA TRA050'!$B$4:$B$7, MATCH(Tabla467824[[#This Row],[Columna4]], '[1]Anexos FICHA TRA050'!$C$4:$C$7, 0)), "") -> 10 | BF69: =IFERROR(INDEX('[1]Anexos FICHA TRA050'!$C$14:$C$22, MATCH(Tabla467824[[#This Row],[Columna5]], '[1]Anexos FICHA TRA050'!$D$14:$D$22, 0)), "") -> 17.92 | BG69: =IFERROR(INDEX('[1]Anexos FICHA TRA050'!$C$49:$C$54, MATCH(Tabla467824[[#This Row],[Columna5]], '[1]Anexos FICHA TRA050'!$D$49:$D$54, 0)), "") -> 13073 | BH69: =+(((Tabla467824[[#This Row],[CVA2]]*Tabla467824[[#This Row],[f2]])-Tabla467824[[#This Row],[CVN2]])/100)*Tabla467824[[#This Row],[L2]] -> 6795.3454 | BK69: =+IF(Tabla467824[[#This Row],[F]]=Tabla467824[[#This Row],[f2]], "IGUAL", "DISTINTO") -> IGUAL | BL69: =+IF(Tabla467824[[#This Row],[CVN]]=Tabla467824[[#This Row],[CVN2]], "IGUAL", "DISTINTO") -> DISTINTO | BM69: =+IF(Tabla467824[[#This Row],[L]]=Tabla467824[[#This Row],[L2]], "IGUAL", "DISTINTO") -> IGUAL
A70: 67 | B70: CAE500105 | C70: 1918LMY | D70: M1 | E70: DIESEL | F70: DIESEL | G70: M1 | H70: X | I70: X | J70: X | L70: x | M70: x | O70: AYVENS | P70: 3 | Q70: ALQUILER | R70: DEVUELTO | S70: 45323 | T70: 45358 | U70: 35 | V70: 2024 | W70: 7 | X70: DIESEL | Y70: OPEL | Z70: CORSA 1.5 D100 CV | AA70: 1505 | AB70: CGAC | AC70: 725496 | AD70: 15 | AE70: 2043MJP | AF70: RENAULT | AG70: KANGOO VAN E-TECH | AH70: ELECTRICO | AI70: 725472 | AJ70: 2023 | AK70: 45135 | AL70: -1 | AM70: 1505 | AN70: 4500352342 | AO70: CGAC | AQ70: X | AR70: CATALUÑA | AS70: VF1RFK00670693201 | AT70: 5.1 | AU70: 10 | AV70: 17.3 | AW70: 13073 | AX70: 4405.601 | AY70: M1 | AZ70: CORRECTO ALQUILER | BA70: =+IF(Tabla467824[[#This Row],[TIPO VEHÍCULO]]=Tabla467824[[#This Row],[Columna2]], "IGUAL", "DISTINTO") -> IGUAL | BB70: =+IF(Tabla467824[[#This Row],[Columna4]]=Tabla467824[[#This Row],[Combustible2]], "IGUAL", "DISTINTO") -> IGUAL | BC70: CAE500105 | BD70: {=IFERROR(INDEX('[1]Anexos FICHA TRA050'!$D$27:$D$44, MATCH(Tabla467824[[#This Row],[Columna5]]&Tabla467824[[#This Row],[Columna4]], '[1]Anexos FICHA TRA050'!$E$27:$E$44&'[1]Anexos FICHA TRA050'!$F$27:$F$44, 0)), "")} -> 6.99 | BE70: =IFERROR(INDEX('[1]Anexos FICHA TRA050'!$B$4:$B$7, MATCH(Tabla467824[[#This Row],[Columna4]], '[1]Anexos FICHA TRA050'!$C$4:$C$7, 0)), "") -> 10 | BF70: =IFERROR(INDEX('[1]Anexos FICHA TRA050'!$C$14:$C$22, MATCH(Tabla467824[[#This Row],[Columna5]], '[1]Anexos FICHA TRA050'!$D$14:$D$22, 0)), "") -> 17.92 | BG70: =IFERROR(INDEX('[1]Anexos FICHA TRA050'!$C$49:$C$54, MATCH(Tabla467824[[#This Row],[Columna5]], '[1]Anexos FICHA TRA050'!$D$49:$D$54, 0)), "") -> 13073 | BH70: =+(((Tabla467824[[#This Row],[CVA2]]*Tabla467824[[#This Row],[f2]])-Tabla467824[[#This Row],[CVN2]])/100)*Tabla467824[[#This Row],[L2]] -> 6795.3454 | BK70: =+IF(Tabla467824[[#This Row],[F]]=Tabla467824[[#This Row],[f2]], "IGUAL", "DISTINTO") -> IGUAL | BL70: =+IF(Tabla467824[[#This Row],[CVN]]=Tabla467824[[#This Row],[CVN2]], "IGUAL", "DISTINTO") -> DISTINTO | BM70: =+IF(Tabla467824[[#This Row],[L]]=Tabla467824[[#This Row],[L2]], "IGUAL", "DISTINTO") -> IGUAL
A71: 68 | B71: CAE500106 | C71: 2258JPC | D71: N1 | E71: DIESEL | F71: DIESEL | G71: N1 | H71: X | I71: X | J71: X | L71: X | M71: X | O71: AYVENS | P71: 1 | Q71: RENTING | R71: DEVUELTO | S71: 42527 | T71: 45316 | U71: 2789 | V71: 2024 | W71: 7 | X71: DIESEL | Y71: OPEL | Z71: COMBO 1.3 CDTI 90 CV | AA71: 1505 | AB71: CGAC | AC71: 205335 | AD71: 16 | AE71: 2062MJP | AF71: RENAULT | AG71: KANGOO VAN E-TECH | AH71: ELECTRICO | AI71: 725441 | AJ71: 2023 | AK71: 45135 | AL71: -1 | AM71: 1505 | AN71: 4500370369 | AO71: CGAC | AQ71: X | AR71: CATALUÑA | AS71: VF1RFK00370927200 | AT71: 5.6 | AU71: 10 | AV71: 17.3 | AW71: 15815 | AX71: 6120.405 | AY71: N1 | AZ71: CORRECTO ALQUILER | BA71: =+IF(Tabla467824[[#This Row],[TIPO VEHÍCULO]]=Tabla467824[[#This Row],[Columna2]], "IGUAL", "DISTINTO") -> IGUAL | BB71: =+IF(Tabla467824[[#This Row],[Columna4]]=Tabla467824[[#This Row],[Combustible2]], "IGUAL", "DISTINTO") -> IGUAL | BC71: CAE500106 | BD71: {=IFERROR(INDEX('[1]Anexos FICHA TRA050'!$D$27:$D$44, MATCH(Tabla467824[[#This Row],[Columna5]]&Tabla467824[[#This Row],[Columna4]], '[1]Anexos FICHA TRA050'!$E$27:$E$44&'[1]Anexos FICHA TRA050'!$F$27:$F$44, 0)), "")} -> 5.63 | BE71: =IFERROR(INDEX('[1]Anexos FICHA TRA050'!$B$4:$B$7, MATCH(Tabla467824[[#This Row],[Columna4]], '[1]Anexos FICHA TRA050'!$C$4:$C$7, 0)), "") -> 10 | BF71: =IFERROR(INDEX('[1]Anexos FICHA TRA050'!$C$14:$C$22, MATCH(Tabla467824[[#This Row],[Columna5]], '[1]Anexos FICHA TRA050'!$D$14:$D$22, 0)), "") -> 20.84 | BG71: =IFERROR(INDEX('[1]Anexos FICHA TRA050'!$C$49:$C$54, MATCH(Tabla467824[[#This Row],[Columna5]], '[1]Anexos FICHA TRA050'!$D$49:$D$54, 0)), "") -> 15815 | BH71: =+(((Tabla467824[[#This Row],[CVA2]]*Tabla467824[[#This Row],[f2]])-Tabla467824[[#This Row],[CVN2]])/100)*Tabla467824[[#This Row],[L2]] -> 5607.999 | BK71: =+IF(Tabla467824[[#This Row],[F]]=Tabla467824[[#This Row],[f2]], "IGUAL", "DISTINTO") -> IGUAL | BL71: =+IF(Tabla467824[[#This Row],[CVN]]=Tabla467824[[#This Row],[CVN2]], "IGUAL", "DISTINTO") -> DISTINTO | BM71: =+IF(Tabla467824[[#This Row],[L]]=Tabla467824[[#This Row],[L2]], "IGUAL", "DISTINTO") -> IGUAL
A72: 69 | B72: CAE500107 | C72: 0290JLY | D72: N1 | E72: DIESEL | F72: DIESEL | G72: N1 | H72: X | I72: X | J72: X | L72: X | M72: X | O72: AYVENS | P72: 1 | Q72: RENTING | R72: DEVUELTO | S72: 42445 | T72: 45001 | U72: 2556 | V72: 2023 | W72: 7 | X72: DIESEL | Y72: OPEL | Z72: COMBO 1.3 CDTI 90 CV | AA72: 1400 | AB72: EGEVASA | AC72: 208405 | AD72: 4 | AE72: 3191MXJ | AF72: RENAULT | AG72: KANGOO VAN E-TECH ELECTRIC | AH72: ELECTRICO | AI72: 208356 | AJ72: 2024 | AK72: 45649 | AL72: 1 | AM72: 1400 | AN72: 4500426875 | AO72: EGEVASA | AQ72: X | AR72: COMUNIDAD VALENCIANA | AS72: VF1RFK00973824863 | AT72: 5.6 | AU72: 10 | AV72: 17.3 | AW72: 15815 | AX72: 6120.405 | AY72: N1 | AZ72: CORRECTO ALQUILER | BA72: =+IF(Tabla467824[[#This Row],[TIPO VEHÍCULO]]=Tabla467824[[#This Row],[Columna2]], "IGUAL", "DISTINTO") -> IGUAL | BB72: =+IF(Tabla467824[[#This Row],[Columna4]]=Tabla467824[[#This Row],[Combustible2]], "IGUAL", "DISTINTO") -> IGUAL | BC72: CAE500107 | BD72: {=IFERROR(INDEX('[1]Anexos FICHA TRA050'!$D$27:$D$44, MATCH(Tabla467824[[#This Row],[Columna5]]&Tabla467824[[#This Row],[Columna4]], '[1]Anexos FICHA TRA050'!$E$27:$E$44&'[1]Anexos FICHA TRA050'!$F$27:$F$44, 0)), "")} -> 5.63 | BE72: =IFERROR(INDEX('[1]Anexos FICHA TRA050'!$B$4:$B$7, MATCH(Tabla467824[[#This Row],[Columna4]], '[1]Anexos FICHA TRA050'!$C$4:$C$7, 0)), "") -> 10 | BF72: =IFERROR(INDEX('[1]Anexos FICHA TRA050'!$C$14:$C$22, MATCH(Tabla467824[[#This Row],[Columna5]], '[1]Anexos FICHA TRA050'!$D$14:$D$22, 0)), "") -> 20.84 | BG72: =IFERROR(INDEX('[1]Anexos FICHA TRA050'!$C$49:$C$54, MATCH(Tabla467824[[#This Row],[Columna5]], '[1]Anexos FICHA TRA050'!$D$49:$D$54, 0)), "") -> 15815 | BH72: =+(((Tabla467824[[#This Row],[CVA2]]*Tabla467824[[#This Row],[f2]])-Tabla467824[[#This Row],[CVN2]])/100)*Tabla467824[[#This Row],[L2]] -> 5607.999 | BK72: =+IF(Tabla467824[[#This Row],[F]]=Tabla467824[[#This Row],[f2]], "IGUAL", "DISTINTO") -> IGUAL | BL72: =+IF(Tabla467824[[#This Row],[CVN]]=Tabla467824[[#This Row],[CVN2]], "IGUAL", "DISTINTO") -> DISTINTO | BM72: =+IF(Tabla467824[[#This Row],[L]]=Tabla467824[[#This Row],[L2]], "IGUAL", "DISTINTO") -> IGUAL
A73: 70 | B73: CAE500108 | C73: 9094KRJ | D73: N1 | E73: DIESEL | F73: DIESEL | G73: N1 | H73: X | I73: X | J73: X | L73: x | M73: x | O73: AYVENS | P73: 1 | Q73: RENTING | R73: DEVUELTO | S73: 43415 | T73: 45356 | U73: 1941 | V73: 2024 | W73: 7 | X73: DIESEL | Y73: OPEL | Z73: COMBO 1.3 CDTI 95 CV | AA73: 1505 | AB73: CGAC | AC73: 205324 | AD73: 17 | AE73: 8623MCZ | AF73: RENAULT | AG73: KANGOO VAN E-TECH | AH73: ELECTRICO | AI73: 725565 | AJ73: 2023 | AK73: 44922 | AL73: -1 | AM73: 1505 | AN73: 4500348261 | AO73: CGAC | AQ73: X | AR73: CATALUÑA | AS73: VF1RFK00870026503 | AT73: 5.6 | AU73: 10 | AV73: 17.3 | AW73: 15815 | AX73: 6120.405 | AY73: N1 | AZ73: CORRECTO ALQUILER | BA73: =+IF(Tabla467824[[#This Row],[TIPO VEHÍCULO]]=Tabla467824[[#This Row],[Columna2]], "IGUAL", "DISTINTO") -> IGUAL | BB73: =+IF(Tabla467824[[#This Row],[Columna4]]=Tabla467824[[#This Row],[Combustible2]], "IGUAL", "DISTINTO") -> IGUAL | BC73: CAE500108 | BD73: {=IFERROR(INDEX('[1]Anexos FICHA TRA050'!$D$27:$D$44, MATCH(Tabla467824[[#This Row],[Columna5]]&Tabla467824[[#This Row],[Columna4]], '[1]Anexos FICHA TRA050'!$E$27:$E$44&'[1]Anexos FICHA TRA050'!$F$27:$F$44, 0)), "")} -> 5.63 | BE73: =IFERROR(INDEX('[1]Anexos FICHA TRA050'!$B$4:$B$7, MATCH(Tabla467824[[#This Row],[Columna4]], '[1]Anexos FICHA TRA050'!$C$4:$C$7, 0)), "") -> 10 | BF73: =IFERROR(INDEX('[1]Anexos FICHA TRA050'!$C$14:$C$22, MATCH(Tabla467824[[#This Row],[Columna5]], '[1]Anexos FICHA TRA050'!$D$14:$D$22, 0)), "") -> 20.84 | BG73: =IFERROR(INDEX('[1]Anexos FICHA TRA050'!$C$49:$C$54, MATCH(Tabla467824[[#This Row],[Columna5]], '[1]Anexos FICHA TRA050'!$D$49:$D$54, 0)), "") -> 15815 | BH73: =+(((Tabla467824[[#This Row],[CVA2]]*Tabla467824[[#This Row],[f2]])-Tabla467824[[#This Row],[CVN2]])/100)*Tabla467824[[#This Row],[L2]] -> 5607.999 | BK73: =+IF(Tabla467824[[#This Row],[F]]=Tabla467824[[#This Row],[f2]], "IGUAL", "DISTINTO") -> IGUAL | BL73: =+IF(Tabla467824[[#This Row],[CVN]]=Tabla467824[[#This Row],[CVN2]], "IGUAL", "DISTINTO") -> DISTINTO | BM73: =+IF(Tabla467824[[#This Row],[L]]=Tabla467824[[#This Row],[L2]], "IGUAL", "DISTINTO") -> IGUAL
A74: 71 | B74: CAE500109 | C74: 6586KPD | D74: N1 | E74: DIESEL | F74: DIESEL | G74: N1 | H74: X | I74: X | J74: X | L74: x | M74: x | O74: AYVENS | P74: 1 | Q74: RENTING | R74: DEVUELTO | S74: 43355 | T74: 45181 | U74: 1826 | V74: 2023 | W74: 7 | X74: DIESEL | Y74: OPEL | Z74: COMBO 1.3 CDTI 95 CV | AA74: 1505 | AB74: CGAC | AC74: 725468 | AD74: 18 | AE74: 8868KDN | AF74: RENAULT | AG74: ZOE 40 | AH74: ELECTRICO | AI74: 725586 | AJ74: 2023 | AK74: 43019 | AL74: 0 | AM74: 1505 | AN74: 4500352582 | AO74: CGAC | AQ74: X | AR74: CATALUÑA | AS74: VF1AGVYC058921527 | AT74: 5.6 | AU74: 10 | AV74: 13.3 | AW74: 15815 | AX74: 6753.005 | AY74: N1 | AZ74: CORRECTO ALQUILER | BA74: =+IF(Tabla467824[[#This Row],[TIPO VEHÍCULO]]=Tabla467824[[#This Row],[Columna2]], "IGUAL", "DISTINTO") -> IGUAL | BB74: =+IF(Tabla467824[[#This Row],[Columna4]]=Tabla467824[[#This Row],[Combustible2]], "IGUAL", "DISTINTO") -> IGUAL | BC74: CAE500109 | BD74: {=IFERROR(INDEX('[1]Anexos FICHA TRA050'!$D$27:$D$44, MATCH(Tabla467824[[#This Row],[Columna5]]&Tabla467824[[#This Row],[Columna4]], '[1]Anexos FICHA TRA050'!$E$27:$E$44&'[1]Anexos FICHA TRA050'!$F$27:$F$44, 0)), "")} -> 5.63 | BE74: =IFERROR(INDEX('[1]Anexos FICHA TRA050'!$B$4:$B$7, MATCH(Tabla467824[[#This Row],[Columna4]], '[1]Anexos FICHA TRA050'!$C$4:$C$7, 0)), "") -> 10 | BF74: =IFERROR(INDEX('[1]Anexos FICHA TRA050'!$C$14:$C$22, MATCH(Tabla467824[[#This Row],[Columna5]], '[1]Anexos FICHA TRA050'!$D$14:$D$22, 0)), "") -> 20.84 | BG74: =IFERROR(INDEX('[1]Anexos FICHA TRA050'!$C$49:$C$54, MATCH(Tabla467824[[#This Row],[Columna5]], '[1]Anexos FICHA TRA050'!$D$49:$D$54, 0)), "") -> 15815 | BH74: =+(((Tabla467824[[#This Row],[CVA2]]*Tabla467824[[#This Row],[f2]])-Tabla467824[[#This Row],[CVN2]])/100)*Tabla467824[[#This Row],[L2]] -> 5607.999 | BK74: =+IF(Tabla467824[[#This Row],[F]]=Tabla467824[[#This Row],[f2]], "IGUAL", "DISTINTO") -> IGUAL | BL74: =+IF(Tabla467824[[#This Row],[CVN]]=Tabla467824[[#This Row],[CVN2]], "IGUAL", "DISTINTO") -> DISTINTO | BM74: =+IF(Tabla467824[[#This Row],[L]]=Tabla467824[[#This Row],[L2]], "IGUAL", "DISTINTO") -> IGUAL
A75: 72 | B75: CAE500110 | C75: 7960KHZ | D75: M1 | E75: DIESEL | F75: DIESEL | G75: M1 | H75: X | I75: X | J75: X | L75: X | M75: X | O75: AYVENS | P75: 1 | Q75: RENTING | R75: DEVUELTO | S75: 43172 | T75: 44998 | U75: 1826 | V75: 2023 | W75: 7 | X75: DIESEL | Y75: OPEL | Z75: CORSA 1.3 CDTI 75 CV 5P | AA75: 1200 | AB75: EMIVASA | AC75: 12009060 | AD75: 6 | AE75: 0210MWZ | AF75: CITROEN | AG75: Ë-C3 ELÉCTRICO MAX | AH75: ELECTRICO | AI75: 100011 | AJ75: 2024 | AK75: 45637 | AL75: 1 | AM75: 1200 | AN75: 4500424902 | AO75: EMIVASA | AQ75: X | AR75: COMUNIDAD VALENCIANA | AS75: VR7CBZYA5RT153037 | AT75: 5.1 | AU75: 10 | AV75: 16.4 | AW75: 13073 | AX75: 4523.258 | AY75: M1 | AZ75: CORRECTO ALQUILER | BA75: =+IF(Tabla467824[[#This Row],[TIPO VEHÍCULO]]=Tabla467824[[#This Row],[Columna2]], "IGUAL", "DISTINTO") -> IGUAL | BB75: =+IF(Tabla467824[[#This Row],[Columna4]]=Tabla467824[[#This Row],[Combustible2]], "IGUAL", "DISTINTO") -> IGUAL | BC75: CAE500110 | BD75: {=IFERROR(INDEX('[1]Anexos FICHA TRA050'!$D$27:$D$44, MATCH(Tabla467824[[#This Row],[Columna5]]&Tabla467824[[#This Row],[Columna4]], '[1]Anexos FICHA TRA050'!$E$27:$E$44&'[1]Anexos FICHA TRA050'!$F$27:$F$44, 0)), "")} -> 6.99 | BE75: =IFERROR(INDEX('[1]Anexos FICHA TRA050'!$B$4:$B$7, MATCH(Tabla467824[[#This Row],[Columna4]], '[1]Anexos FICHA TRA050'!$C$4:$C$7, 0)), "") -> 10 | BF75: =IFERROR(INDEX('[1]Anexos FICHA TRA050'!$C$14:$C$22, MATCH(Tabla467824[[#This Row],[Columna5]], '[1]Anexos FICHA TRA050'!$D$14:$D$22, 0)), "") -> 17.92 | BG75: =IFERROR(INDEX('[1]Anexos FICHA TRA050'!$C$49:$C$54, MATCH(Tabla467824[[#This Row],[Columna5]], '[1]Anexos FICHA TRA050'!$D$49:$D$54, 0)), "") -> 13073 | BH75: =+(((Tabla467824[[#This Row],[CVA2]]*Tabla467824[[#This Row],[f2]])-Tabla467824[[#This Row],[CVN2]])/100)*Tabla467824[[#This Row],[L2]] -> 6795.3454 | BK75: =+IF(Tabla467824[[#This Row],[F]]=Tabla467824[[#This Row],[f2]], "IGUAL", "DISTINTO") -> IGUAL | BL75: =+IF(Tabla467824[[#This Row],[CVN]]=Tabla467824[[#This Row],[CVN2]], "IGUAL", "DISTINTO") -> DISTINTO | BM75: =+IF(Tabla467824[[#This Row],[L]]=Tabla467824[[#This Row],[L2]], "IGUAL", "DISTINTO") -> IGUAL
A76: 73 | B76: CAE500111 | C76: 8288KJX | D76: M1 | E76: DIESEL | F76: DIESEL | G76: M1 | H76: X | I76: X | J76: X | L76: X | M76: X | O76: AYVENS | P76: 1 | Q76: RENTING | R76: DEVUELTO | S76: 43213 | T76: 45039 | U76: 1826 | V76: 2023 | W76: 7 | X76: DIESEL | Y76: OPEL | Z76: CORSA 1.3 CDTI 75 CV 5P | AA76: 1066 | AB76: CANALIZ. CIVILES S.A. | AC76: 356018 | AD76: 6 | AE76: 6033MWV | AF76: CITROEN | AG76: Ë-C3 ELÉCTRICO MAX | AH76: ELECTRICO | AI76: 10669100 | AJ76: 2024 | AK76: 45625 | AL76: 1 | AM76: 1066 | AN76: 4500424801 | AO76: CANALIZ. CIVILES S.A. | AQ76: X | AR76: COMUNIDAD VALENCIANA | AS76: VR7CBZYAXRT152210 | AT76: 5.1 | AU76: 10 | AV76: 16.4 | AW76: 13073 | AX76: 4523.258 | AY76: M1 | AZ76: CORRECTO ALQUILER | BA76: =+IF(Tabla467824[[#This Row],[TIPO VEHÍCULO]]=Tabla467824[[#This Row],[Columna2]], "IGUAL", "DISTINTO") -> IGUAL | BB76: =+IF(Tabla467824[[#This Row],[Columna4]]=Tabla467824[[#This Row],[Combustible2]], "IGUAL", "DISTINTO") -> IGUAL | BC76: CAE500111 | BD76: {=IFERROR(INDEX('[1]Anexos FICHA TRA050'!$D$27:$D$44, MATCH(Tabla467824[[#This Row],[Columna5]]&Tabla467824[[#This Row],[Columna4]], '[1]Anexos FICHA TRA050'!$E$27:$E$44&'[1]Anexos FICHA TRA050'!$F$27:$F$44, 0)), "")} -> 6.99 | BE76: =IFERROR(INDEX('[1]Anexos FICHA TRA050'!$B$4:$B$7, MATCH(Tabla467824[[#This Row],[Columna4]], '[1]Anexos FICHA TRA050'!$C$4:$C$7, 0)), "") -> 10 | BF76: =IFERROR(INDEX('[1]Anexos FICHA TRA050'!$C$14:$C$22, MATCH(Tabla467824[[#This Row],[Columna5]], '[1]Anexos FICHA TRA050'!$D$14:$D$22, 0)), "") -> 17.92 | BG76: =IFERROR(INDEX('[1]Anexos FICHA TRA050'!$C$49:$C$54, MATCH(Tabla467824[[#This Row],[Columna5]], '[1]Anexos FICHA TRA050'!$D$49:$D$54, 0)), "") -> 13073 | BH76: =+(((Tabla467824[[#This Row],[CVA2]]*Tabla467824[[#This Row],[f2]])-Tabla467824[[#This Row],[CVN2]])/100)*Tabla467824[[#This Row],[L2]] -> 6795.3454 | BK76: =+IF(Tabla467824[[#This Row],[F]]=Tabla467824[[#This Row],[f2]], "IGUAL", "DISTINTO") -> IGUAL | BL76: =+IF(Tabla467824[[#This Row],[CVN]]=Tabla467824[[#This Row],[CVN2]], "IGUAL", "DISTINTO") -> DISTINTO | BM76: =+IF(Tabla467824[[#This Row],[L]]=Tabla467824[[#This Row],[L2]], "IGUAL", "DISTINTO") -> IGUAL
A77: 74 | B77: CAE500112 | C77: 0426KHR | D77: M1 | E77: DIESEL | F77: DIESEL | G77: M1 | H77: X | J77: X | L77: x | M77: x | O77: AYVENS | P77: 1 | Q77: RENTING | R77: DEVUELTO | S77: 43160 | T77: 44986 | U77: 1826 | V77: 2023 | W77: 7 | X77: DIESEL | Y77: OPEL | Z77: CORSA 1.3 CDTI 75 CV 5P | AA77: 1001 | AB77: AVSA | AC77: 10019060 | AD77: 16 | AE77: 2704MXG | AF77: RENAULT | AG77: KANGOO VAN E-TECH ELECTRIC | AH77: ELECTRICO | AI77: 200599 | AJ77: 2024 | AK77: 45645 | AL77: 1 | AM77: 1001 | AN77: 4500426846 | AO77: AVSA | AQ77: X | AR77: COMUNIDAD VALENCIANA | AS77: VF1RFK00073934278 | AT77: 5.1 | AU77: 10 | AV77: 17.3 | AW77: 13073 | AX77: 4405.601 | AY77: M1 | AZ77: CORRECTO ALQUILER | BA77: =+IF(Tabla467824[[#This Row],[TIPO VEHÍCULO]]=Tabla467824[[#This Row],[Columna2]], "IGUAL", "DISTINTO") -> IGUAL | BB77: =+IF(Tabla467824[[#This Row],[Columna4]]=Tabla467824[[#This Row],[Combustible2]], "IGUAL", "DISTINTO") -> IGUAL | BC77: CAE500112 | BD77: {=IFERROR(INDEX('[1]Anexos FICHA TRA050'!$D$27:$D$44, MATCH(Tabla467824[[#This Row],[Columna5]]&Tabla467824[[#This Row],[Columna4]], '[1]Anexos FICHA TRA050'!$E$27:$E$44&'[1]Anexos FICHA TRA050'!$F$27:$F$44, 0)), "")} -> 6.99 | BE77: =IFERROR(INDEX('[1]Anexos FICHA TRA050'!$B$4:$B$7, MATCH(Tabla467824[[#This Row],[Columna4]], '[1]Anexos FICHA TRA050'!$C$4:$C$7, 0)), "") -> 10 | BF77: =IFERROR(INDEX('[1]Anexos FICHA TRA050'!$C$14:$C$22, MATCH(Tabla467824[[#This Row],[Columna5]], '[1]Anexos FICHA TRA050'!$D$14:$D$22, 0)), "") -> 17.92 | BG77: =IFERROR(INDEX('[1]Anexos FICHA TRA050'!$C$49:$C$54, MATCH(Tabla467824[[#This Row],[Columna5]], '[1]Anexos FICHA TRA050'!$D$49:$D$54, 0)), "") -> 13073 | BH77: =+(((Tabla467824[[#This Row],[CVA2]]*Tabla467824[[#This Row],[f2]])-Tabla467824[[#This Row],[CVN2]])/100)*Tabla467824[[#This Row],[L2]] -> 6795.3454 | BK77: =+IF(Tabla467824[[#This Row],[F]]=Tabla467824[[#This Row],[f2]], "IGUAL", "DISTINTO") -> IGUAL | BL77: =+IF(Tabla467824[[#This Row],[CVN]]=Tabla467824[[#This Row],[CVN2]], "IGUAL", "DISTINTO") -> DISTINTO | BM77: =+IF(Tabla467824[[#This Row],[L]]=Tabla467824[[#This Row],[L2]], "IGUAL", "DISTINTO") -> IGUAL
A78: 75 | B78: CAE500113 | C78: 2825KMP | D78: M1 | E78: DIESEL | F78: DIESEL | G78: M1 | H78: X | I78: X | J78: X | L78: X | M78: X | O78: AYVENS | P78: 1 | Q78: RENTING | R78: DEVUELTO | S78: 43312 | T78: 45323 | U78: 2011 | V78: 2024 | W78: 7 | X78: DIESEL | Y78: OPEL | Z78: CORSA 1.3 CDTI 75 CV 5P | AA78: 1066 | AB78: CANALIZ. CIVILES S.A. | AC78: 356001 | AD78: 7 | AE78: 8637MWT | AF78: RENAULT | AG78: KANGOO VAN E-TECH ELECTRIC | AH78: ELECTRICO | AI78: 356006 | AJ78: 2024 | AK78: 45625 | AL78: 0 | AM78: 1066 | AN78: 4500426776 | AO78: CANALIZ. CIVILES S.A. | AQ78: X | AR78: COMUNIDAD VALENCIANA | AS78: VF1RFK00973824815 | AT78: 5.1 | AU78: 10 | AV78: 17.3 | AW78: 13073 | AX78: 4405.601 | AY78: M1 | AZ78: CORRECTO ALQUILER | BA78: =+IF(Tabla467824[[#This Row],[TIPO VEHÍCULO]]=Tabla467824[[#This Row],[Columna2]], "IGUAL", "DISTINTO") -> IGUAL | BB78: =+IF(Tabla467824[[#This Row],[Columna4]]=Tabla467824[[#This Row],[Combustible2]], "IGUAL", "DISTINTO") -> IGUAL | BC78: CAE500113 | BD78: {=IFERROR(INDEX('[1]Anexos FICHA TRA050'!$D$27:$D$44, MATCH(Tabla467824[[#This Row],[Columna5]]&Tabla467824[[#This Row],[Columna4]], '[1]Anexos FICHA TRA050'!$E$27:$E$44&'[1]Anexos FICHA TRA050'!$F$27:$F$44, 0)), "")} -> 6.99 | BE78: =IFERROR(INDEX('[1]Anexos FICHA TRA050'!$B$4:$B$7, MATCH(Tabla467824[[#This Row],[Columna4]], '[1]Anexos FICHA TRA050'!$C$4:$C$7, 0)), "") -> 10 | BF78: =IFERROR(INDEX('[1]Anexos FICHA TRA050'!$C$14:$C$22, MATCH(Tabla467824[[#This Row],[Columna5]], '[1]Anexos FICHA TRA050'!$D$14:$D$22, 0)), "") -> 17.92 | BG78: =IFERROR(INDEX('[1]Anexos FICHA TRA050'!$C$49:$C$54, MATCH(Tabla467824[[#This Row],[Columna5]], '[1]Anexos FICHA TRA050'!$D$49:$D$54, 0)), "") -> 13073 | BH78: =+(((Tabla467824[[#This Row],[CVA2]]*Tabla467824[[#This Row],[f2]])-Tabla467824[[#This Row],[CVN2]])/100)*Tabla467824[[#This Row],[L2]] -> 6795.3454 | BK78: =+IF(Tabla467824[[#This Row],[F]]=Tabla467824[[#This Row],[f2]], "IGUAL", "DISTINTO") -> IGUAL | BL78: =+IF(Tabla467824[[#This Row],[CVN]]=Tabla467824[[#This Row],[CVN2]], "IGUAL", "DISTINTO") -> DISTINTO | BM78: =+IF(Tabla467824[[#This Row],[L]]=Tabla467824[[#This Row],[L2]], "IGUAL", "DISTINTO") -> IGUAL
A79: 76 | B79: CAE500114 | C79: 2179KNN | D79: M1 | E79: DIESEL | F79: DIESEL | G79: M1 | H79: X | I79: X | L79: X | M79: X | O79: AYVENS | P79: 1 | Q79: RENTING | R79: DEVUELTO | S79: 43343 | T79: 45016 | U79: 1673 | V79: 2023 | W79: 7 | X79: DIESEL | Y79: OPEL | Z79: CORSA 1.3 CDTI 75 CV 5P | AA79: 1004 | AB79: G.O.MEDIOAMBIENTE S.L. | AC79: 350469 | AD79: 5 | AE79: 5566KSD | AF79: RENAULT | AG79: ZOE 40 | AH79: ELECTRICO | AI79: 724359 | AJ79: 2023 | AK79: 43439 | AL79: 0 | AM79: 1004 | AN79: 4500389256 | AO79: G.O.MEDIOAMBIENTE S.L. | AQ79: X | AR79: COMUNIDAD VALENCIANA | AS79: VF1AG000861226255 | AT79: 5.1 | AU79: 10 | AV79: 13.3 | AW79: 13073 | AX79: 4928.521 | AY79: M1 | AZ79: FALSO ALQUILER | BA79: =+IF(Tabla467824[[#This Row],[TIPO VEHÍCULO]]=Tabla467824[[#This Row],[Columna2]], "IGUAL", "DISTINTO") -> IGUAL | BB79: =+IF(Tabla467824[[#This Row],[Columna4]]=Tabla467824[[#This Row],[Combustible2]], "IGUAL", "DISTINTO") -> IGUAL | BC79: CAE500114 | BD79: {=IFERROR(INDEX('[1]Anexos FICHA TRA050'!$D$27:$D$44, MATCH(Tabla467824[[#This Row],[Columna5]]&Tabla467824[[#This Row],[Columna4]], '[1]Anexos FICHA TRA050'!$E$27:$E$44&'[1]Anexos FICHA TRA050'!$F$27:$F$44, 0)), "")} -> 6.99 | BE79: =IFERROR(INDEX('[1]Anexos FICHA TRA050'!$B$4:$B$7, MATCH(Tabla467824[[#This Row],[Columna4]], '[1]Anexos FICHA TRA050'!$C$4:$C$7, 0)), "") -> 10 | BF79: =IFERROR(INDEX('[1]Anexos FICHA TRA050'!$C$14:$C$22, MATCH(Tabla467824[[#This Row],[Columna5]], '[1]Anexos FICHA TRA050'!$D$14:$D$22, 0)), "") -> 17.92 | BG79: =IFERROR(INDEX('[1]Anexos FICHA TRA050'!$C$49:$C$54, MATCH(Tabla467824[[#This Row],[Columna5]], '[1]Anexos FICHA TRA050'!$D$49:$D$54, 0)), "") -> 13073 | BH79: =+(((Tabla467824[[#This Row],[CVA2]]*Tabla467824[[#This Row],[f2]])-Tabla467824[[#This Row],[CVN2]])/100)*Tabla467824[[#This Row],[L2]] -> 6795.3454 | BK79: =+IF(Tabla467824[[#This Row],[F]]=Tabla467824[[#This Row],[f2]], "IGUAL", "DISTINTO") -> IGUAL | BL79: =+IF(Tabla467824[[#This Row],[CVN]]=Tabla467824[[#This Row],[CVN2]], "IGUAL", "DISTINTO") -> DISTINTO | BM79: =+IF(Tabla467824[[#This Row],[L]]=Tabla467824[[#This Row],[L2]], "IGUAL", "DISTINTO") -> IGUAL
A80: 77 | B80: CAE500115 | C80: 8170LCK | D80: N1 | E80: DIESEL | F80: DIESEL | G80: N1 | H80: X | J80: X | L80: X | M80: X | O80: TLM | P80: 3 | Q80: ALQUILER | R80: DEVUELTO | S80: 45002 | T80: 45307 | U80: 305 | V80: 2024 | W80: 7 | X80: DIESEL | Y80: PEUGEOT | Z80: EXPERT 1.5 HDI 102 CV | AA80: 1066 | AB80: CANALIZ. CIVILES S.A. | AC80: 306050 | AD80: 8 | AE80: 8636MWT | AF80: RENAULT | AG80: KANGOO VAN E-TECH ELECTRIC | AH80: ELECTRICO | AI80: 10669109 | AJ80: 2024 | AK80: 45625 | AL80: 0 | AM80: 1066 | AN80: 4500426780 | AO80: CANALIZ. CIVILES S.A. | AQ80: X | AR80: COMUNIDAD VALENCIANA | AS80: VF1RFK00073824816 | AT80: 5.6 | AU80: 10 | AV80: 17.3 | AW80: 15815 | AX80: 6120.405 | AY80: N1 | AZ80: CORRECTO ALQUILER | BA80: =+IF(Tabla467824[[#This Row],[TIPO VEHÍCULO]]=Tabla467824[[#This Row],[Columna2]], "IGUAL", "DISTINTO") -> IGUAL | BB80: =+IF(Tabla467824[[#This Row],[Columna4]]=Tabla467824[[#This Row],[Combustible2]], "IGUAL", "DISTINTO") -> IGUAL | BC80: CAE500115 | BD80: {=IFERROR(INDEX('[1]Anexos FICHA TRA050'!$D$27:$D$44, MATCH(Tabla467824[[#This Row],[Columna5]]&Tabla467824[[#This Row],[Columna4]], '[1]Anexos FICHA TRA050'!$E$27:$E$44&'[1]Anexos FICHA TRA050'!$F$27:$F$44, 0)), "")} -> 5.63 | BE80: =IFERROR(INDEX('[1]Anexos FICHA TRA050'!$B$4:$B$7, MATCH(Tabla467824[[#This Row],[Columna4]], '[1]Anexos FICHA TRA050'!$C$4:$C$7, 0)), "") -> 10 | BF80: =IFERROR(INDEX('[1]Anexos FICHA TRA050'!$C$14:$C$22, MATCH(Tabla467824[[#This Row],[Columna5]], '[1]Anexos FICHA TRA050'!$D$14:$D$22, 0)), "") -> 20.84 | BG80: =IFERROR(INDEX('[1]Anexos FICHA TRA050'!$C$49:$C$54, MATCH(Tabla467824[[#This Row],[Columna5]], '[1]Anexos FICHA TRA050'!$D$49:$D$54, 0)), "") -> 15815 | BH80: =+(((Tabla467824[[#This Row],[CVA2]]*Tabla467824[[#This Row],[f2]])-Tabla467824[[#This Row],[CVN2]])/100)*Tabla467824[[#This Row],[L2]] -> 5607.999 | BK80: =+IF(Tabla467824[[#This Row],[F]]=Tabla467824[[#This Row],[f2]], "IGUAL", "DISTINTO") -> IGUAL | BL80: =+IF(Tabla467824[[#This Row],[CVN]]=Tabla467824[[#This Row],[CVN2]], "IGUAL", "DISTINTO") -> DISTINTO | BM80: =+IF(Tabla467824[[#This Row],[L]]=Tabla467824[[#This Row],[L2]], "IGUAL", "DISTINTO") -> IGUAL
A81: 78 | B81: CAE500116 | C81: 3310MDB | D81: N1 | E81: DIESEL | F81: DIESEL | G81: N1 | H81: X | I81: X | J81: X | L81: X | M81: X | O81: AYVENS | P81: 3 | Q81: ALQUILER | R81: DEVUELTO | S81: 45323 | T81: 45468 | U81: 145 | V81: 2024 | W81: 7 | X81: DIESEL | Y81: RENAULT | Z81: EXPRESS 1.5 DCI 95 CV | AA81: 1505 | AB81: CGAC | AC81: 725496 | AD81: 19 | AE81: 6445MWV | AF81: CITROEN | AG81: Ë-C3 ELÉCTRICO MAX | AH81: ELECTRICO | AI81: 205567 | AJ81: 2024 | AK81: 45625 | AL81: 0 | AM81: 1505 | AN81: 4500424838 | AO81: CGAC | AQ81: X | AR81: CATALUÑA | AS81: VR7CBZYAXRT153017 | AT81: 5.6 | AU81: 10 | AV81: 16.4 | AW81: 15815 | AX81: 6262.74 | AY81: N1 | AZ81: CORRECTO ALQUILER | BA81: =+IF(Tabla467824[[#This Row],[TIPO VEHÍCULO]]=Tabla467824[[#This Row],[Columna2]], "IGUAL", "DISTINTO") -> IGUAL | BB81: =+IF(Tabla467824[[#This Row],[Columna4]]=Tabla467824[[#This Row],[Combustible2]], "IGUAL", "DISTINTO") -> IGUAL | BC81: CAE500116 | BD81: {=IFERROR(INDEX('[1]Anexos FICHA TRA050'!$D$27:$D$44, MATCH(Tabla467824[[#This Row],[Columna5]]&Tabla467824[[#This Row],[Columna4]], '[1]Anexos FICHA TRA050'!$E$27:$E$44&'[1]Anexos FICHA TRA050'!$F$27:$F$44, 0)), "")} -> 5.63 | BE81: =IFERROR(INDEX('[1]Anexos FICHA TRA050'!$B$4:$B$7, MATCH(Tabla467824[[#This Row],[Columna4]], '[1]Anexos FICHA TRA050'!$C$4:$C$7, 0)), "") -> 10 | BF81: =IFERROR(INDEX('[1]Anexos FICHA TRA050'!$C$14:$C$22, MATCH(Tabla467824[[#This Row],[Columna5]], '[1]Anexos FICHA TRA050'!$D$14:$D$22, 0)), "") -> 20.84 | BG81: =IFERROR(INDEX('[1]Anexos FICHA TRA050'!$C$49:$C$54, MATCH(Tabla467824[[#This Row],[Columna5]], '[1]Anexos FICHA TRA050'!$D$49:$D$54, 0)), "") -> 15815 | BH81: =+(((Tabla467824[[#This Row],[CVA2]]*Tabla467824[[#This Row],[f2]])-Tabla467824[[#This Row],[CVN2]])/100)*Tabla467824[[#This Row],[L2]] -> 5607.999 | BK81: =+IF(Tabla467824[[#This Row],[F]]=Tabla467824[[#This Row],[f2]], "IGUAL", "DISTINTO") -> IGUAL | BL81: =+IF(Tabla467824[[#This Row],[CVN]]=Tabla467824[[#This Row],[CVN2]], "IGUAL", "DISTINTO") -> DISTINTO | BM81: =+IF(Tabla467824[[#This Row],[L]]=Tabla467824[[#This Row],[L2]], "IGUAL", "DISTINTO") -> IGUAL
A82: 79 | B82: CAE500117 | C82: 1722MGL | D82: N1 | E82: DIESEL | F82: DIESEL | G82: N1 | H82: X | I82: X | J82: X | L82: X | M82: X | O82: AYVENS | P82: 3 | Q82: ALQUILER | R82: DEVUELTO | S82: 45323 | T82: 45433 | U82: 110 | V82: 2024 | W82: 7 | X82: DIESEL | Y82: RENAULT | Z82: EXPRESS 1.5 DCI 95 CV | AA82: 1505 | AB82: CGAC | AC82: 725496 | AD82: 20 | AE82: 5020MWL | AF82: NISSAN | AG82: TOWNSTAR | AH82: ELECTRICO | AI82: 205337 | AJ82: 2024 | AK82: 45616 | AL82: 0 | AM82: 1505 | AN82: 4500423385 | AO82: CGAC | AQ82: X | AR82: CATALUÑA | AS82: VNVNFK00571491969 | AT82: 5.6 | AU82: 10 | AV82: 20 | AW82: 15815 | AX82: 5693.4 | AY82: N1 | AZ82: CORRECTO ALQUILER | BA82: =+IF(Tabla467824[[#This Row],[TIPO VEHÍCULO]]=Tabla467824[[#This Row],[Columna2]], "IGUAL", "DISTINTO") -> IGUAL | BB82: =+IF(Tabla467824[[#This Row],[Columna4]]=Tabla467824[[#This Row],[Combustible2]], "IGUAL", "DISTINTO") -> IGUAL | BC82: CAE500117 | BD82: {=IFERROR(INDEX('[1]Anexos FICHA TRA050'!$D$27:$D$44, MATCH(Tabla467824[[#This Row],[Columna5]]&Tabla467824[[#This Row],[Columna4]], '[1]Anexos FICHA TRA050'!$E$27:$E$44&'[1]Anexos FICHA TRA050'!$F$27:$F$44, 0)), "")} -> 5.63 | BE82: =IFERROR(INDEX('[1]Anexos FICHA TRA050'!$B$4:$B$7, MATCH(Tabla467824[[#This Row],[Columna4]], '[1]Anexos FICHA TRA050'!$C$4:$C$7, 0)), "") -> 10 | BF82: =IFERROR(INDEX('[1]Anexos FICHA TRA050'!$C$14:$C$22, MATCH(Tabla467824[[#This Row],[Columna5]], '[1]Anexos FICHA TRA050'!$D$14:$D$22, 0)), "") -> 20.84 | BG82: =IFERROR(INDEX('[1]Anexos FICHA TRA050'!$C$49:$C$54, MATCH(Tabla467824[[#This Row],[Columna5]], '[1]Anexos FICHA TRA050'!$D$49:$D$54, 0)), "") -> 15815 | BH82: =+(((Tabla467824[[#This Row],[CVA2]]*Tabla467824[[#This Row],[f2]])-Tabla467824[[#This Row],[CVN2]])/100)*Tabla467824[[#This Row],[L2]] -> 5607.999 | BK82: =+IF(Tabla467824[[#This Row],[F]]=Tabla467824[[#This Row],[f2]], "IGUAL", "DISTINTO") -> IGUAL | BL82: =+IF(Tabla467824[[#This Row],[CVN]]=Tabla467824[[#This Row],[CVN2]], "IGUAL", "DISTINTO") -> DISTINTO | BM82: =+IF(Tabla467824[[#This Row],[L]]=Tabla467824[[#This Row],[L2]], "IGUAL", "DISTINTO") -> IGUAL
A83: 80 | B83: CAE500119 | C83: 8677MGK | D83: N1 | E83: DIESEL | F83: DIESEL | G83: N1 | H83: X | I83: X | J83: X | L83: X | M83: X | O83: AYVENS | P83: 3 | Q83: ALQUILER | R83: DEVUELTO | S83: 45323 | T83: 45504 | U83: 181 | V83: 2024 | W83: 7 | X83: DIESEL | Y83: RENAULT | Z83: EXPRESS 1.5 DCI 95 CV | AA83: 1505 | AB83: CGAC | AC83: 725400 | AD83: 21 | AE83: 6847MWL | AF83: NISSAN | AG83: TOWNSTAR | AH83: ELECTRICO | AI83: 205337 | AJ83: 2024 | AK83: 45616 | AL83: 0 | AM83: 1505 | AN83: 4500423384 | AO83: CGAC | AQ83: X | AR83: CATALUÑA | AS83: VNVNFK00171491399 | AT83: 5.6 | AU83: 10 | AV83: 20 | AW83: 15815 | AX83: 5693.4 | AY83: N1 | AZ83: CORRECTO ALQUILER | BA83: =+IF(Tabla467824[[#This Row],[TIPO VEHÍCULO]]=Tabla467824[[#This Row],[Columna2]], "IGUAL", "DISTINTO") -> IGUAL | BB83: =+IF(Tabla467824[[#This Row],[Columna4]]=Tabla467824[[#This Row],[Combustible2]], "IGUAL", "DISTINTO") -> IGUAL | BC83: CAE500119 | BD83: {=IFERROR(INDEX('[1]Anexos FICHA TRA050'!$D$27:$D$44, MATCH(Tabla467824[[#This Row],[Columna5]]&Tabla467824[[#This Row],[Columna4]], '[1]Anexos FICHA TRA050'!$E$27:$E$44&'[1]Anexos FICHA TRA050'!$F$27:$F$44, 0)), "")} -> 5.63 | BE83: =IFERROR(INDEX('[1]Anexos FICHA TRA050'!$B$4:$B$7, MATCH(Tabla467824[[#This Row],[Columna4]], '[1]Anexos FICHA TRA050'!$C$4:$C$7, 0)), "") -> 10 | BF83: =IFERROR(INDEX('[1]Anexos FICHA TRA050'!$C$14:$C$22, MATCH(Tabla467824[[#This Row],[Columna5]], '[1]Anexos FICHA TRA050'!$D$14:$D$22, 0)), "") -> 20.84 | BG83: =IFERROR(INDEX('[1]Anexos FICHA TRA050'!$C$49:$C$54, MATCH(Tabla467824[[#This Row],[Columna5]], '[1]Anexos FICHA TRA050'!$D$49:$D$54, 0)), "") -> 15815 | BH83: =+(((Tabla467824[[#This Row],[CVA2]]*Tabla467824[[#This Row],[f2]])-Tabla467824[[#This Row],[CVN2]])/100)*Tabla467824[[#This Row],[L2]] -> 5607.999 | BK83: =+IF(Tabla467824[[#This Row],[F]]=Tabla467824[[#This Row],[f2]], "IGUAL", "DISTINTO") -> IGUAL | BL83: =+IF(Tabla467824[[#This Row],[CVN]]=Tabla467824[[#This Row],[CVN2]], "IGUAL", "DISTINTO") -> DISTINTO | BM83: =+IF(Tabla467824[[#This Row],[L]]=Tabla467824[[#This Row],[L2]], "IGUAL", "DISTINTO") -> IGUAL
A84: 81 | B84: CAE500120 | C84: 2502LZC | D84: N1 | E84: DIESEL | F84: DIESEL | G84: N1 | H84: X | J84: X | L84: X | M84: X | O84: AYVENS | P84: 3 | Q84: ALQUILER | R84: DEVUELTO | S84: 45324 | T84: 45372 | U84: 48 | V84: 2024 | W84: 7 | X84: DIESEL | Y84: RENAULT | Z84: EXPRESS 1.5 DCI 95 CV | AA84: 1505 | AB84: CGAC | AC84: 205337 | AD84: 22 | AE84: 8539MDK | AF84: RENAULT | AG84: KANGOO VAN E-TECH | AH84: ELECTRICO | AI84: 725465 | AJ84: 2023 | AK84: 44945 | AL84: -1 | AM84: 1505 | AN84: 4500351523 | AO84: CGAC | AQ84: X | AR84: CATALUÑA | AS84: VF1RFK00170026505 | AT84: 5.6 | AU84: 10 | AV84: 17.3 | AW84: 15815 | AX84: 6120.405 | AY84: N1 | AZ84: CORRECTO ALQUILER | BA84: =+IF(Tabla467824[[#This Row],[TIPO VEHÍCULO]]=Tabla467824[[#This Row],[Columna2]], "IGUAL", "DISTINTO") -> IGUAL | BB84: =+IF(Tabla467824[[#This Row],[Columna4]]=Tabla467824[[#This Row],[Combustible2]], "IGUAL", "DISTINTO") -> IGUAL | BC84: CAE500120 | BD84: {=IFERROR(INDEX('[1]Anexos FICHA TRA050'!$D$27:$D$44, MATCH(Tabla467824[[#This Row],[Columna5]]&Tabla467824[[#This Row],[Columna4]], '[1]Anexos FICHA TRA050'!$E$27:$E$44&'[1]Anexos FICHA TRA050'!$F$27:$F$44, 0)), "")} -> 5.63 | BE84: =IFERROR(INDEX('[1]Anexos FICHA TRA050'!$B$4:$B$7, MATCH(Tabla467824[[#This Row],[Columna4]], '[1]Anexos FICHA TRA050'!$C$4:$C$7, 0)), "") -> 10 | BF84: =IFERROR(INDEX('[1]Anexos FICHA TRA050'!$C$14:$C$22, MATCH(Tabla467824[[#This Row],[Columna5]], '[1]Anexos FICHA TRA050'!$D$14:$D$22, 0)), "") -> 20.84 | BG84: =IFERROR(INDEX('[1]Anexos FICHA TRA050'!$C$49:$C$54, MATCH(Tabla467824[[#This Row],[Columna5]], '[1]Anexos FICHA TRA050'!$D$49:$D$54, 0)), "") -> 15815 | BH84: =+(((Tabla467824[[#This Row],[CVA2]]*Tabla467824[[#This Row],[f2]])-Tabla467824[[#This Row],[CVN2]])/100)*Tabla467824[[#This Row],[L2]] -> 5607.999 | BK84: =+IF(Tabla467824[[#This Row],[F]]=Tabla467824[[#This Row],[f2]], "IGUAL", "DISTINTO") -> IGUAL | BL84: =+IF(Tabla467824[[#This Row],[CVN]]=Tabla467824[[#This Row],[CVN2]], "IGUAL", "DISTINTO") -> DISTINTO | BM84: =+IF(Tabla467824[[#This Row],[L]]=Tabla467824[[#This Row],[L2]], "IGUAL", "DISTINTO") -> IGUAL
A85: 82 | B85: CAE500121 | C85: 2842LYK | D85: N1 | E85: DIESEL | F85: DIESEL | G85: N1 | H85: X | J85: X | L85: X | M85: X | O85: AYVENS | P85: 3 | Q85: ALQUILER | R85: DEVUELTO | S85: 45324 | T85: 45372 | U85: 48 | V85: 2024 | W85: 7 | X85: DIESEL | Y85: RENAULT | Z85: EXPRESS 1.5 DCI 95 CV | AA85: 1505 | AB85: CGAC | AC85: 205337 | AD85: 23 | AE85: 8533MDK | AF85: RENAULT | AG85: KANGOO VAN E-TECH | AH85: ELECTRICO | AI85: 725465 | AJ85: 2023 | AK85: 44945 | AL85: -1 | AM85: 1505 | AN85: 4500351522 | AO85: CGAC | AQ85: X | AR85: CATALUÑA | AS85: VF1RFK00370026442 | AT85: 5.6 | AU85: 10 | AV85: 17.3 | AW85: 15815 | AX85: 6120.405 | AY85: N1 | AZ85: CORRECTO ALQUILER | BA85: =+IF(Tabla467824[[#This Row],[TIPO VEHÍCULO]]=Tabla467824[[#This Row],[Columna2]], "IGUAL", "DISTINTO") -> IGUAL | BB85: =+IF(Tabla467824[[#This Row],[Columna4]]=Tabla467824[[#This Row],[Combustible2]], "IGUAL", "DISTINTO") -> IGUAL | BC85: CAE500121 | BD85: {=IFERROR(INDEX('[1]Anexos FICHA TRA050'!$D$27:$D$44, MATCH(Tabla467824[[#This Row],[Columna5]]&Tabla467824[[#This Row],[Columna4]], '[1]Anexos FICHA TRA050'!$E$27:$E$44&'[1]Anexos FICHA TRA050'!$F$27:$F$44, 0)), "")} -> 5.63 | BE85: =IFERROR(INDEX('[1]Anexos FICHA TRA050'!$B$4:$B$7, MATCH(Tabla467824[[#This Row],[Columna4]], '[1]Anexos FICHA TRA050'!$C$4:$C$7, 0)), "") -> 10 | BF85: =IFERROR(INDEX('[1]Anexos FICHA TRA050'!$C$14:$C$22, MATCH(Tabla467824[[#This Row],[Columna5]], '[1]Anexos FICHA TRA050'!$D$14:$D$22, 0)), "") -> 20.84 | BG85: =IFERROR(INDEX('[1]Anexos FICHA TRA050'!$C$49:$C$54, MATCH(Tabla467824[[#This Row],[Columna5]], '[1]Anexos FICHA TRA050'!$D$49:$D$54, 0)), "") -> 15815 | BH85: =+(((Tabla467824[[#This Row],[CVA2]]*Tabla467824[[#This Row],[f2]])-Tabla467824[[#This Row],[CVN2]])/100)*Tabla467824[[#This Row],[L2]] -> 5607.999 | BK85: =+IF(Tabla467824[[#This Row],[F]]=Tabla467824[[#This Row],[f2]], "IGUAL", "DISTINTO") -> IGUAL | BL85: =+IF(Tabla467824[[#This Row],[CVN]]=Tabla467824[[#This Row],[CVN2]], "IGUAL", "DISTINTO") -> DISTINTO | BM85: =+IF(Tabla467824[[#This Row],[L]]=Tabla467824[[#This Row],[L2]], "IGUAL", "DISTINTO") -> IGUAL
A86: 83 | B86: CAE500122 | C86: 3264MDB | D86: N1 | E86: DIESEL | F86: DIESEL | G86: N1 | H86: X | I86: X | J86: X | L86: X | M86: X | O86: AYVENS | P86: 3 | Q86: ALQUILER | R86: DEVUELTO | S86: 45323 | T86: 45425 | U86: 102 | V86: 2024 | W86: 7 | X86: DIESEL | Y86: RENAULT | Z86: EXPRESS 1.5 DCI 95 CV | AA86: 1505 | AB86: CGAC | AC86: 725496 | AD86: 24 | AE86: 4073MXK | AF86: RENAULT | AG86: KANGOO VAN E-TECH ELECTRIC | AH86: ELECTRICO | AI86: 205584 | AJ86: 2024 | AK86: 45652 | AL86: 0 | AM86: 1505 | AN86: 4500426777 | AO86: CGAC | AQ86: X | AR86: CATALUÑA | AS86: VF1RFK00073824878 | AT86: 5.6 | AU86: 10 | AV86: 17.3 | AW86: 15815 | AX86: 6120.405 | AY86: N1 | AZ86: CORRECTO ALQUILER | BA86: =+IF(Tabla467824[[#This Row],[TIPO VEHÍCULO]]=Tabla467824[[#This Row],[Columna2]], "IGUAL", "DISTINTO") -> IGUAL | BB86: =+IF(Tabla467824[[#This Row],[Columna4]]=Tabla467824[[#This Row],[Combustible2]], "IGUAL", "DISTINTO") -> IGUAL | BC86: CAE500122 | BD86: {=IFERROR(INDEX('[1]Anexos FICHA TRA050'!$D$27:$D$44, MATCH(Tabla467824[[#This Row],[Columna5]]&Tabla467824[[#This Row],[Columna4]], '[1]Anexos FICHA TRA050'!$E$27:$E$44&'[1]Anexos FICHA TRA050'!$F$27:$F$44, 0)), "")} -> 5.63 | BE86: =IFERROR(INDEX('[1]Anexos FICHA TRA050'!$B$4:$B$7, MATCH(Tabla467824[[#This Row],[Columna4]], '[1]Anexos FICHA TRA050'!$C$4:$C$7, 0)), "") -> 10 | BF86: =IFERROR(INDEX('[1]Anexos FICHA TRA050'!$C$14:$C$22, MATCH(Tabla467824[[#This Row],[Columna5]], '[1]Anexos FICHA TRA050'!$D$14:$D$22, 0)), "") -> 20.84 | BG86: =IFERROR(INDEX('[1]Anexos FICHA TRA050'!$C$49:$C$54, MATCH(Tabla467824[[#This Row],[Columna5]], '[1]Anexos FICHA TRA050'!$D$49:$D$54, 0)), "") -> 15815 | BH86: =+(((Tabla467824[[#This Row],[CVA2]]*Tabla467824[[#This Row],[f2]])-Tabla467824[[#This Row],[CVN2]])/100)*Tabla467824[[#This Row],[L2]] -> 5607.999 | BK86: =+IF(Tabla467824[[#This Row],[F]]=Tabla467824[[#This Row],[f2]], "IGUAL", "DISTINTO") -> IGUAL | BL86: =+IF(Tabla467824[[#This Row],[CVN]]=Tabla467824[[#This Row],[CVN2]], "IGUAL", "DISTINTO") -> DISTINTO | BM86: =+IF(Tabla467824[[#This Row],[L]]=Tabla467824[[#This Row],[L2]], "IGUAL", "DISTINTO") -> IGUAL
A87: 84 | B87: CAE500123 | C87: 9778KJG | D87: M1 | E87: GLP | F87: GLP | G87: M1 | H87: X | J87: X | L87: x | M87: x | O87: AYVENS | P87: 1 | Q87: RENTING | R87: DEVUELTO | S87: 43182 | T87: 45008 | U87: 1826 | V87: 2023 | W87: 7 | X87: GLP | Y87: OPEL | Z87: CROSSLAND X 1.2 80 CV GLP | AA87: 1200 | AB87: EMIVASA | AC87: 200020 | AD87: 7 | AE87: 0213MWZ | AF87: CITROEN | AG87: Ë-C3 ELÉCTRICO MAX | AH87: ELECTRICO | AI87: 12009060 | AJ87: 2024 | AK87: 45637 | AL87: 1 | AM87: 1200 | AN87: 4500424867 | AO87: EMIVASA | AQ87: X | AR87: COMUNIDAD VALENCIANA | AS87: VR7CBZYA6RT153032 | AT87: 5.1 | AU87: 7.16 | AV87: 16.4 | AW87: 13073 | AX87: 2629.7647 | AY87: M1 | AZ87: CORRECTO ALQUILER | BA87: =+IF(Tabla467824[[#This Row],[TIPO VEHÍCULO]]=Tabla467824[[#This Row],[Columna2]], "IGUAL", "DISTINTO") -> IGUAL | BB87: =+IF(Tabla467824[[#This Row],[Columna4]]=Tabla467824[[#This Row],[Combustible2]], "IGUAL", "DISTINTO") -> IGUAL | BC87: CAE500123 | BD87: {=IFERROR(INDEX('[1]Anexos FICHA TRA050'!$D$27:$D$44, MATCH(Tabla467824[[#This Row],[Columna5]]&Tabla467824[[#This Row],[Columna4]], '[1]Anexos FICHA TRA050'!$E$27:$E$44&'[1]Anexos FICHA TRA050'!$F$27:$F$44, 0)), "")} -> 6.45 | BE87: =IFERROR(INDEX('[1]Anexos FICHA TRA050'!$B$4:$B$7, MATCH(Tabla467824[[#This Row],[Columna4]], '[1]Anexos FICHA TRA050'!$C$4:$C$7, 0)), "") -> 7.16 | BF87: =IFERROR(INDEX('[1]Anexos FICHA TRA050'!$C$14:$C$22, MATCH(Tabla467824[[#This Row],[Columna5]], '[1]Anexos FICHA TRA050'!$D$14:$D$22, 0)), "") -> 17.92 | BG87: =IFERROR(INDEX('[1]Anexos FICHA TRA050'!$C$49:$C$54, MATCH(Tabla467824[[#This Row],[Columna5]], '[1]Anexos FICHA TRA050'!$D$49:$D$54, 0)), "") -> 13073 | BH87: =+(((Tabla467824[[#This Row],[CVA2]]*Tabla467824[[#This Row],[f2]])-Tabla467824[[#This Row],[CVN2]])/100)*Tabla467824[[#This Row],[L2]] -> 3694.6913 | BK87: =+IF(Tabla467824[[#This Row],[F]]=Tabla467824[[#This Row],[f2]], "IGUAL", "DISTINTO") -> IGUAL | BL87: =+IF(Tabla467824[[#This Row],[CVN]]=Tabla467824[[#This Row],[CVN2]], "IGUAL", "DISTINTO") -> DISTINTO | BM87: =+IF(Tabla467824[[#This Row],[L]]=Tabla467824[[#This Row],[L2]], "IGUAL", "DISTINTO") -> IGUAL
A88: 85 | B88: CAE500125 | C88: 0842KVR | D88: M1 | E88: B/GLP | F88: GLP | G88: M1 | H88: X | I88: X | J88: X | L88: X | M88: X | O88: AYVENS | P88: 1 | Q88: RENTING | R88: DEVUELTO | S88: 43560 | T88: 45021 | U88: 1461 | V88: 2023 | W88: 7 | X88: GLP | Y88: OPEL | Z88: CROSSLAND X 1.2 80 CV GLP | AA88: 1200 | AB88: EMIVASA | AC88: 12009082 | AD88: 8 | AE88: 0224MWZ | AF88: CITROEN | AG88: Ë-C3 ELÉCTRICO MAX | AH88: ELECTRICO | AI88: 200020 | AJ88: 2024 | AK88: 45637 | AL88: 1 | AM88: 1200 | AN88: 4500424886 | AO88: EMIVASA | AQ88: X | AR88: COMUNIDAD VALENCIANA | AS88: VR7CBZYA2RT153027 | AT88: 5.1 | AU88: 7.16 | AV88: 16.4 | AW88: 13073 | AX88: 2629.7647 | AY88: M1 | AZ88: CORRECTO ALQUILER | BA88: =+IF(Tabla467824[[#This Row],[TIPO VEHÍCULO]]=Tabla467824[[#This Row],[Columna2]], "IGUAL", "DISTINTO") -> IGUAL | BB88: =+IF(Tabla467824[[#This Row],[Columna4]]=Tabla467824[[#This Row],[Combustible2]], "IGUAL", "DISTINTO") -> IGUAL | BC88: CAE500125 | BD88: {=IFERROR(INDEX('[1]Anexos FICHA TRA050'!$D$27:$D$44, MATCH(Tabla467824[[#This Row],[Columna5]]&Tabla467824[[#This Row],[Columna4]], '[1]Anexos FICHA TRA050'!$E$27:$E$44&'[1]Anexos FICHA TRA050'!$F$27:$F$44, 0)), "")} -> 6.45 | BE88: =IFERROR(INDEX('[1]Anexos FICHA TRA050'!$B$4:$B$7, MATCH(Tabla467824[[#This Row],[Columna4]], '[1]Anexos FICHA TRA050'!$C$4:$C$7, 0)), "") -> 7.16 | BF88: =IFERROR(INDEX('[1]Anexos FICHA TRA050'!$C$14:$C$22, MATCH(Tabla467824[[#This Row],[Columna5]], '[1]Anexos FICHA TRA050'!$D$14:$D$22, 0)), "") -> 17.92 | BG88: =IFERROR(INDEX('[1]Anexos FICHA TRA050'!$C$49:$C$54, MATCH(Tabla467824[[#This Row],[Columna5]], '[1]Anexos FICHA TRA050'!$D$49:$D$54, 0)), "") -> 13073 | BH88: =+(((Tabla467824[[#This Row],[CVA2]]*Tabla467824[[#This Row],[f2]])-Tabla467824[[#This Row],[CVN2]])/100)*Tabla467824[[#This Row],[L2]] -> 3694.6913 | BK88: =+IF(Tabla467824[[#This Row],[F]]=Tabla467824[[#This Row],[f2]], "IGUAL", "DISTINTO") -> IGUAL | BL88: =+IF(Tabla467824[[#This Row],[CVN]]=Tabla467824[[#This Row],[CVN2]], "IGUAL", "DISTINTO") -> DISTINTO | BM88: =+IF(Tabla467824[[#This Row],[L]]=Tabla467824[[#This Row],[L2]], "IGUAL", "DISTINTO") -> IGUAL
A89: 86 | B89: CAE500126 | C89: 2316KZH | D89: M1 | E89: DIESEL | F89: DIESEL | G89: M1 | H89: X | I89: X | L89: X | M89: X | O89: AYVENS | P89: 1 | Q89: RENTING | R89: CANCELADO POR SINIESTRO | S89: 43685 | T89: 45512 | U89: 1827 | V89: 2024 | W89: 6 | X89: DIESEL | Y89: OPEL | Z89: CROSSLAND X 1.5 CDTI 102 CV | AA89: 1591 | AB89: EMP.MUN.SERVEIS PUBLICS | AC89: 201591 | AD89: 1 | AE89: 1428KDP | AF89: RENAULT | AG89: ZOE 40 | AH89: ELECTRICO | AI89: 201591 | AJ89: 2023 | AK89: 43019 | AL89: -1 | AM89: 1591 | AN89: 4500349877 | AO89: EMP.MUN.SERVEIS PUBLICS | AR89: CATALUÑA | AS89: VF1AGVYC059144786 | AT89: 5.1 | AU89: 10 | AV89: 13.3 | AW89: 13073 | AX89: 4928.521 | AY89: M1 | AZ89: FALSO ALQUILER | BA89: =+IF(Tabla467824[[#This Row],[TIPO VEHÍCULO]]=Tabla467824[[#This Row],[Columna2]], "IGUAL", "DISTINTO") -> IGUAL | BB89: =+IF(Tabla467824[[#This Row],[Columna4]]=Tabla467824[[#This Row],[Combustible2]], "IGUAL", "DISTINTO") -> IGUAL | BC89: CAE500126 | BD89: {=IFERROR(INDEX('[1]Anexos FICHA TRA050'!$D$27:$D$44, MATCH(Tabla467824[[#This Row],[Columna5]]&Tabla467824[[#This Row],[Columna4]], '[1]Anexos FICHA TRA050'!$E$27:$E$44&'[1]Anexos FICHA TRA050'!$F$27:$F$44, 0)), "")} -> 6.99 | BE89: =IFERROR(INDEX('[1]Anexos FICHA TRA050'!$B$4:$B$7, MATCH(Tabla467824[[#This Row],[Columna4]], '[1]Anexos FICHA TRA050'!$C$4:$C$7, 0)), "") -> 10 | BF89: =IFERROR(INDEX('[1]Anexos FICHA TRA050'!$C$14:$C$22, MATCH(Tabla467824[[#This Row],[Columna5]], '[1]Anexos FICHA TRA050'!$D$14:$D$22, 0)), "") -> 17.92 | BG89: =IFERROR(INDEX('[1]Anexos FICHA TRA050'!$C$49:$C$54, MATCH(Tabla467824[[#This Row],[Columna5]], '[1]Anexos FICHA TRA050'!$D$49:$D$54, 0)), "") -> 13073 | BH89: =+(((Tabla467824[[#This Row],[CVA2]]*Tabla467824[[#This Row],[f2]])-Tabla467824[[#This Row],[CVN2]])/100)*Tabla467824[[#This Row],[L2]] -> 6795.3454 | BK89: =+IF(Tabla467824[[#This Row],[F]]=Tabla467824[[#This Row],[f2]], "IGUAL", "DISTINTO") -> IGUAL | BL89: =+IF(Tabla467824[[#This Row],[CVN]]=Tabla467824[[#This Row],[CVN2]], "IGUAL", "DISTINTO") -> DISTINTO | BM89: =+IF(Tabla467824[[#This Row],[L]]=Tabla467824[[#This Row],[L2]], "IGUAL", "DISTINTO") -> IGUAL
A90: 87 | B90: CAE500127 | C90: 6909MPH | D90: N1 | E90: DIESEL | F90: DIESEL | G90: N1 | H90: X | I90: X | J90: X | L90: X | M90: X | O90: AYVENS | P90: 3 | Q90: ALQUILER | R90: DEVUELTO | S90: 45447 | T90: 45516 | U90: 69 | V90: 2024 | W90: 7 | X90: DIESEL | Y90: RENAULT | Z90: EXPRESS 1.5 DCI 95 CV | AA90: 1505 | AB90: CGAC | AC90: 725498 | AD90: 25 | AE90: 8597MWT | AF90: RENAULT | AG90: KANGOO VAN E-TECH ELECTRIC | AH90: ELECTRICO | AI90: 205571 | AJ90: 2024 | AK90: 45625 | AL90: 0 | AM90: 1505 | AN90: 4500426784 | AO90: CGAC | AQ90: X | AR90: CATALUÑA | AS90: VF1RFK00973824801 | AT90: 5.6 | AU90: 10 | AV90: 17.3 | AW90: 15815 | AX90: 6120.405 | AY90: N1 | AZ90: CORRECTO ALQUILER | BA90: =+IF(Tabla467824[[#This Row],[TIPO VEHÍCULO]]=Tabla467824[[#This Row],[Columna2]], "IGUAL", "DISTINTO") -> IGUAL | BB90: =+IF(Tabla467824[[#This Row],[Columna4]]=Tabla467824[[#This Row],[Combustible2]], "IGUAL", "DISTINTO") -> IGUAL | BC90: CAE500127 | BD90: {=IFERROR(INDEX('[1]Anexos FICHA TRA050'!$D$27:$D$44, MATCH(Tabla467824[[#This Row],[Columna5]]&Tabla467824[[#This Row],[Columna4]], '[1]Anexos FICHA TRA050'!$E$27:$E$44&'[1]Anexos FICHA TRA050'!$F$27:$F$44, 0)), "")} -> 5.63 | BE90: =IFERROR(INDEX('[1]Anexos FICHA TRA050'!$B$4:$B$7, MATCH(Tabla467824[[#This Row],[Columna4]], '[1]Anexos FICHA TRA050'!$C$4:$C$7, 0)), "") -> 10 | BF90: =IFERROR(INDEX('[1]Anexos FICHA TRA050'!$C$14:$C$22, MATCH(Tabla467824[[#This Row],[Columna5]], '[1]Anexos FICHA TRA050'!$D$14:$D$22, 0)), "") -> 20.84 | BG90: =IFERROR(INDEX('[1]Anexos FICHA TRA050'!$C$49:$C$54, MATCH(Tabla467824[[#This Row],[Columna5]], '[1]Anexos FICHA TRA050'!$D$49:$D$54, 0)), "") -> 15815 | BH90: =+(((Tabla467824[[#This Row],[CVA2]]*Tabla467824[[#This Row],[f2]])-Tabla467824[[#This Row],[CVN2]])/100)*Tabla467824[[#This Row],[L2]] -> 5607.999 | BK90: =+IF(Tabla467824[[#This Row],[F]]=Tabla467824[[#This Row],[f2]], "IGUAL", "DISTINTO") -> IGUAL | BL90: =+IF(Tabla467824[[#This Row],[CVN]]=Tabla467824[[#This Row],[CVN2]], "IGUAL", "DISTINTO") -> DISTINTO | BM90: =+IF(Tabla467824[[#This Row],[L]]=Tabla467824[[#This Row],[L2]], "IGUAL", "DISTINTO") -> IGUAL
A91: 88 | B91: CAE500128 | C91: 6937MPH | D91: N1 | E91: DIESEL | F91: DIESEL | G91: N1 | H91: X | I91: X | J91: X | L91: X | M91: X | O91: AYVENS | P91: 3 | Q91: ALQUILER | R91: DEVUELTO | S91: 45447 | T91: 45516 | U91: 69 | V91: 2024 | W91: 7 | X91: DIESEL | Y91: RENAULT | Z91: EXPRESS 1.5 DCI 95 CV | AA91: 1505 | AB91: CGAC | AC91: 725498 | AD91: 26 | AE91: 8601MWT | AF91: RENAULT | AG91: KANGOO VAN E-TECH ELECTRIC | AH91: ELECTRICO | AI91: 205335 | AJ91: 2024 | AK91: 45625 | AL91: 0 | AM91: 1505 | AN91: 4500426757 | AO91: CGAC | AQ91: X | AR91: CATALUÑA | AS91: VF1RFK00073824783 | AT91: 5.6 | AU91: 10 | AV91: 17.3 | AW91: 15815 | AX91: 6120.405 | AY91: N1 | AZ91: CORRECTO ALQUILER | BA91: =+IF(Tabla467824[[#This Row],[TIPO VEHÍCULO]]=Tabla467824[[#This Row],[Columna2]], "IGUAL", "DISTINTO") -> IGUAL | BB91: =+IF(Tabla467824[[#This Row],[Columna4]]=Tabla467824[[#This Row],[Combustible2]], "IGUAL", "DISTINTO") -> IGUAL | BC91: CAE500128 | BD91: {=IFERROR(INDEX('[1]Anexos FICHA TRA050'!$D$27:$D$44, MATCH(Tabla467824[[#This Row],[Columna5]]&Tabla467824[[#This Row],[Columna4]], '[1]Anexos FICHA TRA050'!$E$27:$E$44&'[1]Anexos FICHA TRA050'!$F$27:$F$44, 0)), "")} -> 5.63 | BE91: =IFERROR(INDEX('[1]Anexos FICHA TRA050'!$B$4:$B$7, MATCH(Tabla467824[[#This Row],[Columna4]], '[1]Anexos FICHA TRA050'!$C$4:$C$7, 0)), "") -> 10 | BF91: =IFERROR(INDEX('[1]Anexos FICHA TRA050'!$C$14:$C$22, MATCH(Tabla467824[[#This Row],[Columna5]], '[1]Anexos FICHA TRA050'!$D$14:$D$22, 0)), "") -> 20.84 | BG91: =IFERROR(INDEX('[1]Anexos FICHA TRA050'!$C$49:$C$54, MATCH(Tabla467824[[#This Row],[Columna5]], '[1]Anexos FICHA TRA050'!$D$49:$D$54, 0)), "") -> 15815 | BH91: =+(((Tabla467824[[#This Row],[CVA2]]*Tabla467824[[#This Row],[f2]])-Tabla467824[[#This Row],[CVN2]])/100)*Tabla467824[[#This Row],[L2]] -> 5607.999 | BK91: =+IF(Tabla467824[[#This Row],[F]]=Tabla467824[[#This Row],[f2]], "IGUAL", "DISTINTO") -> IGUAL | BL91: =+IF(Tabla467824[[#This Row],[CVN]]=Tabla467824[[#This Row],[CVN2]], "IGUAL", "DISTINTO") -> DISTINTO | BM91: =+IF(Tabla467824[[#This Row],[L]]=Tabla467824[[#This Row],[L2]], "IGUAL", "DISTINTO") -> IGUAL
A92: 89 | B92: CAE500129 | C92: 7017MPH | D92: N1 | E92: DIESEL | F92: DIESEL | G92: N1 | H92: X | I92: X | J92: X | L92: X | M92: X | O92: AYVENS | P92: 3 | Q92: ALQUILER | R92: DEVUELTO | S92: 45447 | T92: 45516 | U92: 69 | V92: 2024 | W92: 7 | X92: DIESEL | Y92: RENAULT | Z92: EXPRESS 1.5 DCI 95 CV | AA92: 1505 | AB92: CGAC | AC92: 725498 | AD92: 27 | AE92: 8603MWT | AF92: RENAULT | AG92: KANGOO VAN E-TECH ELECTRIC | AH92: ELECTRICO | AI92: 205335 | AJ92: 2024 | AK92: 45625 | AL92: 0 | AM92: 1505 | AN92: 4500426788 | AO92: CGAC | AQ92: X | AR92: CATALUÑA | AS92: VF1RFK00673824805 | AT92: 5.6 | AU92: 10 | AV92: 17.3 | AW92: 15815 | AX92: 6120.405 | AY92: N1 | AZ92: CORRECTO ALQUILER | BA92: =+IF(Tabla467824[[#This Row],[TIPO VEHÍCULO]]=Tabla467824[[#This Row],[Columna2]], "IGUAL", "DISTINTO") -> IGUAL | BB92: =+IF(Tabla467824[[#This Row],[Columna4]]=Tabla467824[[#This Row],[Combustible2]], "IGUAL", "DISTINTO") -> IGUAL | BC92: CAE500129 | BD92: {=IFERROR(INDEX('[1]Anexos FICHA TRA050'!$D$27:$D$44, MATCH(Tabla467824[[#This Row],[Columna5]]&Tabla467824[[#This Row],[Columna4]], '[1]Anexos FICHA TRA050'!$E$27:$E$44&'[1]Anexos FICHA TRA050'!$F$27:$F$44, 0)), "")} -> 5.63 | BE92: =IFERROR(INDEX('[1]Anexos FICHA TRA050'!$B$4:$B$7, MATCH(Tabla467824[[#This Row],[Columna4]], '[1]Anexos FICHA TRA050'!$C$4:$C$7, 0)), "") -> 10 | BF92: =IFERROR(INDEX('[1]Anexos FICHA TRA050'!$C$14:$C$22, MATCH(Tabla467824[[#This Row],[Columna5]], '[1]Anexos FICHA TRA050'!$D$14:$D$22, 0)), "") -> 20.84 | BG92: =IFERROR(INDEX('[1]Anexos FICHA TRA050'!$C$49:$C$54, MATCH(Tabla467824[[#This Row],[Columna5]], '[1]Anexos FICHA TRA050'!$D$49:$D$54, 0)), "") -> 15815 | BH92: =+(((Tabla467824[[#This Row],[CVA2]]*Tabla467824[[#This Row],[f2]])-Tabla467824[[#This Row],[CVN2]])/100)*Tabla467824[[#This Row],[L2]] -> 5607.999 | BK92: =+IF(Tabla467824[[#This Row],[F]]=Tabla467824[[#This Row],[f2]], "IGUAL", "DISTINTO") -> IGUAL | BL92: =+IF(Tabla467824[[#This Row],[CVN]]=Tabla467824[[#This Row],[CVN2]], "IGUAL", "DISTINTO") -> DISTINTO | BM92: =+IF(Tabla467824[[#This Row],[L]]=Tabla467824[[#This Row],[L2]], "IGUAL", "DISTINTO") -> IGUAL
A93: 90 | B93: CAE500130 | C93: 6901MPH | D93: N1 | E93: DIESEL | F93: DIESEL | G93: N1 | H93: X | I93: X | J93: X | L93: X | M93: X | O93: AYVENS | P93: 3 | Q93: ALQUILER | R93: DEVUELTO | S93: 45447 | T93: 45656 | U93: 209 | V93: 2024 | W93: 7 | X93: DIESEL | Y93: RENAULT | Z93: EXPRESS 1.5 DCI 95 CV | AA93: 1505 | AB93: CGAC | AC93: 725498 | AD93: 28 | AE93: 8617MWT | AF93: RENAULT | AG93: KANGOO VAN E-TECH ELECTRIC | AH93: ELECTRICO | AI93: 205327 | AJ93: 2024 | AK93: 45625 | AL93: 0 | AM93: 1505 | AN93: 4500426773 | AO93: CGAC | AQ93: X | AR93: CATALUÑA | AS93: VF1RFK00573824794 | AT93: 5.6 | AU93: 10 | AV93: 17.3 | AW93: 15815 | AX93: 6120.405 | AY93: N1 | AZ93: CORRECTO ALQUILER | BA93: =+IF(Tabla467824[[#This Row],[TIPO VEHÍCULO]]=Tabla467824[[#This Row],[Columna2]], "IGUAL", "DISTINTO") -> IGUAL | BB93: =+IF(Tabla467824[[#This Row],[Columna4]]=Tabla467824[[#This Row],[Combustible2]], "IGUAL", "DISTINTO") -> IGUAL | BC93: CAE500130 | BD93: {=IFERROR(INDEX('[1]Anexos FICHA TRA050'!$D$27:$D$44, MATCH(Tabla467824[[#This Row],[Columna5]]&Tabla467824[[#This Row],[Columna4]], '[1]Anexos FICHA TRA050'!$E$27:$E$44&'[1]Anexos FICHA TRA050'!$F$27:$F$44, 0)), "")} -> 5.63 | BE93: =IFERROR(INDEX('[1]Anexos FICHA TRA050'!$B$4:$B$7, MATCH(Tabla467824[[#This Row],[Columna4]], '[1]Anexos FICHA TRA050'!$C$4:$C$7, 0)), "") -> 10 | BF93: =IFERROR(INDEX('[1]Anexos FICHA TRA050'!$C$14:$C$22, MATCH(Tabla467824[[#This Row],[Columna5]], '[1]Anexos FICHA TRA050'!$D$14:$D$22, 0)), "") -> 20.84 | BG93: =IFERROR(INDEX('[1]Anexos FICHA TRA050'!$C$49:$C$54, MATCH(Tabla467824[[#This Row],[Columna5]], '[1]Anexos FICHA TRA050'!$D$49:$D$54, 0)), "") -> 15815 | BH93: =+(((Tabla467824[[#This Row],[CVA2]]*Tabla467824[[#This Row],[f2]])-Tabla467824[[#This Row],[CVN2]])/100)*Tabla467824[[#This Row],[L2]] -> 5607.999 | BK93: =+IF(Tabla467824[[#This Row],[F]]=Tabla467824[[#This Row],[f2]], "IGUAL", "DISTINTO") -> IGUAL | BL93: =+IF(Tabla467824[[#This Row],[CVN]]=Tabla467824[[#This Row],[CVN2]], "IGUAL", "DISTINTO") -> DISTINTO | BM93: =+IF(Tabla467824[[#This Row],[L]]=Tabla467824[[#This Row],[L2]], "IGUAL", "DISTINTO") -> IGUAL
A94: 91 | B94: CAE500131 | C94: 8497MPH | D94: N1 | E94: DIESEL | F94: DIESEL | G94: N1 | H94: X | L94: X | M94: X | O94: AYVENS | P94: 3 | Q94: ALQUILER | R94: DEVUELTO | S94: 45505 | T94: 45657 | U94: 152 | V94: 2024 | W94: 7 | X94: DIESEL | Y94: RENAULT | Z94: EXPRESS 1.5 DCI 95 CV | AA94: 1505 | AB94: CGAC | AC94: 355470 | AD94: 29 | AE94: 8618MWT | AF94: RENAULT | AG94: KANGOO VAN E-TECH ELECTRIC | AH94: ELECTRICO | AI94: 205567 | AJ94: 2024 | AK94: 45625 | AL94: 0 | AM94: 1505 | AN94: 4500426845 | AO94: CGAC | AQ94: X | AR94: CATALUÑA | AS94: VF1RFK00X73824807 | AT94: 5.6 | AU94: 10 | AV94: 17.3 | AW94: 15815 | AX94: 6120.405 | AY94: N1 | AZ94: FALSO ALQUILER | BA94: =+IF(Tabla467824[[#This Row],[TIPO VEHÍCULO]]=Tabla467824[[#This Row],[Columna2]], "IGUAL", "DISTINTO") -> IGUAL | BB94: =+IF(Tabla467824[[#This Row],[Columna4]]=Tabla467824[[#This Row],[Combustible2]], "IGUAL", "DISTINTO") -> IGUAL | BC94: CAE500131 | BD94: {=IFERROR(INDEX('[1]Anexos FICHA TRA050'!$D$27:$D$44, MATCH(Tabla467824[[#This Row],[Columna5]]&Tabla467824[[#This Row],[Columna4]], '[1]Anexos FICHA TRA050'!$E$27:$E$44&'[1]Anexos FICHA TRA050'!$F$27:$F$44, 0)), "")} -> 5.63 | BE94: =IFERROR(INDEX('[1]Anexos FICHA TRA050'!$B$4:$B$7, MATCH(Tabla467824[[#This Row],[Columna4]], '[1]Anexos FICHA TRA050'!$C$4:$C$7, 0)), "") -> 10 | BF94: =IFERROR(INDEX('[1]Anexos FICHA TRA050'!$C$14:$C$22, MATCH(Tabla467824[[#This Row],[Columna5]], '[1]Anexos FICHA TRA050'!$D$14:$D$22, 0)), "") -> 20.84 | BG94: =IFERROR(INDEX('[1]Anexos FICHA TRA050'!$C$49:$C$54, MATCH(Tabla467824[[#This Row],[Columna5]], '[1]Anexos FICHA TRA050'!$D$49:$D$54, 0)), "") -> 15815 | BH94: =+(((Tabla467824[[#This Row],[CVA2]]*Tabla467824[[#This Row],[f2]])-Tabla467824[[#This Row],[CVN2]])/100)*Tabla467824[[#This Row],[L2]] -> 5607.999 | BK94: =+IF(Tabla467824[[#This Row],[F]]=Tabla467824[[#This Row],[f2]], "IGUAL", "DISTINTO") -> IGUAL | BL94: =+IF(Tabla467824[[#This Row],[CVN]]=Tabla467824[[#This Row],[CVN2]], "IGUAL", "DISTINTO") -> DISTINTO | BM94: =+IF(Tabla467824[[#This Row],[L]]=Tabla467824[[#This Row],[L2]], "IGUAL", "DISTINTO") -> IGUAL
A95: 92 | B95: CAE500132 | C95: 5875KPY | D95: N1 | E95: DIESEL | F95: DIESEL | G95: N1 | H95: X | I95: X | J95: X | L95: x | M95: x | O95: NORTHGATE | P95: 3 | Q95: ALQUILER | R95: DEVUELTO | S95: 44958 | T95: 45107 | U95: 149 | V95: 2023 | W95: 7 | X95: DIESEL | Y95: FIAT | Z95: FIORINO 1.3 MULTIJET 80 CV | AA95: 1505 | AB95: CGAC | AC95: 725485 | AD95: 30 | AE95: 2340MGR | AF95: OPEL | AG95: VIVARO E-FURGON | AH95: ELECTRICO | AI95: 725465 | AJ95: 2023 | AK95: 45051 | AL95: 0 | AM95: 1505 | AN95: 4500351860 | AO95: CGAC | AQ95: X | AR95: CATALUÑA | AS95: VXEV1ZKXZPZ019575 | AT95: 5.6 | AU95: 10 | AV95: 28.1 | AW95: 15815 | AX95: 4412.385 | AY95: N1 | AZ95: CORRECTO ALQUILER | BA95: =+IF(Tabla467824[[#This Row],[TIPO VEHÍCULO]]=Tabla467824[[#This Row],[Columna2]], "IGUAL", "DISTINTO") -> IGUAL | BB95: =+IF(Tabla467824[[#This Row],[Columna4]]=Tabla467824[[#This Row],[Combustible2]], "IGUAL", "DISTINTO") -> IGUAL | BC95: CAE500132 | BD95: {=IFERROR(INDEX('[1]Anexos FICHA TRA050'!$D$27:$D$44, MATCH(Tabla467824[[#This Row],[Columna5]]&Tabla467824[[#This Row],[Columna4]], '[1]Anexos FICHA TRA050'!$E$27:$E$44&'[1]Anexos FICHA TRA050'!$F$27:$F$44, 0)), "")} -> 5.63 | BE95: =IFERROR(INDEX('[1]Anexos FICHA TRA050'!$B$4:$B$7, MATCH(Tabla467824[[#This Row],[Columna4]], '[1]Anexos FICHA TRA050'!$C$4:$C$7, 0)), "") -> 10 | BF95: =IFERROR(INDEX('[1]Anexos FICHA TRA050'!$C$14:$C$22, MATCH(Tabla467824[[#This Row],[Columna5]], '[1]Anexos FICHA TRA050'!$D$14:$D$22, 0)), "") -> 20.84 | BG95: =IFERROR(INDEX('[1]Anexos FICHA TRA050'!$C$49:$C$54, MATCH(Tabla467824[[#This Row],[Columna5]], '[1]Anexos FICHA TRA050'!$D$49:$D$54, 0)), "") -> 15815 | BH95: =+(((Tabla467824[[#This Row],[CVA2]]*Tabla467824[[#This Row],[f2]])-Tabla467824[[#This Row],[CVN2]])/100)*Tabla467824[[#This Row],[L2]] -> 5607.999 | BK95: =+IF(Tabla467824[[#This Row],[F]]=Tabla467824[[#This Row],[f2]], "IGUAL", "DISTINTO") -> IGUAL | BL95: =+IF(Tabla467824[[#This Row],[CVN]]=Tabla467824[[#This Row],[CVN2]], "IGUAL", "DISTINTO") -> DISTINTO | BM95: =+IF(Tabla467824[[#This Row],[L]]=Tabla467824[[#This Row],[L2]], "IGUAL", "DISTINTO") -> IGUAL
A96: 93 | B96: CAE500133 | C96: 0360KLY | D96: N1 | E96: DIESEL | F96: DIESEL | G96: N1 | H96: X | I96: X | J96: X | L96: X | M96: X | O96: AYVENS | P96: 3 | Q96: ALQUILER | R96: DEVUELTO | S96: 45282 | T96: 45321 | U96: 39 | V96: 2024 | W96: 7 | X96: DIESEL | Y96: RENAULT | Z96: KANGOO | AA96: 1021 | AB96: MEDICION AVANZADA CONTAD. | AC96: 357712 | AD96: 10 | AE96: 0693MWT | AF96: RENAULT | AG96: KANGOO VAN E-TECH ELECTRIC | AH96: ELECTRICO | AI96: 357706 | AJ96: 2024 | AK96: 45625 | AL96: 0 | AM96: 1021 | AN96: 4500426790 | AO96: MEDICION AVANZADA CONTAD. | AQ96: X | AR96: COMUNIDAD VALENCIANA | AS96: VF1RFK00873824837 | AT96: 5.6 | AU96: 10 | AV96: 17.3 | AW96: 15815 | AX96: 6120.405 | AY96: N1 | AZ96: CORRECTO ALQUILER | BA96: =+IF(Tabla467824[[#This Row],[TIPO VEHÍCULO]]=Tabla467824[[#This Row],[Columna2]], "IGUAL", "DISTINTO") -> IGUAL | BB96: =+IF(Tabla467824[[#This Row],[Columna4]]=Tabla467824[[#This Row],[Combustible2]], "IGUAL", "DISTINTO") -> IGUAL | BC96: CAE500133 | BD96: {=IFERROR(INDEX('[1]Anexos FICHA TRA050'!$D$27:$D$44, MATCH(Tabla467824[[#This Row],[Columna5]]&Tabla467824[[#This Row],[Columna4]], '[1]Anexos FICHA TRA050'!$E$27:$E$44&'[1]Anexos FICHA TRA050'!$F$27:$F$44, 0)), "")} -> 5.63 | BE96: =IFERROR(INDEX('[1]Anexos FICHA TRA050'!$B$4:$B$7, MATCH(Tabla467824[[#This Row],[Columna4]], '[1]Anexos FICHA TRA050'!$C$4:$C$7, 0)), "") -> 10 | BF96: =IFERROR(INDEX('[1]Anexos FICHA TRA050'!$C$14:$C$22, MATCH(Tabla467824[[#This Row],[Columna5]], '[1]Anexos FICHA TRA050'!$D$14:$D$22, 0)), "") -> 20.84 | BG96: =IFERROR(INDEX('[1]Anexos FICHA TRA050'!$C$49:$C$54, MATCH(Tabla467824[[#This Row],[Columna5]], '[1]Anexos FICHA TRA050'!$D$49:$D$54, 0)), "") -> 15815 | BH96: =+(((Tabla467824[[#This Row],[CVA2]]*Tabla467824[[#This Row],[f2]])-Tabla467824[[#This Row],[CVN2]])/100)*Tabla467824[[#This Row],[L2]] -> 5607.999 | BK96: =+IF(Tabla467824[[#This Row],[F]]=Tabla467824[[#This Row],[f2]], "IGUAL", "DISTINTO") -> IGUAL | BL96: =+IF(Tabla467824[[#This Row],[CVN]]=Tabla467824[[#This Row],[CVN2]], "IGUAL", "DISTINTO") -> DISTINTO | BM96: =+IF(Tabla467824[[#This Row],[L]]=Tabla467824[[#This Row],[L2]], "IGUAL", "DISTINTO") -> IGUAL
